Workbook

Sheet Reproting_ERPALIN
L1: Parametres | O1: Chiffre d'affaires | T1: Marge brute hors transport, hors frais amazon | Z1: Marge brute incluant transport, hors frais amazon | AF1: Marge brute incluant transport, incluant frais amazon
A2: Produit / Service | B2: SKU du produit | C2: Fournisseur | D2: Mois,année | E2: Quantité | F2: Total HT | G2: Coût de livraison HT | H2: Bénéfice | I2: Taux de marque | J2: Livraison: Pays | K2: Référence externe | L2: Mois | M2: Année | N2: Date en nombre | O2: CA unitaire, hors transport | P2: CA ligne de produit, hors transport | Q2: CA unitaire transport HT | R2: CA unitaire, avec transport | S2: CA ligne produit, avec transport | T2: COGS unitaire, hors transport | U2: Marge brute unitaire, hors cout de transport | V2: Marge brute ligne produit, hors cout de transport | W2: GLS | X2: SCHENKER | Y2: GOFO | Z2: Total transport par commande (€) | AA2: Coût de transport par ligne de produit HT | AB2: Coût de transport unitaire HT | AC2: Marge unitaire incluant transport (€ HT) | AD2: Taux de marge, incluant transport (%) | AE2: Marge ligne de produit incluant transport, hors amazon, HT | AF2: Frais amazon par commande HT | AG2: Frais amazon par ligne de produit HT | AH2: Frais amazon unitaire HT | AI2: Marge incluant transport et frais amazon (€ HT) | AJ2: Marge incluant transport et frais amazon (%) | AK2: Marge ligne produit incluant transport et frais amazon (€ HT)
A3: Abena - Couches adulte intraversables Maternity Pad Super - Sachet de 15 pièces | B3: 1000022654 | C3: Abena | D3: 2026-01-01 | E3: 30 | F3: 14.79 | G3: 0 | H3: 10.55 | I3: 71.3 | J3: FR | K3: 408-9873588-3982738 | L3: =MONTH(D3) -> 1 | M3: =YEAR(D3) -> 2026 | N3: =D3*1 -> 46023 | O3: =F3/E3 -> 0.493 | P3: =O3*E3 -> 14.79 | Q3: =G3/E3 -> 0 | R3: =O3+Q3 -> 0.493 | S3: =R3*E3 -> 14.79 | T3: =-(F3-H3)/E3 -> -0.14133333 | U3: =R3+T3 -> 0.35166667 | V3: =U3*E3 -> 10.55 | W3: =SUMIF(GLS!B:B,K3,GLS!C:C) -> 5.48 | Z3: =-IF(W3+X3+Y3=0,"à vérifier",W3+X3+Y3) -> -5.48 | AA3: =IFERROR((SUMIF($K:$K,K3,$Z:$Z)/COUNTIF($K:$K,K3))*E3/SUMIF($K:$K,K3,$E:$E),0) -> -5.48 | AB3: =AA3/E3 -> -0.18266667 | AC3: =AB3+U3 -> 0.169 | AD3: =AC3/R3 -> 0.34279919 | AE3: =AC3*E3 -> 5.07 | AF3: =IFERROR(-ABS(INDEX('frais amazon 011225-150326'!H:H,MATCH(Reproting_ERPALIN!K3,'frais amazon 011225-150326'!D:D,0))/1.2),"Commande hors la France") -> -2.75 | AG3: =IFERROR(AF3*E3/SUMIF($K:$K,K3,$E:$E),0) -> -2.75 | AH3: =AG3/E3 -> -0.091666667 | AI3: =AH3+AC3 -> 0.077333333 | AJ3: =AI3/R3 -> 0.15686275 | AK3: =AI3*E3 -> 2.32
A4: Aiguille hypodermique à usage unique non sécurisée 21G, 0,8 mm x 50 mm | B4: IN-08X50 | C4: ZARYS International Group sp. z o.o. sp.k. | D4: 2026-01-01 | E4: 100 | F4: 12.98 | G4: 4.99 | H4: 11.52 | I4: 88.75 | J4: FR | K4: 408-9840795-1860306 | L4: =MONTH(D4) -> 1 | M4: =YEAR(D4) -> 2026 | N4: =D4*1 -> 46023 | O4: =F4/E4 -> 0.1298 | P4: =O4*E4 -> 12.98 | Q4: =G4/E4 -> 0.0499 | R4: =O4+Q4 -> 0.1797 | S4: =R4*E4 -> 17.97 | T4: =-(F4-H4)/E4 -> -0.0146 | U4: =R4+T4 -> 0.1651 | V4: =U4*E4 -> 16.51 | W4: =SUMIF(GLS!B:B,K4,GLS!C:C) -> 5.25 | Z4: =-IF(W4+X4+Y4=0,"à vérifier",W4+X4+Y4) -> -5.25 | AA4: =IFERROR((SUMIF($K:$K,K4,$Z:$Z)/COUNTIF($K:$K,K4))*E4/SUMIF($K:$K,K4,$E:$E),0) -> -5.25 | AB4: =AA4/E4 -> -0.0525 | AC4: =AB4+U4 -> 0.1126 | AD4: =AC4/R4 -> 0.62659989 | AE4: =AC4*E4 -> 11.26 | AF4: =IFERROR(-ABS(INDEX('frais amazon 011225-150326'!H:H,MATCH(Reproting_ERPALIN!K4,'frais amazon 011225-150326'!D:D,0))/1.2),"Commande hors la France") -> -3.3416667 | AG4: =IFERROR(AF4*E4/SUMIF($K:$K,K4,$E:$E),0) -> -3.3416667 | AH4: =AG4/E4 -> -0.033416667 | AI4: =AH4+AC4 -> 0.079183333 | AJ4: =AI4/R4 -> 0.44064181 | AK4: =AI4*E4 -> 7.9183333
A5: Aiguille hypodermique à usage unique non sécurisée 25G, 0,5 mm x 40 mm | B5: IN-05X40 | C5: ZARYS International Group sp. z o.o. sp.k. | D5: 2025-12-01 | E5: 200 | F5: 21.44 | G5: 4.99 | H5: 19.7 | I5: 91.88 | J5: FR | K5: 408-9832920-5794725 | L5: =MONTH(D5) -> 12 | M5: =YEAR(D5) -> 2025 | N5: =D5*1 -> 45992 | O5: =F5/E5 -> 0.1072 | P5: =O5*E5 -> 21.44 | Q5: =G5/E5 -> 0.02495 | R5: =O5+Q5 -> 0.13215 | S5: =R5*E5 -> 26.43 | T5: =-(F5-H5)/E5 -> -0.0087 | U5: =R5+T5 -> 0.12345 | V5: =U5*E5 -> 24.69 | W5: =SUMIF(GLS!B:B,K5,GLS!C:C) -> 5.25 | Z5: =-IF(W5+X5+Y5=0,"à vérifier",W5+X5+Y5) -> -5.25 | AA5: =IFERROR((SUMIF($K:$K,K5,$Z:$Z)/COUNTIF($K:$K,K5))*E5/SUMIF($K:$K,K5,$E:$E),0) -> -5.25 | AB5: =AA5/E5 -> -0.02625 | AC5: =AB5+U5 -> 0.0972 | AD5: =AC5/R5 -> 0.73552781 | AE5: =AC5*E5 -> 19.44 | AF5: =IFERROR(-ABS(INDEX('frais amazon 011225-150326'!H:H,MATCH(Reproting_ERPALIN!K5,'frais amazon 011225-150326'!D:D,0))/1.2),"Commande hors la France") -> -4.9083333 | AG5: =IFERROR(AF5*E5/SUMIF($K:$K,K5,$E:$E),0) -> -4.9083333 | AH5: =AG5/E5 -> -0.024541667 | AI5: =AH5+AC5 -> 0.072658333 | AJ5: =AI5/R5 -> 0.54981713 | AK5: =AI5*E5 -> 14.531667
A6: Seringue 3 pièces luer lock stérile 10ml, (Boite de 100 pièces) | B6: CH03010LL | C6: Vitrex Medical | D6: 2026-01-01 | E6: 1600 | F6: 210.72 | G6: 0 | H6: 117.92 | I6: 55.96 | J6: FR | K6: 408-9774002-0419541 | L6: =MONTH(D6) -> 1 | M6: =YEAR(D6) -> 2026 | N6: =D6*1 -> 46023 | O6: =F6/E6 -> 0.1317 | P6: =O6*E6 -> 210.72 | Q6: =G6/E6 -> 0 | R6: =O6+Q6 -> 0.1317 | S6: =R6*E6 -> 210.72 | T6: =-(F6-H6)/E6 -> -0.058 | U6: =R6+T6 -> 0.0737 | V6: =U6*E6 -> 117.92 | W6: =SUMIF(GLS!B:B,K6,GLS!C:C) -> 9.72 | Z6: =-IF(W6+X6+Y6=0,"à vérifier",W6+X6+Y6) -> -9.72 | AA6: =IFERROR((SUMIF($K:$K,K6,$Z:$Z)/COUNTIF($K:$K,K6))*E6/SUMIF($K:$K,K6,$E:$E),0) -> -9.72 | AB6: =AA6/E6 -> -0.006075 | AC6: =AB6+U6 -> 0.067625 | AD6: =AC6/R6 -> 0.5134776 | AE6: =AC6*E6 -> 108.2 | AF6: =IFERROR(-ABS(INDEX('frais amazon 011225-150326'!H:H,MATCH(Reproting_ERPALIN!K6,'frais amazon 011225-150326'!D:D,0))/1.2),"Commande hors la France") -> -39.05 | AG6: =IFERROR(AF6*E6/SUMIF($K:$K,K6,$E:$E),0) -> -39.05 | AH6: =AG6/E6 -> -0.02440625 | AI6: =AH6+AC6 -> 0.04321875 | AJ6: =AI6/R6 -> 0.32816059 | AK6: =AI6*E6 -> 69.15
A7: Aiguilles hypodermiques 1.20 x 50 mm, (Boite de 100 pièces) | B7: CH18200 | C7: Vitrex Medical | D7: 2026-01-01 | E7: 100 | F7: 10.93 | G7: 4.99 | H7: 9.07 | I7: 82.98 | J7: FR | K7: 408-9716015-9973139 | L7: =MONTH(D7) -> 1 | M7: =YEAR(D7) -> 2026 | N7: =D7*1 -> 46023 | O7: =F7/E7 -> 0.1093 | P7: =O7*E7 -> 10.93 | Q7: =G7/E7 -> 0.0499 | R7: =O7+Q7 -> 0.1592 | S7: =R7*E7 -> 15.92 | T7: =-(F7-H7)/E7 -> -0.0186 | U7: =R7+T7 -> 0.1406 | V7: =U7*E7 -> 14.06 | W7: =SUMIF(GLS!B:B,K7,GLS!C:C) -> 5.25 | Z7: =-IF(W7+X7+Y7=0,"à vérifier",W7+X7+Y7) -> -5.25 | AA7: =IFERROR((SUMIF($K:$K,K7,$Z:$Z)/COUNTIF($K:$K,K7))*E7/SUMIF($K:$K,K7,$E:$E),0) -> -5.25 | AB7: =AA7/E7 -> -0.0525 | AC7: =AB7+U7 -> 0.0881 | AD7: =AC7/R7 -> 0.55339196 | AE7: =AC7*E7 -> 8.81 | AF7: =IFERROR(-ABS(INDEX('frais amazon 011225-150326'!H:H,MATCH(Reproting_ERPALIN!K7,'frais amazon 011225-150326'!D:D,0))/1.2),"Commande hors la France") -> -2.9666667 | AG7: =IFERROR(AF7*E7/SUMIF($K:$K,K7,$E:$E),0) -> -2.9666667 | AH7: =AG7/E7 -> -0.029666667 | AI7: =AH7+AC7 -> 0.058433333 | AJ7: =AI7/R7 -> 0.36704355 | AK7: =AI7*E7 -> 5.8433333
A8: Abena - Couches adulte intraversables Maternity Pad Super - Sachet de 15 pièces | B8: 1000022654 | C8: Abena | D8: 2026-02-01 | E8: 30 | F8: 14.35 | G8: 0 | H8: 10.08 | I8: 70.21 | J8: FR | K8: 408-9658495-7513141 | L8: =MONTH(D8) -> 2 | M8: =YEAR(D8) -> 2026 | N8: =D8*1 -> 46054 | O8: =F8/E8 -> 0.47833333 | P8: =O8*E8 -> 14.35 | Q8: =G8/E8 -> 0 | R8: =O8+Q8 -> 0.47833333 | S8: =R8*E8 -> 14.35 | T8: =-(F8-H8)/E8 -> -0.14233333 | U8: =R8+T8 -> 0.336 | V8: =U8*E8 -> 10.08 | W8: =SUMIF(GLS!B:B,K8,GLS!C:C) -> 5.25 | Z8: =-IF(W8+X8+Y8=0,"à vérifier",W8+X8+Y8) -> -5.25 | AA8: =IFERROR((SUMIF($K:$K,K8,$Z:$Z)/COUNTIF($K:$K,K8))*E8/SUMIF($K:$K,K8,$E:$E),0) -> -5.25 | AB8: =AA8/E8 -> -0.175 | AC8: =AB8+U8 -> 0.161 | AD8: =AC8/R8 -> 0.33658537 | AE8: =AC8*E8 -> 4.83 | AF8: =IFERROR(-ABS(INDEX('frais amazon 011225-150326'!H:H,MATCH(Reproting_ERPALIN!K8,'frais amazon 011225-150326'!D:D,0))/1.2),"Commande hors la France") -> -2.6666667 | AG8: =IFERROR(AF8*E8/SUMIF($K:$K,K8,$E:$E),0) -> -2.6666667 | AH8: =AG8/E8 -> -0.088888889 | AI8: =AH8+AC8 -> 0.072111111 | AJ8: =AI8/R8 -> 0.15075494 | AK8: =AI8*E8 -> 2.1633333
A9: HARTMANN - ZETUVIT E Pansement absorbant stérile 15 x 20 cm (413792) - Boite de 25 pièces | B9: 413772 | C9: Hartmann | D9: 2026-02-01 | E9: 25 | F9: 9.17 | G9: 8.73 | H9: 3.9 | I9: 42.5 | J9: ES | K9: 408-9628751-6035569 | L9: =MONTH(D9) -> 2 | M9: =YEAR(D9) -> 2026 | N9: =D9*1 -> 46054 | O9: =F9/E9 -> 0.3668 | P9: =O9*E9 -> 9.17 | Q9: =G9/E9 -> 0.3492 | R9: =O9+Q9 -> 0.716 | S9: =R9*E9 -> 17.9 | T9: =-(F9-H9)/E9 -> -0.2108 | U9: =R9+T9 -> 0.5052 | V9: =U9*E9 -> 12.63 | W9: =SUMIF(GLS!B:B,K9,GLS!C:C) -> 10.72 | Z9: =-IF(W9+X9+Y9=0,"à vérifier",W9+X9+Y9) -> -10.72 | AA9: =IFERROR((SUMIF($K:$K,K9,$Z:$Z)/COUNTIF($K:$K,K9))*E9/SUMIF($K:$K,K9,$E:$E),0) -> -10.72 | AB9: =AA9/E9 -> -0.4288 | AC9: =AB9+U9 -> 0.0764 | AD9: =AC9/R9 -> 0.10670391 | AE9: =AC9*E9 -> 1.91 | AF9: =IFERROR(-ABS(INDEX('frais amazon 011225-150326'!H:H,MATCH(Reproting_ERPALIN!K9,'frais amazon 011225-150326'!D:D,0))/1.2),"Commande hors la France") -> Commande hors la France | AG9: =IFERROR(AF9*E9/SUMIF($K:$K,K9,$E:$E),0) -> 0 | AH9: =AG9/E9 -> 0 | AI9: =AH9+AC9 -> 0.0764 | AJ9: =AI9/R9 -> 0.10670391 | AK9: =AI9*E9 -> 1.91
A10: Compresse non tissé stérile 40 g/m2 , 10 cm x 10cm | B10: NL105-S-40 | C10: ZARYS International Group sp. z o.o. sp.k. | D10: 2026-02-01 | E10: 200 | F10: 24.4 | G10: 10.64 | H10: 22.04 | I10: 90.33 | J10: IT | K10: 408-9280083-9908352 | L10: =MONTH(D10) -> 2 | M10: =YEAR(D10) -> 2026 | N10: =D10*1 -> 46054 | O10: =F10/E10 -> 0.122 | P10: =O10*E10 -> 24.4 | Q10: =G10/E10 -> 0.0532 | R10: =O10+Q10 -> 0.1752 | S10: =R10*E10 -> 35.04 | T10: =-(F10-H10)/E10 -> -0.0118 | U10: =R10+T10 -> 0.1634 | V10: =U10*E10 -> 32.68 | W10: =SUMIF(GLS!B:B,K10,GLS!C:C) -> 10.72 | Z10: =-IF(W10+X10+Y10=0,"à vérifier",W10+X10+Y10) -> -10.72 | AA10: =IFERROR((SUMIF($K:$K,K10,$Z:$Z)/COUNTIF($K:$K,K10))*E10/SUMIF($K:$K,K10,$E:$E),0) -> -10.72 | AB10: =AA10/E10 -> -0.0536 | AC10: =AB10+U10 -> 0.1098 | AD10: =AC10/R10 -> 0.62671233 | AE10: =AC10*E10 -> 21.96 | AF10: =IFERROR(-ABS(INDEX('frais amazon 011225-150326'!H:H,MATCH(Reproting_ERPALIN!K10,'frais amazon 011225-150326'!D:D,0))/1.2),"Commande hors la France") -> Commande hors la France | AG10: =IFERROR(AF10*E10/SUMIF($K:$K,K10,$E:$E),0) -> 0 | AH10: =AG10/E10 -> 0 | AI10: =AH10+AC10 -> 0.1098 | AJ10: =AI10/R10 -> 0.62671233 | AK10: =AI10*E10 -> 21.96
A11: Aiguille hypodermique à usage unique non sécurisée 25G, 0,5 mm x 40 mm | B11: IN-05X40 | C11: ZARYS International Group sp. z o.o. sp.k. | D11: 2026-01-01 | E11: 100 | F11: 10.72 | G11: 4.99 | H11: 9.85 | I11: 91.88 | J11: FR | K11: 408-8992526-7392325 | L11: =MONTH(D11) -> 1 | M11: =YEAR(D11) -> 2026 | N11: =D11*1 -> 46023 | O11: =F11/E11 -> 0.1072 | P11: =O11*E11 -> 10.72 | Q11: =G11/E11 -> 0.0499 | R11: =O11+Q11 -> 0.1571 | S11: =R11*E11 -> 15.71 | T11: =-(F11-H11)/E11 -> -0.0087 | U11: =R11+T11 -> 0.1484 | V11: =U11*E11 -> 14.84 | W11: =SUMIF(GLS!B:B,K11,GLS!C:C) -> 9.59 | Z11: =-IF(W11+X11+Y11=0,"à vérifier",W11+X11+Y11) -> -9.59 | AA11: =IFERROR((SUMIF($K:$K,K11,$Z:$Z)/COUNTIF($K:$K,K11))*E11/SUMIF($K:$K,K11,$E:$E),0) -> -9.59 | AB11: =AA11/E11 -> -0.0959 | AC11: =AB11+U11 -> 0.0525 | AD11: =AC11/R11 -> 0.33418205 | AE11: =AC11*E11 -> 5.25 | AF11: =IFERROR(-ABS(INDEX('frais amazon 011225-150326'!H:H,MATCH(Reproting_ERPALIN!K11,'frais amazon 011225-150326'!D:D,0))/1.2),"Commande hors la France") -> -2.9 | AG11: =IFERROR(AF11*E11/SUMIF($K:$K,K11,$E:$E),0) -> -2.9 | AH11: =AG11/E11 -> -0.029 | AI11: =AH11+AC11 -> 0.0235 | AJ11: =AI11/R11 -> 0.14958625 | AK11: =AI11*E11 -> 2.35
A12: HARTMANN Lastopress Bande de Gaze Chair 7 cm x 3 m | B12: 931305 | C12: Hartmann | D12: 2026-01-01 | E12: 2 | F12: 13.72 | G12: 4.99 | H12: -0.46 | I12: -3.37 | J12: FR | K12: 408-8986799-6135540 | L12: =MONTH(D12) -> 1 | M12: =YEAR(D12) -> 2026 | N12: =D12*1 -> 46023 | O12: =F12/E12 -> 6.86 | P12: =O12*E12 -> 13.72 | Q12: =G12/E12 -> 2.495 | R12: =O12+Q12 -> 9.355 | S12: =R12*E12 -> 18.71 | T12: =-(F12-H12)/E12 -> -7.09 | U12: =R12+T12 -> 2.265 | V12: =U12*E12 -> 4.53 | W12: =SUMIF(GLS!B:B,K12,GLS!C:C) -> 5.25 | Z12: =-IF(W12+X12+Y12=0,"à vérifier",W12+X12+Y12) -> -5.25 | AA12: =IFERROR((SUMIF($K:$K,K12,$Z:$Z)/COUNTIF($K:$K,K12))*E12/SUMIF($K:$K,K12,$E:$E),0) -> -5.25 | AB12: =AA12/E12 -> -2.625 | AC12: =AB12+U12 -> -0.36 | AD12: =AC12/R12 -> -0.038482095 | AE12: =AC12*E12 -> -0.72 | AF12: =IFERROR(-ABS(INDEX('frais amazon 011225-150326'!H:H,MATCH(Reproting_ERPALIN!K12,'frais amazon 011225-150326'!D:D,0))/1.2),"Commande hors la France") -> -3.4666667 | AG12: =IFERROR(AF12*E12/SUMIF($K:$K,K12,$E:$E),0) -> -3.4666667 | AH12: =AG12/E12 -> -1.7333333 | AI12: =AH12+AC12 -> -2.0933333 | AJ12: =AI12/R12 -> -0.22376626 | AK12: =AI12*E12 -> -4.1866667
A13: Carrés de soin 50g Octolin 30 x 40 cm - Sachet de 50 pièces | B13: 684358 | C13: Hartmann | D13: 2026-01-01 | E13: 50 | F13: 6.09 | G13: 2.495 | H13: 4.51 | I13: 74.06 | J13: FR | K13: 408-8986137-3153951 | L13: =MONTH(D13) -> 1 | M13: =YEAR(D13) -> 2026 | N13: =D13*1 -> 46023 | O13: =F13/E13 -> 0.1218 | P13: =O13*E13 -> 6.09 | Q13: =G13/E13 -> 0.0499 | R13: =O13+Q13 -> 0.1717 | S13: =R13*E13 -> 8.585 | T13: =-(F13-H13)/E13 -> -0.0316 | U13: =R13+T13 -> 0.1401 | V13: =U13*E13 -> 7.005 | W13: =SUMIF(GLS!B:B,K13,GLS!C:C) -> 5.25 | Z13: =-IF(W13+X13+Y13=0,"à vérifier",W13+X13+Y13) -> -5.25 | AA13: =IFERROR((SUMIF($K:$K,K13,$Z:$Z)/COUNTIF($K:$K,K13))*E13/SUMIF($K:$K,K13,$E:$E),0) -> -2.625 | AB13: =AA13/E13 -> -0.0525 | AC13: =AB13+U13 -> 0.0876 | AD13: =AC13/R13 -> 0.5101922 | AE13: =AC13*E13 -> 4.38 | AF13: =IFERROR(-ABS(INDEX('frais amazon 011225-150326'!H:H,MATCH(Reproting_ERPALIN!K13,'frais amazon 011225-150326'!D:D,0))/1.2),"Commande hors la France") -> -2.2083333 | AG13: =IFERROR(AF13*E13/SUMIF($K:$K,K13,$E:$E),0) -> -1.1041667 | AH13: =AG13/E13 -> -0.022083333 | AI13: =AH13+AC13 -> 0.065516667 | AJ13: =AI13/R13 -> 0.38157639 | AK13: =AI13*E13 -> 3.2758333
A14: HARTMANN - Carrés de soin 50g Octolin 29 x 33 cm - Sachet de 50 pièces | B14: 684352 | C14: Hartmann | D14: 2026-01-01 | E14: 50 | F14: 5.87 | G14: 2.495 | H14: 4.52 | I14: 77 | J14: FR | K14: 408-8986137-3153951 | L14: =MONTH(D14) -> 1 | M14: =YEAR(D14) -> 2026 | N14: =D14*1 -> 46023 | O14: =F14/E14 -> 0.1174 | P14: =O14*E14 -> 5.87 | Q14: =G14/E14 -> 0.0499 | R14: =O14+Q14 -> 0.1673 | S14: =R14*E14 -> 8.365 | T14: =-(F14-H14)/E14 -> -0.027 | U14: =R14+T14 -> 0.1403 | V14: =U14*E14 -> 7.015 | W14: =SUMIF(GLS!B:B,K14,GLS!C:C) -> 5.25 | Z14: =-IF(W14+X14+Y14=0,"à vérifier",W14+X14+Y14) -> -5.25 | AA14: =IFERROR((SUMIF($K:$K,K14,$Z:$Z)/COUNTIF($K:$K,K14))*E14/SUMIF($K:$K,K14,$E:$E),0) -> -2.625 | AB14: =AA14/E14 -> -0.0525 | AC14: =AB14+U14 -> 0.0878 | AD14: =AC14/R14 -> 0.52480574 | AE14: =AC14*E14 -> 4.39 | AF14: =IFERROR(-ABS(INDEX('frais amazon 011225-150326'!H:H,MATCH(Reproting_ERPALIN!K14,'frais amazon 011225-150326'!D:D,0))/1.2),"Commande hors la France") -> -2.2083333 | AG14: =IFERROR(AF14*E14/SUMIF($K:$K,K14,$E:$E),0) -> -1.1041667 | AH14: =AG14/E14 -> -0.022083333 | AI14: =AH14+AC14 -> 0.065716667 | AJ14: =AI14/R14 -> 0.39280733 | AK14: =AI14*E14 -> 3.2858333
A15: Aiguille hypodermique à usage unique non sécurisée 20G, 0,9 mm x 25 mm | B15: IN-09X25 | C15: ZARYS International Group sp. z o.o. sp.k. | D15: 2026-02-01 | E15: 100 | F15: 10.32 | G15: 4.99 | H15: 9.56 | I15: 92.64 | J15: FR | K15: 408-8973722-1049161 | L15: =MONTH(D15) -> 2 | M15: =YEAR(D15) -> 2026 | N15: =D15*1 -> 46054 | O15: =F15/E15 -> 0.1032 | P15: =O15*E15 -> 10.32 | Q15: =G15/E15 -> 0.0499 | R15: =O15+Q15 -> 0.1531 | S15: =R15*E15 -> 15.31 | T15: =-(F15-H15)/E15 -> -0.0076 | U15: =R15+T15 -> 0.1455 | V15: =U15*E15 -> 14.55 | W15: =SUMIF(GLS!B:B,K15,GLS!C:C) -> 5.25 | Z15: =-IF(W15+X15+Y15=0,"à vérifier",W15+X15+Y15) -> -5.25 | AA15: =IFERROR((SUMIF($K:$K,K15,$Z:$Z)/COUNTIF($K:$K,K15))*E15/SUMIF($K:$K,K15,$E:$E),0) -> -5.25 | AB15: =AA15/E15 -> -0.0525 | AC15: =AB15+U15 -> 0.093 | AD15: =AC15/R15 -> 0.60744611 | AE15: =AC15*E15 -> 9.3 | AF15: =IFERROR(-ABS(INDEX('frais amazon 011225-150326'!H:H,MATCH(Reproting_ERPALIN!K15,'frais amazon 011225-150326'!D:D,0))/1.2),"Commande hors la France") -> -2.8333333 | AG15: =IFERROR(AF15*E15/SUMIF($K:$K,K15,$E:$E),0) -> -2.8333333 | AH15: =AG15/E15 -> -0.028333333 | AI15: =AH15+AC15 -> 0.064666667 | AJ15: =AI15/R15 -> 0.42238189 | AK15: =AI15*E15 -> 6.4666667
A16: Abena - Couches adulte intraversables Maternity Pad Super - Sachet de 15 pièces | B16: 1000022654 | C16: Abena | D16: 2026-01-01 | E16: 30 | F16: 14.35 | G16: 0 | H16: 10.08 | I16: 70.21 | J16: FR | K16: 408-8949959-8811522 | L16: =MONTH(D16) -> 1 | M16: =YEAR(D16) -> 2026 | N16: =D16*1 -> 46023 | O16: =F16/E16 -> 0.47833333 | P16: =O16*E16 -> 14.35 | Q16: =G16/E16 -> 0 | R16: =O16+Q16 -> 0.47833333 | S16: =R16*E16 -> 14.35 | T16: =-(F16-H16)/E16 -> -0.14233333 | U16: =R16+T16 -> 0.336 | V16: =U16*E16 -> 10.08 | W16: =SUMIF(GLS!B:B,K16,GLS!C:C) -> 5.48 | Z16: =-IF(W16+X16+Y16=0,"à vérifier",W16+X16+Y16) -> -5.48 | AA16: =IFERROR((SUMIF($K:$K,K16,$Z:$Z)/COUNTIF($K:$K,K16))*E16/SUMIF($K:$K,K16,$E:$E),0) -> -5.48 | AB16: =AA16/E16 -> -0.18266667 | AC16: =AB16+U16 -> 0.15333333 | AD16: =AC16/R16 -> 0.32055749 | AE16: =AC16*E16 -> 4.6 | AF16: =IFERROR(-ABS(INDEX('frais amazon 011225-150326'!H:H,MATCH(Reproting_ERPALIN!K16,'frais amazon 011225-150326'!D:D,0))/1.2),"Commande hors la France") -> -2.6666667 | AG16: =IFERROR(AF16*E16/SUMIF($K:$K,K16,$E:$E),0) -> -2.6666667 | AH16: =AG16/E16 -> -0.088888889 | AI16: =AH16+AC16 -> 0.064444444 | AJ16: =AI16/R16 -> 0.13472706 | AK16: =AI16*E16 -> 1.9333333
A17: Aiguille hypodermique à usage unique non sécurisée 25G, 0,5 mm x 40 mm | B17: IN-05X40 | C17: ZARYS International Group sp. z o.o. sp.k. | D17: 2026-01-01 | E17: 100 | F17: 10.04 | G17: 4.99 | H17: 9.17 | I17: 91.33 | J17: FR | K17: 408-8842324-5805908 | L17: =MONTH(D17) -> 1 | M17: =YEAR(D17) -> 2026 | N17: =D17*1 -> 46023 | O17: =F17/E17 -> 0.1004 | P17: =O17*E17 -> 10.04 | Q17: =G17/E17 -> 0.0499 | R17: =O17+Q17 -> 0.1503 | S17: =R17*E17 -> 15.03 | T17: =-(F17-H17)/E17 -> -0.0087 | U17: =R17+T17 -> 0.1416 | V17: =U17*E17 -> 14.16 | W17: =SUMIF(GLS!B:B,K17,GLS!C:C) -> 5.25 | Z17: =-IF(W17+X17+Y17=0,"à vérifier",W17+X17+Y17) -> -5.25 | AA17: =IFERROR((SUMIF($K:$K,K17,$Z:$Z)/COUNTIF($K:$K,K17))*E17/SUMIF($K:$K,K17,$E:$E),0) -> -5.25 | AB17: =AA17/E17 -> -0.0525 | AC17: =AB17+U17 -> 0.0891 | AD17: =AC17/R17 -> 0.59281437 | AE17: =AC17*E17 -> 8.91 | AF17: =IFERROR(-ABS(INDEX('frais amazon 011225-150326'!H:H,MATCH(Reproting_ERPALIN!K17,'frais amazon 011225-150326'!D:D,0))/1.2),"Commande hors la France") -> -2.7833333 | AG17: =IFERROR(AF17*E17/SUMIF($K:$K,K17,$E:$E),0) -> -2.7833333 | AH17: =AG17/E17 -> -0.027833333 | AI17: =AH17+AC17 -> 0.061266667 | AJ17: =AI17/R17 -> 0.40762919 | AK17: =AI17*E17 -> 6.1266667
A18: HARTMANN - ZETUVIT E Pansement absorbant stérile 15 x 20 cm (413792) - Boite de 25 pièces | B18: 413772 | C18: Hartmann | D18: 2026-01-01 | E18: 100 | F18: 36.97 | G18: 11.45 | H18: 15.88 | I18: 42.95 | J18: IT | K18: 408-8834949-5530704 | L18: =MONTH(D18) -> 1 | M18: =YEAR(D18) -> 2026 | N18: =D18*1 -> 46023 | O18: =F18/E18 -> 0.3697 | P18: =O18*E18 -> 36.97 | Q18: =G18/E18 -> 0.1145 | R18: =O18+Q18 -> 0.4842 | S18: =R18*E18 -> 48.42 | T18: =-(F18-H18)/E18 -> -0.2109 | U18: =R18+T18 -> 0.2733 | V18: =U18*E18 -> 27.33 | W18: =SUMIF(GLS!B:B,K18,GLS!C:C) -> 10.72 | Z18: =-IF(W18+X18+Y18=0,"à vérifier",W18+X18+Y18) -> -10.72 | AA18: =IFERROR((SUMIF($K:$K,K18,$Z:$Z)/COUNTIF($K:$K,K18))*E18/SUMIF($K:$K,K18,$E:$E),0) -> -10.72 | AB18: =AA18/E18 -> -0.1072 | AC18: =AB18+U18 -> 0.1661 | AD18: =AC18/R18 -> 0.34304007 | AE18: =AC18*E18 -> 16.61 | AF18: =IFERROR(-ABS(INDEX('frais amazon 011225-150326'!H:H,MATCH(Reproting_ERPALIN!K18,'frais amazon 011225-150326'!D:D,0))/1.2),"Commande hors la France") -> Commande hors la France | AG18: =IFERROR(AF18*E18/SUMIF($K:$K,K18,$E:$E),0) -> 0 | AH18: =AG18/E18 -> 0 | AI18: =AH18+AC18 -> 0.1661 | AJ18: =AI18/R18 -> 0.34304007 | AK18: =AI18*E18 -> 16.61
A19: AIGUILLE HYPODERMIQUE 21G 25MM | B19: IN-08X25 | C19: ZARYS International Group sp. z o.o. sp.k. | D19: 2026-01-01 | E19: 200 | F19: 19.12 | G19: 4.99 | H19: 17.7 | I19: 92.57 | J19: FR | K19: 408-8808819-1426760 | L19: =MONTH(D19) -> 1 | M19: =YEAR(D19) -> 2026 | N19: =D19*1 -> 46023 | O19: =F19/E19 -> 0.0956 | P19: =O19*E19 -> 19.12 | Q19: =G19/E19 -> 0.02495 | R19: =O19+Q19 -> 0.12055 | S19: =R19*E19 -> 24.11 | T19: =-(F19-H19)/E19 -> -0.0071 | U19: =R19+T19 -> 0.11345 | V19: =U19*E19 -> 22.69 | W19: =SUMIF(GLS!B:B,K19,GLS!C:C) -> 5.25 | Z19: =-IF(W19+X19+Y19=0,"à vérifier",W19+X19+Y19) -> -5.25 | AA19: =IFERROR((SUMIF($K:$K,K19,$Z:$Z)/COUNTIF($K:$K,K19))*E19/SUMIF($K:$K,K19,$E:$E),0) -> -5.25 | AB19: =AA19/E19 -> -0.02625 | AC19: =AB19+U19 -> 0.0872 | AD19: =AC19/R19 -> 0.72335131 | AE19: =AC19*E19 -> 17.44 | AF19: =IFERROR(-ABS(INDEX('frais amazon 011225-150326'!H:H,MATCH(Reproting_ERPALIN!K19,'frais amazon 011225-150326'!D:D,0))/1.2),"Commande hors la France") -> -4.4583333 | AG19: =IFERROR(AF19*E19/SUMIF($K:$K,K19,$E:$E),0) -> -4.4583333 | AH19: =AG19/E19 -> -0.022291667 | AI19: =AH19+AC19 -> 0.064908333 | AJ19: =AI19/R19 -> 0.53843495 | AK19: =AI19*E19 -> 12.981667
A20: Aiguille hypodermique à usage unique non sécurisée 21G, 0,8 mm x 50 mm | B20: IN-08X50 | C20: ZARYS International Group sp. z o.o. sp.k. | D20: 2026-01-01 | E20: 100 | F20: 12.98 | G20: 4.99 | H20: 11.52 | I20: 88.75 | J20: FR | K20: 408-8763175-7451554 | L20: =MONTH(D20) -> 1 | M20: =YEAR(D20) -> 2026 | N20: =D20*1 -> 46023 | O20: =F20/E20 -> 0.1298 | P20: =O20*E20 -> 12.98 | Q20: =G20/E20 -> 0.0499 | R20: =O20+Q20 -> 0.1797 | S20: =R20*E20 -> 17.97 | T20: =-(F20-H20)/E20 -> -0.0146 | U20: =R20+T20 -> 0.1651 | V20: =U20*E20 -> 16.51 | W20: =SUMIF(GLS!B:B,K20,GLS!C:C) -> 5.25 | Z20: =-IF(W20+X20+Y20=0,"à vérifier",W20+X20+Y20) -> -5.25 | AA20: =IFERROR((SUMIF($K:$K,K20,$Z:$Z)/COUNTIF($K:$K,K20))*E20/SUMIF($K:$K,K20,$E:$E),0) -> -5.25 | AB20: =AA20/E20 -> -0.0525 | AC20: =AB20+U20 -> 0.1126 | AD20: =AC20/R20 -> 0.62659989 | AE20: =AC20*E20 -> 11.26 | AF20: =IFERROR(-ABS(INDEX('frais amazon 011225-150326'!H:H,MATCH(Reproting_ERPALIN!K20,'frais amazon 011225-150326'!D:D,0))/1.2),"Commande hors la France") -> -3.3333333 | AG20: =IFERROR(AF20*E20/SUMIF($K:$K,K20,$E:$E),0) -> -3.3333333 | AH20: =AG20/E20 -> -0.033333333 | AI20: =AH20+AC20 -> 0.079266667 | AJ20: =AI20/R20 -> 0.44110555 | AK20: =AI20*E20 -> 7.9266667
A21: Abena - Couches adulte intraversables Maternity Pad Super - Sachet de 15 pièces | B21: 1000022654 | C21: Abena | D21: 2026-02-01 | E21: 30 | F21: 13.49 | G21: 0 | H21: 9.22 | I21: 68.31 | J21: FR | K21: 408-8732277-5985169 | L21: =MONTH(D21) -> 2 | M21: =YEAR(D21) -> 2026 | N21: =D21*1 -> 46054 | O21: =F21/E21 -> 0.44966667 | P21: =O21*E21 -> 13.49 | Q21: =G21/E21 -> 0 | R21: =O21+Q21 -> 0.44966667 | S21: =R21*E21 -> 13.49 | T21: =-(F21-H21)/E21 -> -0.14233333 | U21: =R21+T21 -> 0.30733333 | V21: =U21*E21 -> 9.22 | W21: =SUMIF(GLS!B:B,K21,GLS!C:C) -> 5.25 | Z21: =-IF(W21+X21+Y21=0,"à vérifier",W21+X21+Y21) -> -5.25 | AA21: =IFERROR((SUMIF($K:$K,K21,$Z:$Z)/COUNTIF($K:$K,K21))*E21/SUMIF($K:$K,K21,$E:$E),0) -> -5.25 | AB21: =AA21/E21 -> -0.175 | AC21: =AB21+U21 -> 0.13233333 | AD21: =AC21/R21 -> 0.29429207 | AE21: =AC21*E21 -> 3.97 | AF21: =IFERROR(-ABS(INDEX('frais amazon 011225-150326'!H:H,MATCH(Reproting_ERPALIN!K21,'frais amazon 011225-150326'!D:D,0))/1.2),"Commande hors la France") -> -2.5083333 | AG21: =IFERROR(AF21*E21/SUMIF($K:$K,K21,$E:$E),0) -> -2.5083333 | AH21: =AG21/E21 -> -0.083611111 | AI21: =AH21+AC21 -> 0.048722222 | AJ21: =AI21/R21 -> 0.10835187 | AK21: =AI21*E21 -> 1.4616667
A22: Carrés de soin 50g Octolin 30 x 40 cm - Sachet de 50 pièces | B22: 684358 | C22: Hartmann | D22: 2026-01-01 | E22: 50 | F22: 5.77 | G22: 0.71285714 | H22: 4.19 | I22: 72.62 | J22: FR | K22: 408-8712382-7341952 | L22: =MONTH(D22) -> 1 | M22: =YEAR(D22) -> 2026 | N22: =D22*1 -> 46023 | O22: =F22/E22 -> 0.1154 | P22: =O22*E22 -> 5.77 | Q22: =G22/E22 -> 0.014257143 | R22: =O22+Q22 -> 0.12965714 | S22: =R22*E22 -> 6.4828571 | T22: =-(F22-H22)/E22 -> -0.0316 | U22: =R22+T22 -> 0.098057143 | V22: =U22*E22 -> 4.9028571 | W22: =SUMIF(GLS!B:B,K22,GLS!C:C) -> 5.49 | Z22: =-IF(W22+X22+Y22=0,"à vérifier",W22+X22+Y22) -> -5.49 | AA22: =IFERROR((SUMIF($K:$K,K22,$Z:$Z)/COUNTIF($K:$K,K22))*E22/SUMIF($K:$K,K22,$E:$E),0) -> -0.78428571 | AB22: =AA22/E22 -> -0.015685714 | AC22: =AB22+U22 -> 0.082371429 | AD22: =AC22/R22 -> 0.6353019 | AE22: =AC22*E22 -> 4.1185714 | AF22: =IFERROR(-ABS(INDEX('frais amazon 011225-150326'!H:H,MATCH(Reproting_ERPALIN!K22,'frais amazon 011225-150326'!D:D,0))/1.2),"Commande hors la France") -> -6.7916667 | AG22: =IFERROR(AF22*E22/SUMIF($K:$K,K22,$E:$E),0) -> -0.9702381 | AH22: =AG22/E22 -> -0.019404762 | AI22: =AH22+AC22 -> 0.062966667 | AJ22: =AI22/R22 -> 0.48563978 | AK22: =AI22*E22 -> 3.1483333
A23: HARTMANN - Carrés de soin 50g Octolin 29 x 33 cm - Sachet de 50 pièces | B23: 684352 | C23: Hartmann | D23: 2026-01-01 | E23: 300 | F23: 35.19 | G23: 4.2771429 | H23: 27.09 | I23: 76.98 | J23: FR | K23: 408-8712382-7341952 | L23: =MONTH(D23) -> 1 | M23: =YEAR(D23) -> 2026 | N23: =D23*1 -> 46023 | O23: =F23/E23 -> 0.1173 | P23: =O23*E23 -> 35.19 | Q23: =G23/E23 -> 0.014257143 | R23: =O23+Q23 -> 0.13155714 | S23: =R23*E23 -> 39.467143 | T23: =-(F23-H23)/E23 -> -0.027 | U23: =R23+T23 -> 0.10455714 | V23: =U23*E23 -> 31.367143 | W23: =SUMIF(GLS!B:B,K23,GLS!C:C) -> 5.49 | Z23: =-IF(W23+X23+Y23=0,"à vérifier",W23+X23+Y23) -> -5.49 | AA23: =IFERROR((SUMIF($K:$K,K23,$Z:$Z)/COUNTIF($K:$K,K23))*E23/SUMIF($K:$K,K23,$E:$E),0) -> -4.7057143 | AB23: =AA23/E23 -> -0.015685714 | AC23: =AB23+U23 -> 0.088871429 | AD23: =AC23/R23 -> 0.6755348 | AE23: =AC23*E23 -> 26.661429 | AF23: =IFERROR(-ABS(INDEX('frais amazon 011225-150326'!H:H,MATCH(Reproting_ERPALIN!K23,'frais amazon 011225-150326'!D:D,0))/1.2),"Commande hors la France") -> -6.7916667 | AG23: =IFERROR(AF23*E23/SUMIF($K:$K,K23,$E:$E),0) -> -5.8214286 | AH23: =AG23/E23 -> -0.019404762 | AI23: =AH23+AC23 -> 0.069466667 | AJ23: =AI23/R23 -> 0.52803417 | AK23: =AI23*E23 -> 20.84
A24: Alèse jetable de protection Extra soft pour chaises et lits 60 x 60 cm | B24: 254125 | C24: Abena | D24: 2026-01-01 | E24: 10 | F24: 6.64 | G24: 10.83 | H24: 3.16 | I24: 47.64 | J24: IT | K24: 408-8615211-9073139 | L24: =MONTH(D24) -> 1 | M24: =YEAR(D24) -> 2026 | N24: =D24*1 -> 46023 | O24: =F24/E24 -> 0.664 | P24: =O24*E24 -> 6.64 | Q24: =G24/E24 -> 1.083 | R24: =O24+Q24 -> 1.747 | S24: =R24*E24 -> 17.47 | T24: =-(F24-H24)/E24 -> -0.348 | U24: =R24+T24 -> 1.399 | V24: =U24*E24 -> 13.99 | W24: =SUMIF(GLS!B:B,K24,GLS!C:C) -> 11.05 | Z24: =-IF(W24+X24+Y24=0,"à vérifier",W24+X24+Y24) -> -11.05 | AA24: =IFERROR((SUMIF($K:$K,K24,$Z:$Z)/COUNTIF($K:$K,K24))*E24/SUMIF($K:$K,K24,$E:$E),0) -> -11.05 | AB24: =AA24/E24 -> -1.105 | AC24: =AB24+U24 -> 0.294 | AD24: =AC24/R24 -> 0.16828849 | AE24: =AC24*E24 -> 2.94 | AF24: =IFERROR(-ABS(INDEX('frais amazon 011225-150326'!H:H,MATCH(Reproting_ERPALIN!K24,'frais amazon 011225-150326'!D:D,0))/1.2),"Commande hors la France") -> Commande hors la France | AG24: =IFERROR(AF24*E24/SUMIF($K:$K,K24,$E:$E),0) -> 0 | AH24: =AG24/E24 -> 0 | AI24: =AH24+AC24 -> 0.294 | AJ24: =AI24/R24 -> 0.16828849 | AK24: =AI24*E24 -> 2.94
A25: Seringue à insuline, stérile - Boite de 100 pièces - Rouge | B25: IN-U40-1-BL | C25: ZARYS International Group sp. z o.o. sp.k. | D25: 2026-01-01 | E25: 100 | F25: 16.87 | G25: 16.31 | H25: 14.76 | I25: 87.49 | J25: IT | K25: 408-8512935-6400369 | L25: =MONTH(D25) -> 1 | M25: =YEAR(D25) -> 2026 | N25: =D25*1 -> 46023 | O25: =F25/E25 -> 0.1687 | P25: =O25*E25 -> 16.87 | Q25: =G25/E25 -> 0.1631 | R25: =O25+Q25 -> 0.3318 | S25: =R25*E25 -> 33.18 | T25: =-(F25-H25)/E25 -> -0.0211 | U25: =R25+T25 -> 0.3107 | V25: =U25*E25 -> 31.07 | W25: =SUMIF(GLS!B:B,K25,GLS!C:C) -> 10.72 | Z25: =-IF(W25+X25+Y25=0,"à vérifier",W25+X25+Y25) -> -10.72 | AA25: =IFERROR((SUMIF($K:$K,K25,$Z:$Z)/COUNTIF($K:$K,K25))*E25/SUMIF($K:$K,K25,$E:$E),0) -> -10.72 | AB25: =AA25/E25 -> -0.1072 | AC25: =AB25+U25 -> 0.2035 | AD25: =AC25/R25 -> 0.61332128 | AE25: =AC25*E25 -> 20.35 | AF25: =IFERROR(-ABS(INDEX('frais amazon 011225-150326'!H:H,MATCH(Reproting_ERPALIN!K25,'frais amazon 011225-150326'!D:D,0))/1.2),"Commande hors la France") -> Commande hors la France | AG25: =IFERROR(AF25*E25/SUMIF($K:$K,K25,$E:$E),0) -> 0 | AH25: =AG25/E25 -> 0 | AI25: =AH25+AC25 -> 0.2035 | AJ25: =AI25/R25 -> 0.61332128 | AK25: =AI25*E25 -> 20.35
A26: FL MEDICAL - Pots à urine 120 ml avec étiquette avec bouchon à vis - 300 pièces | B26: 25033 | C26: FL MEDICAL | D26: 2026-01-01 | E26: 300 | F26: 32.52 | G26: 12.26 | H26: 16.17 | I26: 49.72 | J26: IT | K26: 408-8462591-7611546 | L26: =MONTH(D26) -> 1 | M26: =YEAR(D26) -> 2026 | N26: =D26*1 -> 46023 | O26: =F26/E26 -> 0.1084 | P26: =O26*E26 -> 32.52 | Q26: =G26/E26 -> 0.040866667 | R26: =O26+Q26 -> 0.14926667 | S26: =R26*E26 -> 44.78 | T26: =-(F26-H26)/E26 -> -0.0545 | U26: =R26+T26 -> 0.094766667 | V26: =U26*E26 -> 28.43 | W26: =SUMIF(GLS!B:B,K26,GLS!C:C) -> 66.84 | Z26: =-IF(W26+X26+Y26=0,"à vérifier",W26+X26+Y26) -> -66.84 | AA26: =IFERROR((SUMIF($K:$K,K26,$Z:$Z)/COUNTIF($K:$K,K26))*E26/SUMIF($K:$K,K26,$E:$E),0) -> -66.84 | AB26: =AA26/E26 -> -0.2228 | AC26: =AB26+U26 -> -0.12803333 | AD26: =AC26/R26 -> -0.857749 | AE26: =AC26*E26 -> -38.41 | AF26: =IFERROR(-ABS(INDEX('frais amazon 011225-150326'!H:H,MATCH(Reproting_ERPALIN!K26,'frais amazon 011225-150326'!D:D,0))/1.2),"Commande hors la France") -> Commande hors la France | AG26: =IFERROR(AF26*E26/SUMIF($K:$K,K26,$E:$E),0) -> 0 | AH26: =AG26/E26 -> 0 | AI26: =AH26+AC26 -> -0.12803333 | AJ26: =AI26/R26 -> -0.857749 | AK26: =AI26*E26 -> -38.41
A27: Aiguille d'injection sans phtalate - Boite de 100 pièces - 22G - 30 mm | B27: IN-07X30 | C27: ZARYS International Group sp. z o.o. sp.k. | D27: 2026-01-01 | E27: 100 | F27: 12.05 | G27: 4.99 | H27: 11.35 | I27: 94.19 | J27: FR | K27: 408-8373165-8705937 | L27: =MONTH(D27) -> 1 | M27: =YEAR(D27) -> 2026 | N27: =D27*1 -> 46023 | O27: =F27/E27 -> 0.1205 | P27: =O27*E27 -> 12.05 | Q27: =G27/E27 -> 0.0499 | R27: =O27+Q27 -> 0.1704 | S27: =R27*E27 -> 17.04 | T27: =-(F27-H27)/E27 -> -0.007 | U27: =R27+T27 -> 0.1634 | V27: =U27*E27 -> 16.34 | W27: =SUMIF(GLS!B:B,K27,GLS!C:C) -> 5.25 | Z27: =-IF(W27+X27+Y27=0,"à vérifier",W27+X27+Y27) -> -5.25 | AA27: =IFERROR((SUMIF($K:$K,K27,$Z:$Z)/COUNTIF($K:$K,K27))*E27/SUMIF($K:$K,K27,$E:$E),0) -> -5.25 | AB27: =AA27/E27 -> -0.0525 | AC27: =AB27+U27 -> 0.1109 | AD27: =AC27/R27 -> 0.6508216 | AE27: =AC27*E27 -> 11.09 | AF27: =IFERROR(-ABS(INDEX('frais amazon 011225-150326'!H:H,MATCH(Reproting_ERPALIN!K27,'frais amazon 011225-150326'!D:D,0))/1.2),"Commande hors la France") -> -3.15 | AG27: =IFERROR(AF27*E27/SUMIF($K:$K,K27,$E:$E),0) -> -3.15 | AH27: =AG27/E27 -> -0.0315 | AI27: =AH27+AC27 -> 0.0794 | AJ27: =AI27/R27 -> 0.46596244 | AK27: =AI27*E27 -> 7.94
A28: Comed - Abaisse langue en bois adulte (Boite de 100 pièces) | B28: 25 105 00 | C28: COMED | D28: 2026-01-01 | E28: 100 | F28: 6.23 | G28: 0 | H28: 4.62 | I28: 74.16 | J28: FR | K28: 408-8368946-2157146 | L28: =MONTH(D28) -> 1 | M28: =YEAR(D28) -> 2026 | N28: =D28*1 -> 46023 | O28: =F28/E28 -> 0.0623 | P28: =O28*E28 -> 6.23 | Q28: =G28/E28 -> 0 | R28: =O28+Q28 -> 0.0623 | S28: =R28*E28 -> 6.23 | T28: =-(F28-H28)/E28 -> -0.0161 | U28: =R28+T28 -> 0.0462 | V28: =U28*E28 -> 4.62 | W28: =SUMIF(GLS!B:B,K28,GLS!C:C) -> 5.25 | Z28: =-IF(W28+X28+Y28=0,"à vérifier",W28+X28+Y28) -> -5.25 | AA28: =IFERROR((SUMIF($K:$K,K28,$Z:$Z)/COUNTIF($K:$K,K28))*E28/SUMIF($K:$K,K28,$E:$E),0) -> -5.25 | AB28: =AA28/E28 -> -0.0525 | AC28: =AB28+U28 -> -0.0063 | AD28: =AC28/R28 -> -0.1011236 | AE28: =AC28*E28 -> -0.63 | AF28: =IFERROR(-ABS(INDEX('frais amazon 011225-150326'!H:H,MATCH(Reproting_ERPALIN!K28,'frais amazon 011225-150326'!D:D,0))/1.2),"Commande hors la France") -> -0.61666667 | AG28: =IFERROR(AF28*E28/SUMIF($K:$K,K28,$E:$E),0) -> -0.61666667 | AH28: =AG28/E28 -> -0.0061666667 | AI28: =AH28+AC28 -> -0.012466667 | AJ28: =AI28/R28 -> -0.20010701 | AK28: =AI28*E28 -> -1.2466667
A29: Pied A Serum 2 Crochets Inox | B29: 45 410 05 | C29: Hartmann | D29: 2026-01-01 | E29: 2 | F29: 143.48 | G29: 4.99 | H29: 49.48 | I29: 34.49 | J29: FR | K29: 408-8166202-4187523 | L29: =MONTH(D29) -> 1 | M29: =YEAR(D29) -> 2026 | N29: =D29*1 -> 46023 | O29: =F29/E29 -> 71.74 | P29: =O29*E29 -> 143.48 | Q29: =G29/E29 -> 2.495 | R29: =O29+Q29 -> 74.235 | S29: =R29*E29 -> 148.47 | T29: =-(F29-H29)/E29 -> -47 | U29: =R29+T29 -> 27.235 | V29: =U29*E29 -> 54.47 | W29: =SUMIF(GLS!B:B,K29,GLS!C:C) -> 0 | Z29: =-IF(W29+X29+Y29=0,"à vérifier",W29+X29+Y29) -> #VALUE! | AA29: =IFERROR((SUMIF($K:$K,K29,$Z:$Z)/COUNTIF($K:$K,K29))*E29/SUMIF($K:$K,K29,$E:$E),0) -> 0 | AB29: =AA29/E29 -> 0 | AC29: =AB29+U29 -> 27.235 | AD29: =AC29/R29 -> 0.36687546 | AE29: =AC29*E29 -> 54.47 | AF29: =IFERROR(-ABS(INDEX('frais amazon 011225-150326'!H:H,MATCH(Reproting_ERPALIN!K29,'frais amazon 011225-150326'!D:D,0))/1.2),"Commande hors la France") -> -27.516667 | AG29: =IFERROR(AF29*E29/SUMIF($K:$K,K29,$E:$E),0) -> -27.516667 | AH29: =AG29/E29 -> -13.758333 | AI29: =AH29+AC29 -> 13.476667 | AJ29: =AI29/R29 -> 0.1815406 | AK29: =AI29*E29 -> 26.953333
A30: Abena - Couches adulte intraversables Maternity Pad Super - Sachet de 15 pièces | B30: 1000022654 | C30: Abena | D30: 2026-01-01 | E30: 30 | F30: 14.35 | G30: 0 | H30: 10.08 | I30: 70.21 | J30: FR | K30: 408-8116156-3541903 | L30: =MONTH(D30) -> 1 | M30: =YEAR(D30) -> 2026 | N30: =D30*1 -> 46023 | O30: =F30/E30 -> 0.47833333 | P30: =O30*E30 -> 14.35 | Q30: =G30/E30 -> 0 | R30: =O30+Q30 -> 0.47833333 | S30: =R30*E30 -> 14.35 | T30: =-(F30-H30)/E30 -> -0.14233333 | U30: =R30+T30 -> 0.336 | V30: =U30*E30 -> 10.08 | W30: =SUMIF(GLS!B:B,K30,GLS!C:C) -> 5.48 | Z30: =-IF(W30+X30+Y30=0,"à vérifier",W30+X30+Y30) -> -5.48 | AA30: =IFERROR((SUMIF($K:$K,K30,$Z:$Z)/COUNTIF($K:$K,K30))*E30/SUMIF($K:$K,K30,$E:$E),0) -> -5.48 | AB30: =AA30/E30 -> -0.18266667 | AC30: =AB30+U30 -> 0.15333333 | AD30: =AC30/R30 -> 0.32055749 | AE30: =AC30*E30 -> 4.6 | AF30: =IFERROR(-ABS(INDEX('frais amazon 011225-150326'!H:H,MATCH(Reproting_ERPALIN!K30,'frais amazon 011225-150326'!D:D,0))/1.2),"Commande hors la France") -> -2.65 | AG30: =IFERROR(AF30*E30/SUMIF($K:$K,K30,$E:$E),0) -> -2.65 | AH30: =AG30/E30 -> -0.088333333 | AI30: =AH30+AC30 -> 0.065 | AJ30: =AI30/R30 -> 0.1358885 | AK30: =AI30*E30 -> 1.95
A31: ZARYS - Sonde béquillée TIEMANN- CH14, (Boite de 50 pièces) | B31: CT-14-40 | C31: ZARYS International Group sp. z o.o. sp.k. | D31: 2026-01-01 | E31: 50 | F31: 25.14 | G31: 4.99 | H31: 18.85 | I31: 74.98 | J31: FR | K31: 408-8021122-5188353 | L31: =MONTH(D31) -> 1 | M31: =YEAR(D31) -> 2026 | N31: =D31*1 -> 46023 | O31: =F31/E31 -> 0.5028 | P31: =O31*E31 -> 25.14 | Q31: =G31/E31 -> 0.0998 | R31: =O31+Q31 -> 0.6026 | S31: =R31*E31 -> 30.13 | T31: =-(F31-H31)/E31 -> -0.1258 | U31: =R31+T31 -> 0.4768 | V31: =U31*E31 -> 23.84 | W31: =SUMIF(GLS!B:B,K31,GLS!C:C) -> 5.25 | Z31: =-IF(W31+X31+Y31=0,"à vérifier",W31+X31+Y31) -> -5.25 | AA31: =IFERROR((SUMIF($K:$K,K31,$Z:$Z)/COUNTIF($K:$K,K31))*E31/SUMIF($K:$K,K31,$E:$E),0) -> -5.25 | AB31: =AA31/E31 -> -0.105 | AC31: =AB31+U31 -> 0.3718 | AD31: =AC31/R31 -> 0.61699303 | AE31: =AC31*E31 -> 18.59 | AF31: =IFERROR(-ABS(INDEX('frais amazon 011225-150326'!H:H,MATCH(Reproting_ERPALIN!K31,'frais amazon 011225-150326'!D:D,0))/1.2),"Commande hors la France") -> -5.575 | AG31: =IFERROR(AF31*E31/SUMIF($K:$K,K31,$E:$E),0) -> -5.575 | AH31: =AG31/E31 -> -0.1115 | AI31: =AH31+AC31 -> 0.2603 | AJ31: =AI31/R31 -> 0.4319615 | AK31: =AI31*E31 -> 13.015
A32: Seringue à usage unique, 3 parties, Luer Lock de 50 ml, (Boite de 25 pièces) | B32: 050ML-3CZ-LL-PI | C32: ZARYS International Group sp. z o.o. sp.k. | D32: 2026-01-01 | E32: 25 | F32: 17.94 | G32: 4.99 | H32: 14.65 | I32: 81.66 | J32: FR | K32: 408-7962812-0682700 | L32: =MONTH(D32) -> 1 | M32: =YEAR(D32) -> 2026 | N32: =D32*1 -> 46023 | O32: =F32/E32 -> 0.7176 | P32: =O32*E32 -> 17.94 | Q32: =G32/E32 -> 0.1996 | R32: =O32+Q32 -> 0.9172 | S32: =R32*E32 -> 22.93 | T32: =-(F32-H32)/E32 -> -0.1316 | U32: =R32+T32 -> 0.7856 | V32: =U32*E32 -> 19.64 | W32: =SUMIF(GLS!B:B,K32,GLS!C:C) -> 5.48 | Z32: =-IF(W32+X32+Y32=0,"à vérifier",W32+X32+Y32) -> -5.48 | AA32: =IFERROR((SUMIF($K:$K,K32,$Z:$Z)/COUNTIF($K:$K,K32))*E32/SUMIF($K:$K,K32,$E:$E),0) -> -5.48 | AB32: =AA32/E32 -> -0.2192 | AC32: =AB32+U32 -> 0.5664 | AD32: =AC32/R32 -> 0.61753162 | AE32: =AC32*E32 -> 14.16 | AF32: =IFERROR(-ABS(INDEX('frais amazon 011225-150326'!H:H,MATCH(Reproting_ERPALIN!K32,'frais amazon 011225-150326'!D:D,0))/1.2),"Commande hors la France") -> -4.25 | AG32: =IFERROR(AF32*E32/SUMIF($K:$K,K32,$E:$E),0) -> -4.25 | AH32: =AG32/E32 -> -0.17 | AI32: =AH32+AC32 -> 0.3964 | AJ32: =AI32/R32 -> 0.43218491 | AK32: =AI32*E32 -> 9.91
A33: Aiguille hypodermique à usage unique non sécurisée 25G, 0,5 mm x 40 mm | B33: IN-05X40 | C33: ZARYS International Group sp. z o.o. sp.k. | D33: 2026-01-01 | E33: 100 | F33: 10.72 | G33: 4.99 | H33: 9.85 | I33: 91.88 | J33: FR | K33: 408-7942697-7501904 | L33: =MONTH(D33) -> 1 | M33: =YEAR(D33) -> 2026 | N33: =D33*1 -> 46023 | O33: =F33/E33 -> 0.1072 | P33: =O33*E33 -> 10.72 | Q33: =G33/E33 -> 0.0499 | R33: =O33+Q33 -> 0.1571 | S33: =R33*E33 -> 15.71 | T33: =-(F33-H33)/E33 -> -0.0087 | U33: =R33+T33 -> 0.1484 | V33: =U33*E33 -> 14.84 | W33: =SUMIF(GLS!B:B,K33,GLS!C:C) -> 5.25 | Z33: =-IF(W33+X33+Y33=0,"à vérifier",W33+X33+Y33) -> -5.25 | AA33: =IFERROR((SUMIF($K:$K,K33,$Z:$Z)/COUNTIF($K:$K,K33))*E33/SUMIF($K:$K,K33,$E:$E),0) -> -5.25 | AB33: =AA33/E33 -> -0.0525 | AC33: =AB33+U33 -> 0.0959 | AD33: =AC33/R33 -> 0.61043921 | AE33: =AC33*E33 -> 9.59 | AF33: =IFERROR(-ABS(INDEX('frais amazon 011225-150326'!H:H,MATCH(Reproting_ERPALIN!K33,'frais amazon 011225-150326'!D:D,0))/1.2),"Commande hors la France") -> -2.9166667 | AG33: =IFERROR(AF33*E33/SUMIF($K:$K,K33,$E:$E),0) -> -2.9166667 | AH33: =AG33/E33 -> -0.029166667 | AI33: =AH33+AC33 -> 0.066733333 | AJ33: =AI33/R33 -> 0.42478252 | AK33: =AI33*E33 -> 6.6733333
A34: ZARYS - Seringue à usage unique en 3 parties luer avec aiguille stérile 2 ml buse centrique 0.6mm x 30mm bleu foncé - Boite de 100 pcs | B34: 002ML-3CZ-SN | C34: ZARYS International Group sp. z o.o. sp.k. | D34: 2026-01-01 | E34: 100 | F34: 9.48 | G34: 4.99 | H34: 7.34 | I34: 77.43 | J34: FR | K34: 408-7746100-0015500 | L34: =MONTH(D34) -> 1 | M34: =YEAR(D34) -> 2026 | N34: =D34*1 -> 46023 | O34: =F34/E34 -> 0.0948 | P34: =O34*E34 -> 9.48 | Q34: =G34/E34 -> 0.0499 | R34: =O34+Q34 -> 0.1447 | S34: =R34*E34 -> 14.47 | T34: =-(F34-H34)/E34 -> -0.0214 | U34: =R34+T34 -> 0.1233 | V34: =U34*E34 -> 12.33 | W34: =SUMIF(GLS!B:B,K34,GLS!C:C) -> 5.25 | Z34: =-IF(W34+X34+Y34=0,"à vérifier",W34+X34+Y34) -> -5.25 | AA34: =IFERROR((SUMIF($K:$K,K34,$Z:$Z)/COUNTIF($K:$K,K34))*E34/SUMIF($K:$K,K34,$E:$E),0) -> -5.25 | AB34: =AA34/E34 -> -0.0525 | AC34: =AB34+U34 -> 0.0708 | AD34: =AC34/R34 -> 0.48928818 | AE34: =AC34*E34 -> 7.08 | AF34: =IFERROR(-ABS(INDEX('frais amazon 011225-150326'!H:H,MATCH(Reproting_ERPALIN!K34,'frais amazon 011225-150326'!D:D,0))/1.2),"Commande hors la France") -> -2.675 | AG34: =IFERROR(AF34*E34/SUMIF($K:$K,K34,$E:$E),0) -> -2.675 | AH34: =AG34/E34 -> -0.02675 | AI34: =AH34+AC34 -> 0.04405 | AJ34: =AI34/R34 -> 0.30442294 | AK34: =AI34*E34 -> 4.405
A35: Aiguille d'injection sans phtalate - Boite de 100 pièces - 25G - 25 mm | B35: IN-05X25 | C35: ZARYS International Group sp. z o.o. sp.k. | D35: 2026-01-01 | E35: 100 | F35: 10.05 | G35: 11.38 | H35: 9.27 | I35: 92.24 | J35: IE | K35: 408-7714441-4337122 | L35: =MONTH(D35) -> 1 | M35: =YEAR(D35) -> 2026 | N35: =D35*1 -> 46023 | O35: =F35/E35 -> 0.1005 | P35: =O35*E35 -> 10.05 | Q35: =G35/E35 -> 0.1138 | R35: =O35+Q35 -> 0.2143 | S35: =R35*E35 -> 21.43 | T35: =-(F35-H35)/E35 -> -0.0078 | U35: =R35+T35 -> 0.2065 | V35: =U35*E35 -> 20.65 | W35: =SUMIF(GLS!B:B,K35,GLS!C:C) -> 11.72 | Z35: =-IF(W35+X35+Y35=0,"à vérifier",W35+X35+Y35) -> -11.72 | AA35: =IFERROR((SUMIF($K:$K,K35,$Z:$Z)/COUNTIF($K:$K,K35))*E35/SUMIF($K:$K,K35,$E:$E),0) -> -11.72 | AB35: =AA35/E35 -> -0.1172 | AC35: =AB35+U35 -> 0.0893 | AD35: =AC35/R35 -> 0.41670555 | AE35: =AC35*E35 -> 8.93 | AF35: =IFERROR(-ABS(INDEX('frais amazon 011225-150326'!H:H,MATCH(Reproting_ERPALIN!K35,'frais amazon 011225-150326'!D:D,0))/1.2),"Commande hors la France") -> Commande hors la France | AG35: =IFERROR(AF35*E35/SUMIF($K:$K,K35,$E:$E),0) -> 0 | AH35: =AG35/E35 -> 0 | AI35: =AH35+AC35 -> 0.0893 | AJ35: =AI35/R35 -> 0.41670555 | AK35: =AI35*E35 -> 8.93
A36: Aiguille d'injection sans phtalate - Boite de 100 pièces - 23G - 30 mm | B36: IN-06X30 | C36: ZARYS International Group sp. z o.o. sp.k. | D36: 2026-01-01 | E36: 100 | F36: 10.47 | G36: 8.75 | H36: 9.7 | I36: 92.65 | J36: ES | K36: 408-7640878-0907507 | L36: =MONTH(D36) -> 1 | M36: =YEAR(D36) -> 2026 | N36: =D36*1 -> 46023 | O36: =F36/E36 -> 0.1047 | P36: =O36*E36 -> 10.47 | Q36: =G36/E36 -> 0.0875 | R36: =O36+Q36 -> 0.1922 | S36: =R36*E36 -> 19.22 | T36: =-(F36-H36)/E36 -> -0.0077 | U36: =R36+T36 -> 0.1845 | V36: =U36*E36 -> 18.45 | W36: =SUMIF(GLS!B:B,K36,GLS!C:C) -> 10.72 | Z36: =-IF(W36+X36+Y36=0,"à vérifier",W36+X36+Y36) -> -10.72 | AA36: =IFERROR((SUMIF($K:$K,K36,$Z:$Z)/COUNTIF($K:$K,K36))*E36/SUMIF($K:$K,K36,$E:$E),0) -> -10.72 | AB36: =AA36/E36 -> -0.1072 | AC36: =AB36+U36 -> 0.0773 | AD36: =AC36/R36 -> 0.40218522 | AE36: =AC36*E36 -> 7.73 | AF36: =IFERROR(-ABS(INDEX('frais amazon 011225-150326'!H:H,MATCH(Reproting_ERPALIN!K36,'frais amazon 011225-150326'!D:D,0))/1.2),"Commande hors la France") -> Commande hors la France | AG36: =IFERROR(AF36*E36/SUMIF($K:$K,K36,$E:$E),0) -> 0 | AH36: =AG36/E36 -> 0 | AI36: =AH36+AC36 -> 0.0773 | AJ36: =AI36/R36 -> 0.40218522 | AK36: =AI36*E36 -> 7.73
A37: Abena - Gants d'examen nitrile en bleu non poudrés 240mm - Classic - Boite de 100 pièces L | B37: 1999905274 | C37: Abena | D37: 2025-12-01 | E37: 1000 | F37: 30.7 | G37: 4.99 | H37: 13.5 | I37: 43.97 | J37: FR | K37: 408-7640860-0578732 | L37: =MONTH(D37) -> 12 | M37: =YEAR(D37) -> 2025 | N37: =D37*1 -> 45992 | O37: =F37/E37 -> 0.0307 | P37: =O37*E37 -> 30.7 | Q37: =G37/E37 -> 0.00499 | R37: =O37+Q37 -> 0.03569 | S37: =R37*E37 -> 35.69 | T37: =-(F37-H37)/E37 -> -0.0172 | U37: =R37+T37 -> 0.01849 | V37: =U37*E37 -> 18.49 | W37: =SUMIF(GLS!B:B,K37,GLS!C:C) -> 6.13 | Z37: =-IF(W37+X37+Y37=0,"à vérifier",W37+X37+Y37) -> -6.13 | AA37: =IFERROR((SUMIF($K:$K,K37,$Z:$Z)/COUNTIF($K:$K,K37))*E37/SUMIF($K:$K,K37,$E:$E),0) -> -6.13 | AB37: =AA37/E37 -> -0.00613 | AC37: =AB37+U37 -> 0.01236 | AD37: =AC37/R37 -> 0.34631549 | AE37: =AC37*E37 -> 12.36 | AF37: =IFERROR(-ABS(INDEX('frais amazon 011225-150326'!H:H,MATCH(Reproting_ERPALIN!K37,'frais amazon 011225-150326'!D:D,0))/1.2),"Commande hors la France") -> -6.425 | AG37: =IFERROR(AF37*E37/SUMIF($K:$K,K37,$E:$E),0) -> -6.425 | AH37: =AG37/E37 -> -0.006425 | AI37: =AH37+AC37 -> 0.005935 | AJ37: =AI37/R37 -> 0.16629308 | AK37: =AI37*E37 -> 5.935
A38: Aiguille d'injection sans phtalate - Boite de 100 pièces - 22G - 30 mm | B38: IN-07X30 | C38: ZARYS International Group sp. z o.o. sp.k. | D38: 2026-01-01 | E38: 100 | F38: 12.05 | G38: 4.99 | H38: 11.35 | I38: 94.19 | J38: FR | K38: 408-7491984-3217121 | L38: =MONTH(D38) -> 1 | M38: =YEAR(D38) -> 2026 | N38: =D38*1 -> 46023 | O38: =F38/E38 -> 0.1205 | P38: =O38*E38 -> 12.05 | Q38: =G38/E38 -> 0.0499 | R38: =O38+Q38 -> 0.1704 | S38: =R38*E38 -> 17.04 | T38: =-(F38-H38)/E38 -> -0.007 | U38: =R38+T38 -> 0.1634 | V38: =U38*E38 -> 16.34 | W38: =SUMIF(GLS!B:B,K38,GLS!C:C) -> 5.49 | Z38: =-IF(W38+X38+Y38=0,"à vérifier",W38+X38+Y38) -> -5.49 | AA38: =IFERROR((SUMIF($K:$K,K38,$Z:$Z)/COUNTIF($K:$K,K38))*E38/SUMIF($K:$K,K38,$E:$E),0) -> -5.49 | AB38: =AA38/E38 -> -0.0549 | AC38: =AB38+U38 -> 0.1085 | AD38: =AC38/R38 -> 0.63673709 | AE38: =AC38*E38 -> 10.85 | AF38: =IFERROR(-ABS(INDEX('frais amazon 011225-150326'!H:H,MATCH(Reproting_ERPALIN!K38,'frais amazon 011225-150326'!D:D,0))/1.2),"Commande hors la France") -> -3.1666667 | AG38: =IFERROR(AF38*E38/SUMIF($K:$K,K38,$E:$E),0) -> -3.1666667 | AH38: =AG38/E38 -> -0.031666667 | AI38: =AH38+AC38 -> 0.076833333 | AJ38: =AI38/R38 -> 0.45089984 | AK38: =AI38*E38 -> 7.6833333
A39: Aiguille hypodermique à usage unique non sécurisée 25G, 0,5 mm x 40 mm | B39: IN-05X40 | C39: ZARYS International Group sp. z o.o. sp.k. | D39: 2026-01-01 | E39: 100 | F39: 10.72 | G39: 4.99 | H39: 9.85 | I39: 91.88 | J39: FR | K39: 408-7271559-7642744 | L39: =MONTH(D39) -> 1 | M39: =YEAR(D39) -> 2026 | N39: =D39*1 -> 46023 | O39: =F39/E39 -> 0.1072 | P39: =O39*E39 -> 10.72 | Q39: =G39/E39 -> 0.0499 | R39: =O39+Q39 -> 0.1571 | S39: =R39*E39 -> 15.71 | T39: =-(F39-H39)/E39 -> -0.0087 | U39: =R39+T39 -> 0.1484 | V39: =U39*E39 -> 14.84 | W39: =SUMIF(GLS!B:B,K39,GLS!C:C) -> 5.25 | Z39: =-IF(W39+X39+Y39=0,"à vérifier",W39+X39+Y39) -> -5.25 | AA39: =IFERROR((SUMIF($K:$K,K39,$Z:$Z)/COUNTIF($K:$K,K39))*E39/SUMIF($K:$K,K39,$E:$E),0) -> -5.25 | AB39: =AA39/E39 -> -0.0525 | AC39: =AB39+U39 -> 0.0959 | AD39: =AC39/R39 -> 0.61043921 | AE39: =AC39*E39 -> 9.59 | AF39: =IFERROR(-ABS(INDEX('frais amazon 011225-150326'!H:H,MATCH(Reproting_ERPALIN!K39,'frais amazon 011225-150326'!D:D,0))/1.2),"Commande hors la France") -> -2.9166667 | AG39: =IFERROR(AF39*E39/SUMIF($K:$K,K39,$E:$E),0) -> -2.9166667 | AH39: =AG39/E39 -> -0.029166667 | AI39: =AH39+AC39 -> 0.066733333 | AJ39: =AI39/R39 -> 0.42478252 | AK39: =AI39*E39 -> 6.6733333
A40: Abena - Couches adulte intraversables Maternity Pad Super - Sachet de 15 pièces | B40: 1000022654 | C40: Abena | D40: 2026-01-01 | E40: 15 | F40: 6.93 | G40: 4.99 | H40: 4.79 | I40: 69.16 | J40: FR | K40: 408-7121406-3360337 | L40: =MONTH(D40) -> 1 | M40: =YEAR(D40) -> 2026 | N40: =D40*1 -> 46023 | O40: =F40/E40 -> 0.462 | P40: =O40*E40 -> 6.93 | Q40: =G40/E40 -> 0.33266667 | R40: =O40+Q40 -> 0.79466667 | S40: =R40*E40 -> 11.92 | T40: =-(F40-H40)/E40 -> -0.14266667 | U40: =R40+T40 -> 0.652 | V40: =U40*E40 -> 9.78 | W40: =SUMIF(GLS!B:B,K40,GLS!C:C) -> 5.25 | Z40: =-IF(W40+X40+Y40=0,"à vérifier",W40+X40+Y40) -> -5.25 | AA40: =IFERROR((SUMIF($K:$K,K40,$Z:$Z)/COUNTIF($K:$K,K40))*E40/SUMIF($K:$K,K40,$E:$E),0) -> -5.25 | AB40: =AA40/E40 -> -0.35 | AC40: =AB40+U40 -> 0.302 | AD40: =AC40/R40 -> 0.38003356 | AE40: =AC40*E40 -> 4.53 | AF40: =IFERROR(-ABS(INDEX('frais amazon 011225-150326'!H:H,MATCH(Reproting_ERPALIN!K40,'frais amazon 011225-150326'!D:D,0))/1.2),"Commande hors la France") -> -2.2083333 | AG40: =IFERROR(AF40*E40/SUMIF($K:$K,K40,$E:$E),0) -> -2.2083333 | AH40: =AG40/E40 -> -0.14722222 | AI40: =AH40+AC40 -> 0.15477778 | AJ40: =AI40/R40 -> 0.19477069 | AK40: =AI40*E40 -> 2.3216667
A41: Abena - Couches adulte intraversables Maternity Pad Super - Sachet de 15 pièces | B41: 1000022654 | C41: Abena | D41: 2026-01-01 | E41: 30 | F41: 13.63 | G41: 4.99 | H41: 9.36 | I41: 68.64 | J41: FR | K41: 408-7044132-6785932 | L41: =MONTH(D41) -> 1 | M41: =YEAR(D41) -> 2026 | N41: =D41*1 -> 46023 | O41: =F41/E41 -> 0.45433333 | P41: =O41*E41 -> 13.63 | Q41: =G41/E41 -> 0.16633333 | R41: =O41+Q41 -> 0.62066667 | S41: =R41*E41 -> 18.62 | T41: =-(F41-H41)/E41 -> -0.14233333 | U41: =R41+T41 -> 0.47833333 | V41: =U41*E41 -> 14.35 | W41: =SUMIF(GLS!B:B,K41,GLS!C:C) -> 5.48 | Z41: =-IF(W41+X41+Y41=0,"à vérifier",W41+X41+Y41) -> -5.48 | AA41: =IFERROR((SUMIF($K:$K,K41,$Z:$Z)/COUNTIF($K:$K,K41))*E41/SUMIF($K:$K,K41,$E:$E),0) -> -5.48 | AB41: =AA41/E41 -> -0.18266667 | AC41: =AB41+U41 -> 0.29566667 | AD41: =AC41/R41 -> 0.4763695 | AE41: =AC41*E41 -> 8.87 | AF41: =IFERROR(-ABS(INDEX('frais amazon 011225-150326'!H:H,MATCH(Reproting_ERPALIN!K41,'frais amazon 011225-150326'!D:D,0))/1.2),"Commande hors la France") -> -3.4583333 | AG41: =IFERROR(AF41*E41/SUMIF($K:$K,K41,$E:$E),0) -> -3.4583333 | AH41: =AG41/E41 -> -0.11527778 | AI41: =AH41+AC41 -> 0.18038889 | AJ41: =AI41/R41 -> 0.29063731 | AK41: =AI41*E41 -> 5.4116667
A42: Abena - Couches adulte intraversables Maternity Pad Super - Sachet de 15 pièces | B42: 1000022654 | C42: Abena | D42: 2026-02-01 | E42: 30 | F42: 13.49 | G42: 0 | H42: 9.22 | I42: 68.31 | J42: FR | K42: 408-6637906-4315557 | L42: =MONTH(D42) -> 2 | M42: =YEAR(D42) -> 2026 | N42: =D42*1 -> 46054 | O42: =F42/E42 -> 0.44966667 | P42: =O42*E42 -> 13.49 | Q42: =G42/E42 -> 0 | R42: =O42+Q42 -> 0.44966667 | S42: =R42*E42 -> 13.49 | T42: =-(F42-H42)/E42 -> -0.14233333 | U42: =R42+T42 -> 0.30733333 | V42: =U42*E42 -> 9.22 | W42: =SUMIF(GLS!B:B,K42,GLS!C:C) -> 5.25 | Z42: =-IF(W42+X42+Y42=0,"à vérifier",W42+X42+Y42) -> -5.25 | AA42: =IFERROR((SUMIF($K:$K,K42,$Z:$Z)/COUNTIF($K:$K,K42))*E42/SUMIF($K:$K,K42,$E:$E),0) -> -5.25 | AB42: =AA42/E42 -> -0.175 | AC42: =AB42+U42 -> 0.13233333 | AD42: =AC42/R42 -> 0.29429207 | AE42: =AC42*E42 -> 3.97 | AF42: =IFERROR(-ABS(INDEX('frais amazon 011225-150326'!H:H,MATCH(Reproting_ERPALIN!K42,'frais amazon 011225-150326'!D:D,0))/1.2),"Commande hors la France") -> -2.4916667 | AG42: =IFERROR(AF42*E42/SUMIF($K:$K,K42,$E:$E),0) -> -2.4916667 | AH42: =AG42/E42 -> -0.083055556 | AI42: =AH42+AC42 -> 0.049277778 | AJ42: =AI42/R42 -> 0.10958735 | AK42: =AI42*E42 -> 1.4783333
A43: Seringue à insuline, stérile - Boite de 100 pièces - Rouge | B43: IN-U40-1-BL | C43: ZARYS International Group sp. z o.o. sp.k. | D43: 2026-01-01 | E43: 100 | F43: 19.51 | G43: 16.58 | H43: 17.4 | I43: 89.19 | J43: IT | K43: 408-6527931-4840314 | L43: =MONTH(D43) -> 1 | M43: =YEAR(D43) -> 2026 | N43: =D43*1 -> 46023 | O43: =F43/E43 -> 0.1951 | P43: =O43*E43 -> 19.51 | Q43: =G43/E43 -> 0.1658 | R43: =O43+Q43 -> 0.3609 | S43: =R43*E43 -> 36.09 | T43: =-(F43-H43)/E43 -> -0.0211 | U43: =R43+T43 -> 0.3398 | V43: =U43*E43 -> 33.98 | W43: =SUMIF(GLS!B:B,K43,GLS!C:C) -> 10.72 | Z43: =-IF(W43+X43+Y43=0,"à vérifier",W43+X43+Y43) -> -10.72 | AA43: =IFERROR((SUMIF($K:$K,K43,$Z:$Z)/COUNTIF($K:$K,K43))*E43/SUMIF($K:$K,K43,$E:$E),0) -> -10.72 | AB43: =AA43/E43 -> -0.1072 | AC43: =AB43+U43 -> 0.2326 | AD43: =AC43/R43 -> 0.64449986 | AE43: =AC43*E43 -> 23.26 | AF43: =IFERROR(-ABS(INDEX('frais amazon 011225-150326'!H:H,MATCH(Reproting_ERPALIN!K43,'frais amazon 011225-150326'!D:D,0))/1.2),"Commande hors la France") -> Commande hors la France | AG43: =IFERROR(AF43*E43/SUMIF($K:$K,K43,$E:$E),0) -> 0 | AH43: =AG43/E43 -> 0 | AI43: =AH43+AC43 -> 0.2326 | AJ43: =AI43/R43 -> 0.64449986 | AK43: =AI43*E43 -> 23.26
A44: Seringue à insuline, stérile - Boite de 100 pièces - Orangé | B44: IN-U100-1-BL | C44: ZARYS International Group sp. z o.o. sp.k. | D44: 2026-02-01 | E44: 100 | F44: 21.53 | G44: 4.99 | H44: 19.37 | I44: 89.97 | J44: FR | K44: 408-6461783-9435520 | L44: =MONTH(D44) -> 2 | M44: =YEAR(D44) -> 2026 | N44: =D44*1 -> 46054 | O44: =F44/E44 -> 0.2153 | P44: =O44*E44 -> 21.53 | Q44: =G44/E44 -> 0.0499 | R44: =O44+Q44 -> 0.2652 | S44: =R44*E44 -> 26.52 | T44: =-(F44-H44)/E44 -> -0.0216 | U44: =R44+T44 -> 0.2436 | V44: =U44*E44 -> 24.36 | W44: =SUMIF(GLS!B:B,K44,GLS!C:C) -> 5.25 | Z44: =-IF(W44+X44+Y44=0,"à vérifier",W44+X44+Y44) -> -5.25 | AA44: =IFERROR((SUMIF($K:$K,K44,$Z:$Z)/COUNTIF($K:$K,K44))*E44/SUMIF($K:$K,K44,$E:$E),0) -> -5.25 | AB44: =AA44/E44 -> -0.0525 | AC44: =AB44+U44 -> 0.1911 | AD44: =AC44/R44 -> 0.72058824 | AE44: =AC44*E44 -> 19.11 | AF44: =IFERROR(-ABS(INDEX('frais amazon 011225-150326'!H:H,MATCH(Reproting_ERPALIN!K44,'frais amazon 011225-150326'!D:D,0))/1.2),"Commande hors la France") -> -4.45 | AG44: =IFERROR(AF44*E44/SUMIF($K:$K,K44,$E:$E),0) -> -4.45 | AH44: =AG44/E44 -> -0.0445 | AI44: =AH44+AC44 -> 0.1466 | AJ44: =AI44/R44 -> 0.55279035 | AK44: =AI44*E44 -> 14.66
A45: ONTEX - Slip absorbant iD Pants Plus - Sachet de 14 pièces - XL / carton de 56 pièces | B45: 5531465140-03 | C45: Ontex Santé France | D45: 2026-01-01 | E45: 14 | F45: 20.61 | G45: 4.99 | H45: 9.27 | I45: 44.97 | J45: FR | K45: 408-6341014-6641114 | L45: =MONTH(D45) -> 1 | M45: =YEAR(D45) -> 2026 | N45: =D45*1 -> 46023 | O45: =F45/E45 -> 1.4721429 | P45: =O45*E45 -> 20.61 | Q45: =G45/E45 -> 0.35642857 | R45: =O45+Q45 -> 1.8285714 | S45: =R45*E45 -> 25.6 | T45: =-(F45-H45)/E45 -> -0.81 | U45: =R45+T45 -> 1.0185714 | V45: =U45*E45 -> 14.26 | W45: =SUMIF(GLS!B:B,K45,GLS!C:C) -> 5.48 | Z45: =-IF(W45+X45+Y45=0,"à vérifier",W45+X45+Y45) -> -5.48 | AA45: =IFERROR((SUMIF($K:$K,K45,$Z:$Z)/COUNTIF($K:$K,K45))*E45/SUMIF($K:$K,K45,$E:$E),0) -> -5.48 | AB45: =AA45/E45 -> -0.39142857 | AC45: =AB45+U45 -> 0.62714286 | AD45: =AC45/R45 -> 0.34296875 | AE45: =AC45*E45 -> 8.78 | AF45: =IFERROR(-ABS(INDEX('frais amazon 011225-150326'!H:H,MATCH(Reproting_ERPALIN!K45,'frais amazon 011225-150326'!D:D,0))/1.2),"Commande hors la France") -> -4.7583333 | AG45: =IFERROR(AF45*E45/SUMIF($K:$K,K45,$E:$E),0) -> -4.7583333 | AH45: =AG45/E45 -> -0.33988095 | AI45: =AH45+AC45 -> 0.2872619 | AJ45: =AI45/R45 -> 0.15709635 | AK45: =AI45*E45 -> 4.0216667
A46: Abena - Couches adulte intraversables Maternity Pad Super - Sachet de 15 pièces | B46: 1000022654 | C46: Abena | D46: 2026-02-01 | E46: 30 | F46: 13.49 | G46: 0 | H46: 9.22 | I46: 68.31 | J46: FR | K46: 408-6275839-8263552 | L46: =MONTH(D46) -> 2 | M46: =YEAR(D46) -> 2026 | N46: =D46*1 -> 46054 | O46: =F46/E46 -> 0.44966667 | P46: =O46*E46 -> 13.49 | Q46: =G46/E46 -> 0 | R46: =O46+Q46 -> 0.44966667 | S46: =R46*E46 -> 13.49 | T46: =-(F46-H46)/E46 -> -0.14233333 | U46: =R46+T46 -> 0.30733333 | V46: =U46*E46 -> 9.22 | W46: =SUMIF(GLS!B:B,K46,GLS!C:C) -> 5.48 | Z46: =-IF(W46+X46+Y46=0,"à vérifier",W46+X46+Y46) -> -5.48 | AA46: =IFERROR((SUMIF($K:$K,K46,$Z:$Z)/COUNTIF($K:$K,K46))*E46/SUMIF($K:$K,K46,$E:$E),0) -> -5.48 | AB46: =AA46/E46 -> -0.18266667 | AC46: =AB46+U46 -> 0.12466667 | AD46: =AC46/R46 -> 0.2772424 | AE46: =AC46*E46 -> 3.74 | AF46: =IFERROR(-ABS(INDEX('frais amazon 011225-150326'!H:H,MATCH(Reproting_ERPALIN!K46,'frais amazon 011225-150326'!D:D,0))/1.2),"Commande hors la France") -> -2.4916667 | AG46: =IFERROR(AF46*E46/SUMIF($K:$K,K46,$E:$E),0) -> -2.4916667 | AH46: =AG46/E46 -> -0.083055556 | AI46: =AH46+AC46 -> 0.041611111 | AJ46: =AI46/R46 -> 0.092537682 | AK46: =AI46*E46 -> 1.2483333
A47: ZARYS - Aiguille pour stylo à insuline stérile 29 G x 12 mm - Boite de 100 pièces | B47: INP-033X12 | C47: ZARYS International Group sp. z o.o. sp.k. | D47: 2025-12-01 | E47: 100 | F47: 12.47 | G47: 4.99 | H47: 9.79 | I47: 78.51 | J47: FR | K47: 408-6273121-3482724 | L47: =MONTH(D47) -> 12 | M47: =YEAR(D47) -> 2025 | N47: =D47*1 -> 45992 | O47: =F47/E47 -> 0.1247 | P47: =O47*E47 -> 12.47 | Q47: =G47/E47 -> 0.0499 | R47: =O47+Q47 -> 0.1746 | S47: =R47*E47 -> 17.46 | T47: =-(F47-H47)/E47 -> -0.0268 | U47: =R47+T47 -> 0.1478 | V47: =U47*E47 -> 14.78 | W47: =SUMIF(GLS!B:B,K47,GLS!C:C) -> 5.25 | Z47: =-IF(W47+X47+Y47=0,"à vérifier",W47+X47+Y47) -> -5.25 | AA47: =IFERROR((SUMIF($K:$K,K47,$Z:$Z)/COUNTIF($K:$K,K47))*E47/SUMIF($K:$K,K47,$E:$E),0) -> -5.25 | AB47: =AA47/E47 -> -0.0525 | AC47: =AB47+U47 -> 0.0953 | AD47: =AC47/R47 -> 0.54581901 | AE47: =AC47*E47 -> 9.53 | AF47: =IFERROR(-ABS(INDEX('frais amazon 011225-150326'!H:H,MATCH(Reproting_ERPALIN!K47,'frais amazon 011225-150326'!D:D,0))/1.2),"Commande hors la France") -> -3.2333333 | AG47: =IFERROR(AF47*E47/SUMIF($K:$K,K47,$E:$E),0) -> -3.2333333 | AH47: =AG47/E47 -> -0.032333333 | AI47: =AH47+AC47 -> 0.062966667 | AJ47: =AI47/R47 -> 0.36063383 | AK47: =AI47*E47 -> 6.2966667
A48: HARTMANN - Samu Maxi Plus - Pansement gynécologique 11 X 35cm - Boite de 56 pièces | B48: 716313 | C48: Hartmann | D48: 2026-02-01 | E48: 56 | F48: 12.09 | G48: 4.99 | H48: 5.67 | I48: 46.92 | J48: FR | K48: 408-6255953-9458728 | L48: =MONTH(D48) -> 2 | M48: =YEAR(D48) -> 2026 | N48: =D48*1 -> 46054 | O48: =F48/E48 -> 0.21589286 | P48: =O48*E48 -> 12.09 | Q48: =G48/E48 -> 0.089107143 | R48: =O48+Q48 -> 0.305 | S48: =R48*E48 -> 17.08 | T48: =-(F48-H48)/E48 -> -0.11464286 | U48: =R48+T48 -> 0.19035714 | V48: =U48*E48 -> 10.66 | W48: =SUMIF(GLS!B:B,K48,GLS!C:C) -> 5.48 | Z48: =-IF(W48+X48+Y48=0,"à vérifier",W48+X48+Y48) -> -5.48 | AA48: =IFERROR((SUMIF($K:$K,K48,$Z:$Z)/COUNTIF($K:$K,K48))*E48/SUMIF($K:$K,K48,$E:$E),0) -> -5.48 | AB48: =AA48/E48 -> -0.097857143 | AC48: =AB48+U48 -> 0.0925 | AD48: =AC48/R48 -> 0.30327869 | AE48: =AC48*E48 -> 5.18 | AF48: =IFERROR(-ABS(INDEX('frais amazon 011225-150326'!H:H,MATCH(Reproting_ERPALIN!K48,'frais amazon 011225-150326'!D:D,0))/1.2),"Commande hors la France") -> -3.1583333 | AG48: =IFERROR(AF48*E48/SUMIF($K:$K,K48,$E:$E),0) -> -3.1583333 | AH48: =AG48/E48 -> -0.05639881 | AI48: =AH48+AC48 -> 0.03610119 | AJ48: =AI48/R48 -> 0.11836456 | AK48: =AI48*E48 -> 2.0216667
A49: Tena - Couche adulte - Slip ProSkin Plus XS - Sachet de 30 pièces | B49: 710473 | C49: TENA | D49: 2026-01-01 | E49: 30 | F49: 16.04 | G49: 4.99 | H49: 3.59 | I49: 22.4 | J49: FR | K49: 408-6236851-3925145 | L49: =MONTH(D49) -> 1 | M49: =YEAR(D49) -> 2026 | N49: =D49*1 -> 46023 | O49: =F49/E49 -> 0.53466667 | P49: =O49*E49 -> 16.04 | Q49: =G49/E49 -> 0.16633333 | R49: =O49+Q49 -> 0.701 | S49: =R49*E49 -> 21.03 | T49: =-(F49-H49)/E49 -> -0.415 | U49: =R49+T49 -> 0.286 | V49: =U49*E49 -> 8.58 | W49: =SUMIF(GLS!B:B,K49,GLS!C:C) -> 5.49 | Z49: =-IF(W49+X49+Y49=0,"à vérifier",W49+X49+Y49) -> -5.49 | AA49: =IFERROR((SUMIF($K:$K,K49,$Z:$Z)/COUNTIF($K:$K,K49))*E49/SUMIF($K:$K,K49,$E:$E),0) -> -5.49 | AB49: =AA49/E49 -> -0.183 | AC49: =AB49+U49 -> 0.103 | AD49: =AC49/R49 -> 0.14693295 | AE49: =AC49*E49 -> 3.09 | AF49: =IFERROR(-ABS(INDEX('frais amazon 011225-150326'!H:H,MATCH(Reproting_ERPALIN!K49,'frais amazon 011225-150326'!D:D,0))/1.2),"Commande hors la France") -> -3.8916667 | AG49: =IFERROR(AF49*E49/SUMIF($K:$K,K49,$E:$E),0) -> -3.8916667 | AH49: =AG49/E49 -> -0.12972222 | AI49: =AH49+AC49 -> -0.026722222 | AJ49: =AI49/R49 -> -0.038120146 | AK49: =AI49*E49 -> -0.80166667
A50: Aiguille hypodermique à usage unique non sécurisée 26G, 0,45 mm x 16 mm | B50: IN-045X16 | C50: ZARYS International Group sp. z o.o. sp.k. | D50: 2026-02-01 | E50: 100 | F50: 10.19 | G50: 8.68 | H50: 9.18 | I50: 90.09 | J50: ES | K50: 408-5981551-5808365 | L50: =MONTH(D50) -> 2 | M50: =YEAR(D50) -> 2026 | N50: =D50*1 -> 46054 | O50: =F50/E50 -> 0.1019 | P50: =O50*E50 -> 10.19 | Q50: =G50/E50 -> 0.0868 | R50: =O50+Q50 -> 0.1887 | S50: =R50*E50 -> 18.87 | T50: =-(F50-H50)/E50 -> -0.0101 | U50: =R50+T50 -> 0.1786 | V50: =U50*E50 -> 17.86 | W50: =SUMIF(GLS!B:B,K50,GLS!C:C) -> 10.72 | Z50: =-IF(W50+X50+Y50=0,"à vérifier",W50+X50+Y50) -> -10.72 | AA50: =IFERROR((SUMIF($K:$K,K50,$Z:$Z)/COUNTIF($K:$K,K50))*E50/SUMIF($K:$K,K50,$E:$E),0) -> -10.72 | AB50: =AA50/E50 -> -0.1072 | AC50: =AB50+U50 -> 0.0714 | AD50: =AC50/R50 -> 0.37837838 | AE50: =AC50*E50 -> 7.14 | AF50: =IFERROR(-ABS(INDEX('frais amazon 011225-150326'!H:H,MATCH(Reproting_ERPALIN!K50,'frais amazon 011225-150326'!D:D,0))/1.2),"Commande hors la France") -> Commande hors la France | AG50: =IFERROR(AF50*E50/SUMIF($K:$K,K50,$E:$E),0) -> 0 | AH50: =AG50/E50 -> 0 | AI50: =AH50+AC50 -> 0.0714 | AJ50: =AI50/R50 -> 0.37837838 | AK50: =AI50*E50 -> 7.14
A51: HARTMANN - MoliCare - Couche adulte 6 Gouttes - Premium Elastic, Large - Sachet de 30 pièces | B51: 165273 | C51: Hartmann | D51: 2026-01-01 | E51: 120 | F51: 110.23 | G51: 0 | H51: 49.27 | I51: 44.7 | J51: FR | K51: 408-5814323-4233141 | L51: =MONTH(D51) -> 1 | M51: =YEAR(D51) -> 2026 | N51: =D51*1 -> 46023 | O51: =F51/E51 -> 0.91858333 | P51: =O51*E51 -> 110.23 | Q51: =G51/E51 -> 0 | R51: =O51+Q51 -> 0.91858333 | S51: =R51*E51 -> 110.23 | T51: =-(F51-H51)/E51 -> -0.508 | U51: =R51+T51 -> 0.41058333 | V51: =U51*E51 -> 49.27 | W51: =SUMIF(GLS!B:B,K51,GLS!C:C) -> 16.32 | Z51: =-IF(W51+X51+Y51=0,"à vérifier",W51+X51+Y51) -> -16.32 | AA51: =IFERROR((SUMIF($K:$K,K51,$Z:$Z)/COUNTIF($K:$K,K51))*E51/SUMIF($K:$K,K51,$E:$E),0) -> -16.32 | AB51: =AA51/E51 -> -0.136 | AC51: =AB51+U51 -> 0.27458333 | AD51: =AC51/R51 -> 0.29892044 | AE51: =AC51*E51 -> 32.95 | AF51: =IFERROR(-ABS(INDEX('frais amazon 011225-150326'!H:H,MATCH(Reproting_ERPALIN!K51,'frais amazon 011225-150326'!D:D,0))/1.2),"Commande hors la France") -> -20.433333 | AG51: =IFERROR(AF51*E51/SUMIF($K:$K,K51,$E:$E),0) -> -20.433333 | AH51: =AG51/E51 -> -0.17027778 | AI51: =AH51+AC51 -> 0.10430556 | AJ51: =AI51/R51 -> 0.11355046 | AK51: =AI51*E51 -> 12.516667
A52: ZARYS - Seringue à usage unique en 3 parties luer avec aiguille stérile 2 ml buse centrique 0.6mm x 30mm bleu foncé - Boite de 100 pcs | B52: 002ML-3CZ-SN | C52: ZARYS International Group sp. z o.o. sp.k. | D52: 2026-02-01 | E52: 100 | F52: 9.18 | G52: 4.99 | H52: 7.04 | I52: 76.69 | J52: FR | K52: 408-5813984-5560340 | L52: =MONTH(D52) -> 2 | M52: =YEAR(D52) -> 2026 | N52: =D52*1 -> 46054 | O52: =F52/E52 -> 0.0918 | P52: =O52*E52 -> 9.18 | Q52: =G52/E52 -> 0.0499 | R52: =O52+Q52 -> 0.1417 | S52: =R52*E52 -> 14.17 | T52: =-(F52-H52)/E52 -> -0.0214 | U52: =R52+T52 -> 0.1203 | V52: =U52*E52 -> 12.03 | W52: =SUMIF(GLS!B:B,K52,GLS!C:C) -> 5.25 | Z52: =-IF(W52+X52+Y52=0,"à vérifier",W52+X52+Y52) -> -5.25 | AA52: =IFERROR((SUMIF($K:$K,K52,$Z:$Z)/COUNTIF($K:$K,K52))*E52/SUMIF($K:$K,K52,$E:$E),0) -> -5.25 | AB52: =AA52/E52 -> -0.0525 | AC52: =AB52+U52 -> 0.0678 | AD52: =AC52/R52 -> 0.47847565 | AE52: =AC52*E52 -> 6.78 | AF52: =IFERROR(-ABS(INDEX('frais amazon 011225-150326'!H:H,MATCH(Reproting_ERPALIN!K52,'frais amazon 011225-150326'!D:D,0))/1.2),"Commande hors la France") -> -2.6333333 | AG52: =IFERROR(AF52*E52/SUMIF($K:$K,K52,$E:$E),0) -> -2.6333333 | AH52: =AG52/E52 -> -0.026333333 | AI52: =AH52+AC52 -> 0.041466667 | AJ52: =AI52/R52 -> 0.29263703 | AK52: =AI52*E52 -> 4.1466667
A53: Aiguille hypodermique à usage unique non sécurisée 21G, 0,8 mm x 50 mm | B53: IN-08X50 | C53: ZARYS International Group sp. z o.o. sp.k. | D53: 2026-01-01 | E53: 100 | F53: 12.98 | G53: 4.99 | H53: 11.52 | I53: 88.75 | J53: FR | K53: 408-5783181-2285141 | L53: =MONTH(D53) -> 1 | M53: =YEAR(D53) -> 2026 | N53: =D53*1 -> 46023 | O53: =F53/E53 -> 0.1298 | P53: =O53*E53 -> 12.98 | Q53: =G53/E53 -> 0.0499 | R53: =O53+Q53 -> 0.1797 | S53: =R53*E53 -> 17.97 | T53: =-(F53-H53)/E53 -> -0.0146 | U53: =R53+T53 -> 0.1651 | V53: =U53*E53 -> 16.51 | W53: =SUMIF(GLS!B:B,K53,GLS!C:C) -> 5.25 | Z53: =-IF(W53+X53+Y53=0,"à vérifier",W53+X53+Y53) -> -5.25 | AA53: =IFERROR((SUMIF($K:$K,K53,$Z:$Z)/COUNTIF($K:$K,K53))*E53/SUMIF($K:$K,K53,$E:$E),0) -> -5.25 | AB53: =AA53/E53 -> -0.0525 | AC53: =AB53+U53 -> 0.1126 | AD53: =AC53/R53 -> 0.62659989 | AE53: =AC53*E53 -> 11.26 | AF53: =IFERROR(-ABS(INDEX('frais amazon 011225-150326'!H:H,MATCH(Reproting_ERPALIN!K53,'frais amazon 011225-150326'!D:D,0))/1.2),"Commande hors la France") -> -3.3333333 | AG53: =IFERROR(AF53*E53/SUMIF($K:$K,K53,$E:$E),0) -> -3.3333333 | AH53: =AG53/E53 -> -0.033333333 | AI53: =AH53+AC53 -> 0.079266667 | AJ53: =AI53/R53 -> 0.44110555 | AK53: =AI53*E53 -> 7.9266667
A54: AIGUILLE HYPODERMIQUE 21G 25MM | B54: IN-08X25 | C54: ZARYS International Group sp. z o.o. sp.k. | D54: 2026-01-01 | E54: 100 | F54: 10.32 | G54: 4.99 | H54: 9.61 | I54: 93.12 | J54: FR | K54: 408-5773707-5530708 | L54: =MONTH(D54) -> 1 | M54: =YEAR(D54) -> 2026 | N54: =D54*1 -> 46023 | O54: =F54/E54 -> 0.1032 | P54: =O54*E54 -> 10.32 | Q54: =G54/E54 -> 0.0499 | R54: =O54+Q54 -> 0.1531 | S54: =R54*E54 -> 15.31 | T54: =-(F54-H54)/E54 -> -0.0071 | U54: =R54+T54 -> 0.146 | V54: =U54*E54 -> 14.6 | W54: =SUMIF(GLS!B:B,K54,GLS!C:C) -> 5.25 | Z54: =-IF(W54+X54+Y54=0,"à vérifier",W54+X54+Y54) -> -5.25 | AA54: =IFERROR((SUMIF($K:$K,K54,$Z:$Z)/COUNTIF($K:$K,K54))*E54/SUMIF($K:$K,K54,$E:$E),0) -> -5.25 | AB54: =AA54/E54 -> -0.0525 | AC54: =AB54+U54 -> 0.0935 | AD54: =AC54/R54 -> 0.61071195 | AE54: =AC54*E54 -> 9.35 | AF54: =IFERROR(-ABS(INDEX('frais amazon 011225-150326'!H:H,MATCH(Reproting_ERPALIN!K54,'frais amazon 011225-150326'!D:D,0))/1.2),"Commande hors la France") -> -2.85 | AG54: =IFERROR(AF54*E54/SUMIF($K:$K,K54,$E:$E),0) -> -2.85 | AH54: =AG54/E54 -> -0.0285 | AI54: =AH54+AC54 -> 0.065 | AJ54: =AI54/R54 -> 0.42455911 | AK54: =AI54*E54 -> 6.5
A55: HARTMANN - MoliCare Rectangular - Protection absorbante droite - Sachet de 28 pièces | B55: 160860 | C55: Hartmann | D55: 2025-12-01 | E55: 56 | F55: 18.32 | G55: 4.99 | H55: 7.88 | I55: 43.02 | J55: FR | K55: 408-5548280-3261910 | L55: =MONTH(D55) -> 12 | M55: =YEAR(D55) -> 2025 | N55: =D55*1 -> 45992 | O55: =F55/E55 -> 0.32714286 | P55: =O55*E55 -> 18.32 | Q55: =G55/E55 -> 0.089107143 | R55: =O55+Q55 -> 0.41625 | S55: =R55*E55 -> 23.31 | T55: =-(F55-H55)/E55 -> -0.18642857 | U55: =R55+T55 -> 0.22982143 | V55: =U55*E55 -> 12.87 | W55: =SUMIF(GLS!B:B,K55,GLS!C:C) -> 5.5 | Z55: =-IF(W55+X55+Y55=0,"à vérifier",W55+X55+Y55) -> -5.5 | AA55: =IFERROR((SUMIF($K:$K,K55,$Z:$Z)/COUNTIF($K:$K,K55))*E55/SUMIF($K:$K,K55,$E:$E),0) -> -5.5 | AB55: =AA55/E55 -> -0.098214286 | AC55: =AB55+U55 -> 0.13160714 | AD55: =AC55/R55 -> 0.31617332 | AE55: =AC55*E55 -> 7.37 | AF55: =IFERROR(-ABS(INDEX('frais amazon 011225-150326'!H:H,MATCH(Reproting_ERPALIN!K55,'frais amazon 011225-150326'!D:D,0))/1.2),"Commande hors la France") -> -4.3333333 | AG55: =IFERROR(AF55*E55/SUMIF($K:$K,K55,$E:$E),0) -> -4.3333333 | AH55: =AG55/E55 -> -0.077380952 | AI55: =AH55+AC55 -> 0.05422619 | AJ55: =AI55/R55 -> 0.13027313 | AK55: =AI55*E55 -> 3.0366667
A56: Abena - Couches adulte intraversables Maternity Pad Super - Sachet de 15 pièces | B56: 1000022654 | C56: Abena | D56: 2026-01-01 | E56: 60 | F56: 29.59 | G56: 0 | H56: 21.04 | I56: 71.11 | J56: FR | K56: 408-5526873-5797137 | L56: =MONTH(D56) -> 1 | M56: =YEAR(D56) -> 2026 | N56: =D56*1 -> 46023 | O56: =F56/E56 -> 0.49316667 | P56: =O56*E56 -> 29.59 | Q56: =G56/E56 -> 0 | R56: =O56+Q56 -> 0.49316667 | S56: =R56*E56 -> 29.59 | T56: =-(F56-H56)/E56 -> -0.1425 | U56: =R56+T56 -> 0.35066667 | V56: =U56*E56 -> 21.04 | W56: =SUMIF(GLS!B:B,K56,GLS!C:C) -> 5.49 | Z56: =-IF(W56+X56+Y56=0,"à vérifier",W56+X56+Y56) -> -5.49 | AA56: =IFERROR((SUMIF($K:$K,K56,$Z:$Z)/COUNTIF($K:$K,K56))*E56/SUMIF($K:$K,K56,$E:$E),0) -> -5.49 | AB56: =AA56/E56 -> -0.0915 | AC56: =AB56+U56 -> 0.25916667 | AD56: =AC56/R56 -> 0.52551538 | AE56: =AC56*E56 -> 15.55 | AF56: =IFERROR(-ABS(INDEX('frais amazon 011225-150326'!H:H,MATCH(Reproting_ERPALIN!K56,'frais amazon 011225-150326'!D:D,0))/1.2),"Commande hors la France") -> -5.475 | AG56: =IFERROR(AF56*E56/SUMIF($K:$K,K56,$E:$E),0) -> -5.475 | AH56: =AG56/E56 -> -0.09125 | AI56: =AH56+AC56 -> 0.16791667 | AJ56: =AI56/R56 -> 0.34048665 | AK56: =AI56*E56 -> 10.075
A57: Abena - Couches adulte intraversables Maternity Pad Super - Sachet de 15 pièces | B57: 1000022654 | C57: Abena | D57: 2026-02-01 | E57: 30 | F57: 13.49 | G57: 0 | H57: 9.22 | I57: 68.31 | J57: FR | K57: 408-5461293-8271503 | L57: =MONTH(D57) -> 2 | M57: =YEAR(D57) -> 2026 | N57: =D57*1 -> 46054 | O57: =F57/E57 -> 0.44966667 | P57: =O57*E57 -> 13.49 | Q57: =G57/E57 -> 0 | R57: =O57+Q57 -> 0.44966667 | S57: =R57*E57 -> 13.49 | T57: =-(F57-H57)/E57 -> -0.14233333 | U57: =R57+T57 -> 0.30733333 | V57: =U57*E57 -> 9.22 | W57: =SUMIF(GLS!B:B,K57,GLS!C:C) -> 5.48 | Z57: =-IF(W57+X57+Y57=0,"à vérifier",W57+X57+Y57) -> -5.48 | AA57: =IFERROR((SUMIF($K:$K,K57,$Z:$Z)/COUNTIF($K:$K,K57))*E57/SUMIF($K:$K,K57,$E:$E),0) -> -5.48 | AB57: =AA57/E57 -> -0.18266667 | AC57: =AB57+U57 -> 0.12466667 | AD57: =AC57/R57 -> 0.2772424 | AE57: =AC57*E57 -> 3.74 | AF57: =IFERROR(-ABS(INDEX('frais amazon 011225-150326'!H:H,MATCH(Reproting_ERPALIN!K57,'frais amazon 011225-150326'!D:D,0))/1.2),"Commande hors la France") -> -2.4916667 | AG57: =IFERROR(AF57*E57/SUMIF($K:$K,K57,$E:$E),0) -> -2.4916667 | AH57: =AG57/E57 -> -0.083055556 | AI57: =AH57+AC57 -> 0.041611111 | AJ57: =AI57/R57 -> 0.092537682 | AK57: =AI57*E57 -> 1.2483333
A58: Aiguille d'injection sans phtalate - Boite de 100 pièces - 30G - 13 mm | B58: IN-03X13 | C58: ZARYS International Group sp. z o.o. sp.k. | D58: 2026-01-01 | E58: 100 | F58: 10.37 | G58: 8.75 | H58: 9.55 | I58: 92.09 | J58: NL | K58: 408-5457356-1682710 | L58: =MONTH(D58) -> 1 | M58: =YEAR(D58) -> 2026 | N58: =D58*1 -> 46023 | O58: =F58/E58 -> 0.1037 | P58: =O58*E58 -> 10.37 | Q58: =G58/E58 -> 0.0875 | R58: =O58+Q58 -> 0.1912 | S58: =R58*E58 -> 19.12 | T58: =-(F58-H58)/E58 -> -0.0082 | U58: =R58+T58 -> 0.183 | V58: =U58*E58 -> 18.3 | W58: =SUMIF(GLS!B:B,K58,GLS!C:C) -> 9.39 | Z58: =-IF(W58+X58+Y58=0,"à vérifier",W58+X58+Y58) -> -9.39 | AA58: =IFERROR((SUMIF($K:$K,K58,$Z:$Z)/COUNTIF($K:$K,K58))*E58/SUMIF($K:$K,K58,$E:$E),0) -> -9.39 | AB58: =AA58/E58 -> -0.0939 | AC58: =AB58+U58 -> 0.0891 | AD58: =AC58/R58 -> 0.46600418 | AE58: =AC58*E58 -> 8.91 | AF58: =IFERROR(-ABS(INDEX('frais amazon 011225-150326'!H:H,MATCH(Reproting_ERPALIN!K58,'frais amazon 011225-150326'!D:D,0))/1.2),"Commande hors la France") -> Commande hors la France | AG58: =IFERROR(AF58*E58/SUMIF($K:$K,K58,$E:$E),0) -> 0 | AH58: =AG58/E58 -> 0 | AI58: =AH58+AC58 -> 0.0891 | AJ58: =AI58/R58 -> 0.46600418 | AK58: =AI58*E58 -> 8.91
A59: Abena - Couches adulte intraversables Maternity Pad Super - Sachet de 15 pièces | B59: 1000022654 | C59: Abena | D59: 2026-02-01 | E59: 30 | F59: 13.49 | G59: 0 | H59: 9.22 | I59: 68.31 | J59: FR | K59: 408-5221931-1219561 | L59: =MONTH(D59) -> 2 | M59: =YEAR(D59) -> 2026 | N59: =D59*1 -> 46054 | O59: =F59/E59 -> 0.44966667 | P59: =O59*E59 -> 13.49 | Q59: =G59/E59 -> 0 | R59: =O59+Q59 -> 0.44966667 | S59: =R59*E59 -> 13.49 | T59: =-(F59-H59)/E59 -> -0.14233333 | U59: =R59+T59 -> 0.30733333 | V59: =U59*E59 -> 9.22 | W59: =SUMIF(GLS!B:B,K59,GLS!C:C) -> 5.48 | Z59: =-IF(W59+X59+Y59=0,"à vérifier",W59+X59+Y59) -> -5.48 | AA59: =IFERROR((SUMIF($K:$K,K59,$Z:$Z)/COUNTIF($K:$K,K59))*E59/SUMIF($K:$K,K59,$E:$E),0) -> -5.48 | AB59: =AA59/E59 -> -0.18266667 | AC59: =AB59+U59 -> 0.12466667 | AD59: =AC59/R59 -> 0.2772424 | AE59: =AC59*E59 -> 3.74 | AF59: =IFERROR(-ABS(INDEX('frais amazon 011225-150326'!H:H,MATCH(Reproting_ERPALIN!K59,'frais amazon 011225-150326'!D:D,0))/1.2),"Commande hors la France") -> -2.5083333 | AG59: =IFERROR(AF59*E59/SUMIF($K:$K,K59,$E:$E),0) -> -2.5083333 | AH59: =AG59/E59 -> -0.083611111 | AI59: =AH59+AC59 -> 0.041055556 | AJ59: =AI59/R59 -> 0.091302199 | AK59: =AI59*E59 -> 1.2316667
A60: Seringue à insuline, stérile - Boite de 100 pièces - Rouge | B60: IN-U40-1-BL | C60: ZARYS International Group sp. z o.o. sp.k. | D60: 2025-12-01 | E60: 100 | F60: 19.51 | G60: 9.98 | H60: 17.4 | I60: 89.19 | J60: ES | K60: 408-5192546-3684330 | L60: =MONTH(D60) -> 12 | M60: =YEAR(D60) -> 2025 | N60: =D60*1 -> 45992 | O60: =F60/E60 -> 0.1951 | P60: =O60*E60 -> 19.51 | Q60: =G60/E60 -> 0.0998 | R60: =O60+Q60 -> 0.2949 | S60: =R60*E60 -> 29.49 | T60: =-(F60-H60)/E60 -> -0.0211 | U60: =R60+T60 -> 0.2738 | V60: =U60*E60 -> 27.38 | W60: =SUMIF(GLS!B:B,K60,GLS!C:C) -> 10.72 | Z60: =-IF(W60+X60+Y60=0,"à vérifier",W60+X60+Y60) -> -10.72 | AA60: =IFERROR((SUMIF($K:$K,K60,$Z:$Z)/COUNTIF($K:$K,K60))*E60/SUMIF($K:$K,K60,$E:$E),0) -> -10.72 | AB60: =AA60/E60 -> -0.1072 | AC60: =AB60+U60 -> 0.1666 | AD60: =AC60/R60 -> 0.56493727 | AE60: =AC60*E60 -> 16.66 | AF60: =IFERROR(-ABS(INDEX('frais amazon 011225-150326'!H:H,MATCH(Reproting_ERPALIN!K60,'frais amazon 011225-150326'!D:D,0))/1.2),"Commande hors la France") -> Commande hors la France | AG60: =IFERROR(AF60*E60/SUMIF($K:$K,K60,$E:$E),0) -> 0 | AH60: =AG60/E60 -> 0 | AI60: =AH60+AC60 -> 0.1666 | AJ60: =AI60/R60 -> 0.56493727 | AK60: =AI60*E60 -> 16.66
A61: Échelle De Parinaud 33cm | B61: 32 820 00 | C61: COMED | D61: 2026-01-01 | E61: 1 | F61: 39.57 | G61: 4.99 | H61: 19.57 | I61: 49.46 | J61: FR | K61: 408-5190667-6588319 | L61: =MONTH(D61) -> 1 | M61: =YEAR(D61) -> 2026 | N61: =D61*1 -> 46023 | O61: =F61/E61 -> 39.57 | P61: =O61*E61 -> 39.57 | Q61: =G61/E61 -> 4.99 | R61: =O61+Q61 -> 44.56 | S61: =R61*E61 -> 44.56 | T61: =-(F61-H61)/E61 -> -20 | U61: =R61+T61 -> 24.56 | V61: =U61*E61 -> 24.56 | W61: =SUMIF(GLS!B:B,K61,GLS!C:C) -> 5.25 | Z61: =-IF(W61+X61+Y61=0,"à vérifier",W61+X61+Y61) -> -5.25 | AA61: =IFERROR((SUMIF($K:$K,K61,$Z:$Z)/COUNTIF($K:$K,K61))*E61/SUMIF($K:$K,K61,$E:$E),0) -> -5.25 | AB61: =AA61/E61 -> -5.25 | AC61: =AB61+U61 -> 19.31 | AD61: =AC61/R61 -> 0.43334829 | AE61: =AC61*E61 -> 19.31 | AF61: =IFERROR(-ABS(INDEX('frais amazon 011225-150326'!H:H,MATCH(Reproting_ERPALIN!K61,'frais amazon 011225-150326'!D:D,0))/1.2),"Commande hors la France") -> -8.0166667 | AG61: =IFERROR(AF61*E61/SUMIF($K:$K,K61,$E:$E),0) -> -8.0166667 | AH61: =AG61/E61 -> -8.0166667 | AI61: =AH61+AC61 -> 11.293333 | AJ61: =AI61/R61 -> 0.25344105 | AK61: =AI61*E61 -> 11.293333
A62: ONTEX - iD Comfy Junior Pants Unisex 8-15 Ans - Sachet 14 Pièces - Blanc / carton de 112 pièces | B62: IDJ41321414 | C62: Ontex Santé France | D62: 2026-01-01 | E62: 14 | F62: 8.93 | G62: 4.99 | H62: 2.98 | I62: 33.32 | J62: FR | K62: 408-5178238-8736320 | L62: =MONTH(D62) -> 1 | M62: =YEAR(D62) -> 2026 | N62: =D62*1 -> 46023 | O62: =F62/E62 -> 0.63785714 | P62: =O62*E62 -> 8.93 | Q62: =G62/E62 -> 0.35642857 | R62: =O62+Q62 -> 0.99428571 | S62: =R62*E62 -> 13.92 | T62: =-(F62-H62)/E62 -> -0.425 | U62: =R62+T62 -> 0.56928571 | V62: =U62*E62 -> 7.97 | W62: =SUMIF(GLS!B:B,K62,GLS!C:C) -> 5.25 | Z62: =-IF(W62+X62+Y62=0,"à vérifier",W62+X62+Y62) -> -5.25 | AA62: =IFERROR((SUMIF($K:$K,K62,$Z:$Z)/COUNTIF($K:$K,K62))*E62/SUMIF($K:$K,K62,$E:$E),0) -> -5.25 | AB62: =AA62/E62 -> -0.375 | AC62: =AB62+U62 -> 0.19428571 | AD62: =AC62/R62 -> 0.1954023 | AE62: =AC62*E62 -> 2.72 | AF62: =IFERROR(-ABS(INDEX('frais amazon 011225-150326'!H:H,MATCH(Reproting_ERPALIN!K62,'frais amazon 011225-150326'!D:D,0))/1.2),"Commande hors la France") -> -2.5916667 | AG62: =IFERROR(AF62*E62/SUMIF($K:$K,K62,$E:$E),0) -> -2.5916667 | AH62: =AG62/E62 -> -0.18511905 | AI62: =AH62+AC62 -> 0.0091666667 | AJ62: =AI62/R62 -> 0.0092193487 | AK62: =AI62*E62 -> 0.12833333
A63: Abena - Couche culotte absorbante Pants Junior Extra Small - Jour - Niveau 2 - Sachet de 18 pièces | B63: 1000021317 | C63: Abena | D63: 2025-12-01 | E63: 36 | F63: 33.6 | G63: 4.99 | H63: 17.18 | I63: 51.12 | J63: FR | K63: 408-5085495-1257931 | L63: =MONTH(D63) -> 12 | M63: =YEAR(D63) -> 2025 | N63: =D63*1 -> 45992 | O63: =F63/E63 -> 0.93333333 | P63: =O63*E63 -> 33.6 | Q63: =G63/E63 -> 0.13861111 | R63: =O63+Q63 -> 1.0719444 | S63: =R63*E63 -> 38.59 | T63: =-(F63-H63)/E63 -> -0.45611111 | U63: =R63+T63 -> 0.61583333 | V63: =U63*E63 -> 22.17 | W63: =SUMIF(GLS!B:B,K63,GLS!C:C) -> 5.5 | Z63: =-IF(W63+X63+Y63=0,"à vérifier",W63+X63+Y63) -> -5.5 | AA63: =IFERROR((SUMIF($K:$K,K63,$Z:$Z)/COUNTIF($K:$K,K63))*E63/SUMIF($K:$K,K63,$E:$E),0) -> -5.5 | AB63: =AA63/E63 -> -0.15277778 | AC63: =AB63+U63 -> 0.46305556 | AD63: =AC63/R63 -> 0.4319772 | AE63: =AC63*E63 -> 16.67 | AF63: =IFERROR(-ABS(INDEX('frais amazon 011225-150326'!H:H,MATCH(Reproting_ERPALIN!K63,'frais amazon 011225-150326'!D:D,0))/1.2),"Commande hors la France") -> -7.15 | AG63: =IFERROR(AF63*E63/SUMIF($K:$K,K63,$E:$E),0) -> -7.15 | AH63: =AG63/E63 -> -0.19861111 | AI63: =AH63+AC63 -> 0.26444444 | AJ63: =AI63/R63 -> 0.24669604 | AK63: =AI63*E63 -> 9.52
A64: HARTMANN - MoliCare - Slip de maintien Unisexe - Fixpants Premium longleg - Boite de 3 pièces - Taille M | B64: 947806 | C64: Hartmann | D64: 2026-02-01 | E64: 3 | F64: 8.47 | G64: 4.99 | H64: 5.28 | I64: 62.34 | J64: FR | K64: 408-5005041-4613949 | L64: =MONTH(D64) -> 2 | M64: =YEAR(D64) -> 2026 | N64: =D64*1 -> 46054 | O64: =F64/E64 -> 2.8233333 | P64: =O64*E64 -> 8.47 | Q64: =G64/E64 -> 1.6633333 | R64: =O64+Q64 -> 4.4866667 | S64: =R64*E64 -> 13.46 | T64: =-(F64-H64)/E64 -> -1.0633333 | U64: =R64+T64 -> 3.4233333 | V64: =U64*E64 -> 10.27 | W64: =SUMIF(GLS!B:B,K64,GLS!C:C) -> 5.25 | Z64: =-IF(W64+X64+Y64=0,"à vérifier",W64+X64+Y64) -> -5.25 | AA64: =IFERROR((SUMIF($K:$K,K64,$Z:$Z)/COUNTIF($K:$K,K64))*E64/SUMIF($K:$K,K64,$E:$E),0) -> -5.25 | AB64: =AA64/E64 -> -1.75 | AC64: =AB64+U64 -> 1.6733333 | AD64: =AC64/R64 -> 0.37295691 | AE64: =AC64*E64 -> 5.02 | AF64: =IFERROR(-ABS(INDEX('frais amazon 011225-150326'!H:H,MATCH(Reproting_ERPALIN!K64,'frais amazon 011225-150326'!D:D,0))/1.2),"Commande hors la France") -> -2.5 | AG64: =IFERROR(AF64*E64/SUMIF($K:$K,K64,$E:$E),0) -> -2.5 | AH64: =AG64/E64 -> -0.83333333 | AI64: =AH64+AC64 -> 0.84 | AJ64: =AI64/R64 -> 0.1872214 | AK64: =AI64*E64 -> 2.52
A65: Sonde foley urinaire en 3 voies avec valve en plastique CH 16, (Boite de 10 Pièces) | B65: CFNL-3D-16-30-P | C65: ZARYS International Group sp. z o.o. sp.k. | D65: 2026-02-01 | E65: 20 | F65: 38.23 | G65: 4.99 | H65: 30.47 | I65: 79.7 | J65: FR | K65: 408-4795674-0863565 | L65: =MONTH(D65) -> 2 | M65: =YEAR(D65) -> 2026 | N65: =D65*1 -> 46054 | O65: =F65/E65 -> 1.9115 | P65: =O65*E65 -> 38.23 | Q65: =G65/E65 -> 0.2495 | R65: =O65+Q65 -> 2.161 | S65: =R65*E65 -> 43.22 | T65: =-(F65-H65)/E65 -> -0.388 | U65: =R65+T65 -> 1.773 | V65: =U65*E65 -> 35.46 | W65: =SUMIF(GLS!B:B,K65,GLS!C:C) -> 5.48 | Z65: =-IF(W65+X65+Y65=0,"à vérifier",W65+X65+Y65) -> -5.48 | AA65: =IFERROR((SUMIF($K:$K,K65,$Z:$Z)/COUNTIF($K:$K,K65))*E65/SUMIF($K:$K,K65,$E:$E),0) -> -5.48 | AB65: =AA65/E65 -> -0.274 | AC65: =AB65+U65 -> 1.499 | AD65: =AC65/R65 -> 0.69366034 | AE65: =AC65*E65 -> 29.98 | AF65: =IFERROR(-ABS(INDEX('frais amazon 011225-150326'!H:H,MATCH(Reproting_ERPALIN!K65,'frais amazon 011225-150326'!D:D,0))/1.2),"Commande hors la France") -> -8.0166667 | AG65: =IFERROR(AF65*E65/SUMIF($K:$K,K65,$E:$E),0) -> -8.0166667 | AH65: =AG65/E65 -> -0.40083333 | AI65: =AH65+AC65 -> 1.0981667 | AJ65: =AI65/R65 -> 0.50817523 | AK65: =AI65*E65 -> 21.963333
A66: Aiguille d'injection sans phtalate - Boite de 100 pièces - 30G - 13 mm | B66: IN-03X13 | C66: ZARYS International Group sp. z o.o. sp.k. | D66: 2026-01-01 | E66: 100 | F66: 10.29 | G66: 8.67 | H66: 9.47 | I66: 92.03 | J66: NL | K66: 408-4472208-5211523 | L66: =MONTH(D66) -> 1 | M66: =YEAR(D66) -> 2026 | N66: =D66*1 -> 46023 | O66: =F66/E66 -> 0.1029 | P66: =O66*E66 -> 10.29 | Q66: =G66/E66 -> 0.0867 | R66: =O66+Q66 -> 0.1896 | S66: =R66*E66 -> 18.96 | T66: =-(F66-H66)/E66 -> -0.0082 | U66: =R66+T66 -> 0.1814 | V66: =U66*E66 -> 18.14 | W66: =SUMIF(GLS!B:B,K66,GLS!C:C) -> 9.39 | Z66: =-IF(W66+X66+Y66=0,"à vérifier",W66+X66+Y66) -> -9.39 | AA66: =IFERROR((SUMIF($K:$K,K66,$Z:$Z)/COUNTIF($K:$K,K66))*E66/SUMIF($K:$K,K66,$E:$E),0) -> -9.39 | AB66: =AA66/E66 -> -0.0939 | AC66: =AB66+U66 -> 0.0875 | AD66: =AC66/R66 -> 0.46149789 | AE66: =AC66*E66 -> 8.75 | AF66: =IFERROR(-ABS(INDEX('frais amazon 011225-150326'!H:H,MATCH(Reproting_ERPALIN!K66,'frais amazon 011225-150326'!D:D,0))/1.2),"Commande hors la France") -> Commande hors la France | AG66: =IFERROR(AF66*E66/SUMIF($K:$K,K66,$E:$E),0) -> 0 | AH66: =AG66/E66 -> 0 | AI66: =AH66+AC66 -> 0.0875 | AJ66: =AI66/R66 -> 0.46149789 | AK66: =AI66*E66 -> 8.75
A67: Sonde foley urinaire, 2 voies, avec valve en Plastique - 400 mm - 10 Pièces - CH 12 - 5-10 ml | B67: CFNL-2D-12-10-P | C67: ZARYS International Group sp. z o.o. sp.k. | D67: 2026-01-01 | E67: 10 | F67: 18.29 | G67: 4.99 | H67: 15.06 | I67: 82.33 | J67: FR | K67: 408-4391067-3553150 | L67: =MONTH(D67) -> 1 | M67: =YEAR(D67) -> 2026 | N67: =D67*1 -> 46023 | O67: =F67/E67 -> 1.829 | P67: =O67*E67 -> 18.29 | Q67: =G67/E67 -> 0.499 | R67: =O67+Q67 -> 2.328 | S67: =R67*E67 -> 23.28 | T67: =-(F67-H67)/E67 -> -0.323 | U67: =R67+T67 -> 2.005 | V67: =U67*E67 -> 20.05 | W67: =SUMIF(GLS!B:B,K67,GLS!C:C) -> 5.25 | Z67: =-IF(W67+X67+Y67=0,"à vérifier",W67+X67+Y67) -> -5.25 | AA67: =IFERROR((SUMIF($K:$K,K67,$Z:$Z)/COUNTIF($K:$K,K67))*E67/SUMIF($K:$K,K67,$E:$E),0) -> -5.25 | AB67: =AA67/E67 -> -0.525 | AC67: =AB67+U67 -> 1.48 | AD67: =AC67/R67 -> 0.63573883 | AE67: =AC67*E67 -> 14.8 | AF67: =IFERROR(-ABS(INDEX('frais amazon 011225-150326'!H:H,MATCH(Reproting_ERPALIN!K67,'frais amazon 011225-150326'!D:D,0))/1.2),"Commande hors la France") -> -3.9083333 | AG67: =IFERROR(AF67*E67/SUMIF($K:$K,K67,$E:$E),0) -> -3.9083333 | AH67: =AG67/E67 -> -0.39083333 | AI67: =AH67+AC67 -> 1.0891667 | AJ67: =AI67/R67 -> 0.4678551 | AK67: =AI67*E67 -> 10.891667
A68: ZARYS - Seringue à usage unique en 3 parties luer avec aiguille stérile 2 ml buse centrique 0.6mm x 30mm bleu foncé - Boite de 100 pcs | B68: 002ML-3CZ-SN | C68: ZARYS International Group sp. z o.o. sp.k. | D68: 2026-01-01 | E68: 100 | F68: 9.48 | G68: 4.99 | H68: 7.34 | I68: 77.43 | J68: FR | K68: 408-4311962-4013953 | L68: =MONTH(D68) -> 1 | M68: =YEAR(D68) -> 2026 | N68: =D68*1 -> 46023 | O68: =F68/E68 -> 0.0948 | P68: =O68*E68 -> 9.48 | Q68: =G68/E68 -> 0.0499 | R68: =O68+Q68 -> 0.1447 | S68: =R68*E68 -> 14.47 | T68: =-(F68-H68)/E68 -> -0.0214 | U68: =R68+T68 -> 0.1233 | V68: =U68*E68 -> 12.33 | W68: =SUMIF(GLS!B:B,K68,GLS!C:C) -> 5.25 | Z68: =-IF(W68+X68+Y68=0,"à vérifier",W68+X68+Y68) -> -5.25 | AA68: =IFERROR((SUMIF($K:$K,K68,$Z:$Z)/COUNTIF($K:$K,K68))*E68/SUMIF($K:$K,K68,$E:$E),0) -> -5.25 | AB68: =AA68/E68 -> -0.0525 | AC68: =AB68+U68 -> 0.0708 | AD68: =AC68/R68 -> 0.48928818 | AE68: =AC68*E68 -> 7.08 | AF68: =IFERROR(-ABS(INDEX('frais amazon 011225-150326'!H:H,MATCH(Reproting_ERPALIN!K68,'frais amazon 011225-150326'!D:D,0))/1.2),"Commande hors la France") -> -2.675 | AG68: =IFERROR(AF68*E68/SUMIF($K:$K,K68,$E:$E),0) -> -2.675 | AH68: =AG68/E68 -> -0.02675 | AI68: =AH68+AC68 -> 0.04405 | AJ68: =AI68/R68 -> 0.30442294 | AK68: =AI68*E68 -> 4.405
A69: Seringue à tuberculine - Stérile - Boite de 100 pièces | B69: TU-U20-1-BL | C69: ZARYS International Group sp. z o.o. sp.k. | D69: 2026-01-01 | E69: 100 | F69: 16.25 | G69: 16.58 | H69: 13.96 | I69: 85.91 | J69: IT | K69: 408-4198711-4873143 | L69: =MONTH(D69) -> 1 | M69: =YEAR(D69) -> 2026 | N69: =D69*1 -> 46023 | O69: =F69/E69 -> 0.1625 | P69: =O69*E69 -> 16.25 | Q69: =G69/E69 -> 0.1658 | R69: =O69+Q69 -> 0.3283 | S69: =R69*E69 -> 32.83 | T69: =-(F69-H69)/E69 -> -0.0229 | U69: =R69+T69 -> 0.3054 | V69: =U69*E69 -> 30.54 | W69: =SUMIF(GLS!B:B,K69,GLS!C:C) -> 65.5 | Z69: =-IF(W69+X69+Y69=0,"à vérifier",W69+X69+Y69) -> -65.5 | AA69: =IFERROR((SUMIF($K:$K,K69,$Z:$Z)/COUNTIF($K:$K,K69))*E69/SUMIF($K:$K,K69,$E:$E),0) -> -65.5 | AB69: =AA69/E69 -> -0.655 | AC69: =AB69+U69 -> -0.3496 | AD69: =AC69/R69 -> -1.0648797 | AE69: =AC69*E69 -> -34.96 | AF69: =IFERROR(-ABS(INDEX('frais amazon 011225-150326'!H:H,MATCH(Reproting_ERPALIN!K69,'frais amazon 011225-150326'!D:D,0))/1.2),"Commande hors la France") -> Commande hors la France | AG69: =IFERROR(AF69*E69/SUMIF($K:$K,K69,$E:$E),0) -> 0 | AH69: =AG69/E69 -> 0 | AI69: =AH69+AC69 -> -0.3496 | AJ69: =AI69/R69 -> -1.0648797 | AK69: =AI69*E69 -> -34.96
A70: Abena - Couche culotte absorbante Pants Premium - Nuit - Niveau 3 Medium - Sachet de 15 pièces | B70: 1000021324 | C70: Abena | D70: 2026-02-01 | E70: 15 | F70: 16.65 | G70: 0 | H70: 6.93 | I70: 41.64 | J70: FR | K70: 408-4137536-0177967 | L70: =MONTH(D70) -> 2 | M70: =YEAR(D70) -> 2026 | N70: =D70*1 -> 46054 | O70: =F70/E70 -> 1.11 | P70: =O70*E70 -> 16.65 | Q70: =G70/E70 -> 0 | R70: =O70+Q70 -> 1.11 | S70: =R70*E70 -> 16.65 | T70: =-(F70-H70)/E70 -> -0.648 | U70: =R70+T70 -> 0.462 | V70: =U70*E70 -> 6.93 | W70: =SUMIF(GLS!B:B,K70,GLS!C:C) -> 5.49 | Z70: =-IF(W70+X70+Y70=0,"à vérifier",W70+X70+Y70) -> -5.49 | AA70: =IFERROR((SUMIF($K:$K,K70,$Z:$Z)/COUNTIF($K:$K,K70))*E70/SUMIF($K:$K,K70,$E:$E),0) -> -5.49 | AB70: =AA70/E70 -> -0.366 | AC70: =AB70+U70 -> 0.096 | AD70: =AC70/R70 -> 0.086486486 | AE70: =AC70*E70 -> 1.44 | AF70: =IFERROR(-ABS(INDEX('frais amazon 011225-150326'!H:H,MATCH(Reproting_ERPALIN!K70,'frais amazon 011225-150326'!D:D,0))/1.2),"Commande hors la France") -> -3.0916667 | AG70: =IFERROR(AF70*E70/SUMIF($K:$K,K70,$E:$E),0) -> -3.0916667 | AH70: =AG70/E70 -> -0.20611111 | AI70: =AH70+AC70 -> -0.11011111 | AJ70: =AI70/R70 -> -0.099199199 | AK70: =AI70*E70 -> -1.6516667
A71: Gants Nitriles Non poudrés Taille L, (Boite de 100 pièces) | B71: RNBL10001 | C71: ZARYS International Group sp. z o.o. sp.k. | D71: 2026-01-01 | E71: 1500 | F71: 43.8 | G71: 13.16 | H71: 18.9 | I71: 43.15 | J71: IT | K71: 408-4101634-7011543 | L71: =MONTH(D71) -> 1 | M71: =YEAR(D71) -> 2026 | N71: =D71*1 -> 46023 | O71: =F71/E71 -> 0.0292 | P71: =O71*E71 -> 43.8 | Q71: =G71/E71 -> 0.0087733333 | R71: =O71+Q71 -> 0.037973333 | S71: =R71*E71 -> 56.96 | T71: =-(F71-H71)/E71 -> -0.0166 | U71: =R71+T71 -> 0.021373333 | V71: =U71*E71 -> 32.06 | W71: =SUMIF(GLS!B:B,K71,GLS!C:C) -> 12.73 | Z71: =-IF(W71+X71+Y71=0,"à vérifier",W71+X71+Y71) -> -12.73 | AA71: =IFERROR((SUMIF($K:$K,K71,$Z:$Z)/COUNTIF($K:$K,K71))*E71/SUMIF($K:$K,K71,$E:$E),0) -> -12.73 | AB71: =AA71/E71 -> -0.0084866667 | AC71: =AB71+U71 -> 0.012886667 | AD71: =AC71/R71 -> 0.33936096 | AE71: =AC71*E71 -> 19.33 | AF71: =IFERROR(-ABS(INDEX('frais amazon 011225-150326'!H:H,MATCH(Reproting_ERPALIN!K71,'frais amazon 011225-150326'!D:D,0))/1.2),"Commande hors la France") -> Commande hors la France | AG71: =IFERROR(AF71*E71/SUMIF($K:$K,K71,$E:$E),0) -> 0 | AH71: =AG71/E71 -> 0 | AI71: =AH71+AC71 -> 0.012886667 | AJ71: =AI71/R71 -> 0.33936096 | AK71: =AI71*E71 -> 19.33
A72: HARTMANN - ZETUVIT E Pansement absorbant stérile 15 x 20 cm (413792) - Boite de 25 pièces | B72: 413772 | C72: Hartmann | D72: 2026-01-01 | E72: 100 | F72: 36.36 | G72: 11.26 | H72: 15.27 | I72: 42 | J72: IT | K72: 408-4095612-6293120 | L72: =MONTH(D72) -> 1 | M72: =YEAR(D72) -> 2026 | N72: =D72*1 -> 46023 | O72: =F72/E72 -> 0.3636 | P72: =O72*E72 -> 36.36 | Q72: =G72/E72 -> 0.1126 | R72: =O72+Q72 -> 0.4762 | S72: =R72*E72 -> 47.62 | T72: =-(F72-H72)/E72 -> -0.2109 | U72: =R72+T72 -> 0.2653 | V72: =U72*E72 -> 26.53 | W72: =SUMIF(GLS!B:B,K72,GLS!C:C) -> 11.76 | Z72: =-IF(W72+X72+Y72=0,"à vérifier",W72+X72+Y72) -> -11.76 | AA72: =IFERROR((SUMIF($K:$K,K72,$Z:$Z)/COUNTIF($K:$K,K72))*E72/SUMIF($K:$K,K72,$E:$E),0) -> -11.76 | AB72: =AA72/E72 -> -0.1176 | AC72: =AB72+U72 -> 0.1477 | AD72: =AC72/R72 -> 0.3101638 | AE72: =AC72*E72 -> 14.77 | AF72: =IFERROR(-ABS(INDEX('frais amazon 011225-150326'!H:H,MATCH(Reproting_ERPALIN!K72,'frais amazon 011225-150326'!D:D,0))/1.2),"Commande hors la France") -> Commande hors la France | AG72: =IFERROR(AF72*E72/SUMIF($K:$K,K72,$E:$E),0) -> 0 | AH72: =AG72/E72 -> 0 | AI72: =AH72+AC72 -> 0.1477 | AJ72: =AI72/R72 -> 0.3101638 | AK72: =AI72*E72 -> 14.77
A73: Aiguille d'injection sans phtalate - Boite de 100 pièces - 18G - 40 mm | B73: IN-12X40 | C73: ZARYS International Group sp. z o.o. sp.k. | D73: 2026-01-01 | E73: 100 | F73: 10.47 | G73: 8.75 | H73: 9.44 | I73: 90.16 | J73: ES | K73: 408-3958171-2827500 | L73: =MONTH(D73) -> 1 | M73: =YEAR(D73) -> 2026 | N73: =D73*1 -> 46023 | O73: =F73/E73 -> 0.1047 | P73: =O73*E73 -> 10.47 | Q73: =G73/E73 -> 0.0875 | R73: =O73+Q73 -> 0.1922 | S73: =R73*E73 -> 19.22 | T73: =-(F73-H73)/E73 -> -0.0103 | U73: =R73+T73 -> 0.1819 | V73: =U73*E73 -> 18.19 | W73: =SUMIF(GLS!B:B,K73,GLS!C:C) -> 10.72 | Z73: =-IF(W73+X73+Y73=0,"à vérifier",W73+X73+Y73) -> -10.72 | AA73: =IFERROR((SUMIF($K:$K,K73,$Z:$Z)/COUNTIF($K:$K,K73))*E73/SUMIF($K:$K,K73,$E:$E),0) -> -10.72 | AB73: =AA73/E73 -> -0.1072 | AC73: =AB73+U73 -> 0.0747 | AD73: =AC73/R73 -> 0.38865765 | AE73: =AC73*E73 -> 7.47 | AF73: =IFERROR(-ABS(INDEX('frais amazon 011225-150326'!H:H,MATCH(Reproting_ERPALIN!K73,'frais amazon 011225-150326'!D:D,0))/1.2),"Commande hors la France") -> Commande hors la France | AG73: =IFERROR(AF73*E73/SUMIF($K:$K,K73,$E:$E),0) -> 0 | AH73: =AG73/E73 -> 0 | AI73: =AH73+AC73 -> 0.0747 | AJ73: =AI73/R73 -> 0.38865765 | AK73: =AI73*E73 -> 7.47
A74: Abena - Couches adulte intraversables Maternity Pad Super - Sachet de 15 pièces | B74: 1000022654 | C74: Abena | D74: 2026-01-01 | E74: 15 | F74: 6.93 | G74: 4.99 | H74: 4.79 | I74: 69.16 | J74: FR | K74: 408-3668604-0606701 | L74: =MONTH(D74) -> 1 | M74: =YEAR(D74) -> 2026 | N74: =D74*1 -> 46023 | O74: =F74/E74 -> 0.462 | P74: =O74*E74 -> 6.93 | Q74: =G74/E74 -> 0.33266667 | R74: =O74+Q74 -> 0.79466667 | S74: =R74*E74 -> 11.92 | T74: =-(F74-H74)/E74 -> -0.14266667 | U74: =R74+T74 -> 0.652 | V74: =U74*E74 -> 9.78 | W74: =SUMIF(GLS!B:B,K74,GLS!C:C) -> 5.25 | Z74: =-IF(W74+X74+Y74=0,"à vérifier",W74+X74+Y74) -> -5.25 | AA74: =IFERROR((SUMIF($K:$K,K74,$Z:$Z)/COUNTIF($K:$K,K74))*E74/SUMIF($K:$K,K74,$E:$E),0) -> -5.25 | AB74: =AA74/E74 -> -0.35 | AC74: =AB74+U74 -> 0.302 | AD74: =AC74/R74 -> 0.38003356 | AE74: =AC74*E74 -> 4.53 | AF74: =IFERROR(-ABS(INDEX('frais amazon 011225-150326'!H:H,MATCH(Reproting_ERPALIN!K74,'frais amazon 011225-150326'!D:D,0))/1.2),"Commande hors la France") -> -2.2083333 | AG74: =IFERROR(AF74*E74/SUMIF($K:$K,K74,$E:$E),0) -> -2.2083333 | AH74: =AG74/E74 -> -0.14722222 | AI74: =AH74+AC74 -> 0.15477778 | AJ74: =AI74/R74 -> 0.19477069 | AK74: =AI74*E74 -> 2.3216667
A75: MASQUE NÉBULISEUR avec tubulure stérile, 210cm +/- 5%, taille XL, (Boite de 50 pièces) | B75: MTN-XL | C75: ZARYS International Group sp. z o.o. sp.k. | D75: 2026-01-01 | E75: 1 | F75: 6.43 | G75: 8.67 | H75: 5.9 | I75: 91.7 | J75: ES | K75: 408-3417120-7685165 | L75: =MONTH(D75) -> 1 | M75: =YEAR(D75) -> 2026 | N75: =D75*1 -> 46023 | O75: =F75/E75 -> 6.43 | P75: =O75*E75 -> 6.43 | Q75: =G75/E75 -> 8.67 | R75: =O75+Q75 -> 15.1 | S75: =R75*E75 -> 15.1 | T75: =-(F75-H75)/E75 -> -0.53 | U75: =R75+T75 -> 14.57 | V75: =U75*E75 -> 14.57 | W75: =SUMIF(GLS!B:B,K75,GLS!C:C) -> 10.72 | Z75: =-IF(W75+X75+Y75=0,"à vérifier",W75+X75+Y75) -> -10.72 | AA75: =IFERROR((SUMIF($K:$K,K75,$Z:$Z)/COUNTIF($K:$K,K75))*E75/SUMIF($K:$K,K75,$E:$E),0) -> -10.72 | AB75: =AA75/E75 -> -10.72 | AC75: =AB75+U75 -> 3.85 | AD75: =AC75/R75 -> 0.25496689 | AE75: =AC75*E75 -> 3.85 | AF75: =IFERROR(-ABS(INDEX('frais amazon 011225-150326'!H:H,MATCH(Reproting_ERPALIN!K75,'frais amazon 011225-150326'!D:D,0))/1.2),"Commande hors la France") -> Commande hors la France | AG75: =IFERROR(AF75*E75/SUMIF($K:$K,K75,$E:$E),0) -> 0 | AH75: =AG75/E75 -> 0 | AI75: =AH75+AC75 -> 3.85 | AJ75: =AI75/R75 -> 0.25496689 | AK75: =AI75*E75 -> 3.85
A76: MoliCare Skin - Creme dermoprotectrice Zinc 200ml | B76: 995022 | C76: Hartmann | D76: 2026-01-01 | E76: 4 | F76: 18.5 | G76: 8.33 | H76: 4.41 | I76: 23.85 | J76: ES | K76: 408-3383658-5280366 | L76: =MONTH(D76) -> 1 | M76: =YEAR(D76) -> 2026 | N76: =D76*1 -> 46023 | O76: =F76/E76 -> 4.625 | P76: =O76*E76 -> 18.5 | Q76: =G76/E76 -> 2.0825 | R76: =O76+Q76 -> 6.7075 | S76: =R76*E76 -> 26.83 | T76: =-(F76-H76)/E76 -> -3.5225 | U76: =R76+T76 -> 3.185 | V76: =U76*E76 -> 12.74 | W76: =SUMIF(GLS!B:B,K76,GLS!C:C) -> 11.05 | Z76: =-IF(W76+X76+Y76=0,"à vérifier",W76+X76+Y76) -> -11.05 | AA76: =IFERROR((SUMIF($K:$K,K76,$Z:$Z)/COUNTIF($K:$K,K76))*E76/SUMIF($K:$K,K76,$E:$E),0) -> -11.05 | AB76: =AA76/E76 -> -2.7625 | AC76: =AB76+U76 -> 0.4225 | AD76: =AC76/R76 -> 0.062989191 | AE76: =AC76*E76 -> 1.69 | AF76: =IFERROR(-ABS(INDEX('frais amazon 011225-150326'!H:H,MATCH(Reproting_ERPALIN!K76,'frais amazon 011225-150326'!D:D,0))/1.2),"Commande hors la France") -> Commande hors la France | AG76: =IFERROR(AF76*E76/SUMIF($K:$K,K76,$E:$E),0) -> 0 | AH76: =AG76/E76 -> 0 | AI76: =AH76+AC76 -> 0.4225 | AJ76: =AI76/R76 -> 0.062989191 | AK76: =AI76*E76 -> 1.69
A77: Seringue 3 pièces luer lock stérile 10ml, (Boite de 100 pièces) | B77: CH03010LL | C77: Vitrex Medical | D77: 2026-01-01 | E77: 100 | F77: 14.78 | G77: 0 | H77: 8.98 | I77: 60.76 | J77: FR | K77: 408-3376791-7795524 | L77: =MONTH(D77) -> 1 | M77: =YEAR(D77) -> 2026 | N77: =D77*1 -> 46023 | O77: =F77/E77 -> 0.1478 | P77: =O77*E77 -> 14.78 | Q77: =G77/E77 -> 0 | R77: =O77+Q77 -> 0.1478 | S77: =R77*E77 -> 14.78 | T77: =-(F77-H77)/E77 -> -0.058 | U77: =R77+T77 -> 0.0898 | V77: =U77*E77 -> 8.98 | W77: =SUMIF(GLS!B:B,K77,GLS!C:C) -> 5.48 | Z77: =-IF(W77+X77+Y77=0,"à vérifier",W77+X77+Y77) -> -5.48 | AA77: =IFERROR((SUMIF($K:$K,K77,$Z:$Z)/COUNTIF($K:$K,K77))*E77/SUMIF($K:$K,K77,$E:$E),0) -> -5.48 | AB77: =AA77/E77 -> -0.0548 | AC77: =AB77+U77 -> 0.035 | AD77: =AC77/R77 -> 0.2368065 | AE77: =AC77*E77 -> 3.5 | AF77: =IFERROR(-ABS(INDEX('frais amazon 011225-150326'!H:H,MATCH(Reproting_ERPALIN!K77,'frais amazon 011225-150326'!D:D,0))/1.2),"Commande hors la France") -> -2.7333333 | AG77: =IFERROR(AF77*E77/SUMIF($K:$K,K77,$E:$E),0) -> -2.7333333 | AH77: =AG77/E77 -> -0.027333333 | AI77: =AH77+AC77 -> 0.0076666667 | AJ77: =AI77/R77 -> 0.051871899 | AK77: =AI77*E77 -> 0.76666667
A78: Aiguille d'injection sans phtalate - Boite de 100 pièces - 22G - 30 mm | B78: IN-07X30 | C78: ZARYS International Group sp. z o.o. sp.k. | D78: 2026-01-01 | E78: 100 | F78: 10.47 | G78: 8.75 | H78: 9.77 | I78: 93.31 | J78: ES | K78: 408-3266373-9079500 | L78: =MONTH(D78) -> 1 | M78: =YEAR(D78) -> 2026 | N78: =D78*1 -> 46023 | O78: =F78/E78 -> 0.1047 | P78: =O78*E78 -> 10.47 | Q78: =G78/E78 -> 0.0875 | R78: =O78+Q78 -> 0.1922 | S78: =R78*E78 -> 19.22 | T78: =-(F78-H78)/E78 -> -0.007 | U78: =R78+T78 -> 0.1852 | V78: =U78*E78 -> 18.52 | W78: =SUMIF(GLS!B:B,K78,GLS!C:C) -> 10.72 | Z78: =-IF(W78+X78+Y78=0,"à vérifier",W78+X78+Y78) -> -10.72 | AA78: =IFERROR((SUMIF($K:$K,K78,$Z:$Z)/COUNTIF($K:$K,K78))*E78/SUMIF($K:$K,K78,$E:$E),0) -> -10.72 | AB78: =AA78/E78 -> -0.1072 | AC78: =AB78+U78 -> 0.078 | AD78: =AC78/R78 -> 0.40582726 | AE78: =AC78*E78 -> 7.8 | AF78: =IFERROR(-ABS(INDEX('frais amazon 011225-150326'!H:H,MATCH(Reproting_ERPALIN!K78,'frais amazon 011225-150326'!D:D,0))/1.2),"Commande hors la France") -> Commande hors la France | AG78: =IFERROR(AF78*E78/SUMIF($K:$K,K78,$E:$E),0) -> 0 | AH78: =AG78/E78 -> 0 | AI78: =AH78+AC78 -> 0.078 | AJ78: =AI78/R78 -> 0.40582726 | AK78: =AI78*E78 -> 7.8
A79: Aiguille d'injection sans phtalate - Boite de 100 pièces - 22G - 30 mm | B79: IN-07X30 | C79: ZARYS International Group sp. z o.o. sp.k. | D79: 2026-01-01 | E79: 100 | F79: 12.05 | G79: 4.99 | H79: 11.35 | I79: 94.19 | J79: FR | K79: 408-3263695-7297105 | L79: =MONTH(D79) -> 1 | M79: =YEAR(D79) -> 2026 | N79: =D79*1 -> 46023 | O79: =F79/E79 -> 0.1205 | P79: =O79*E79 -> 12.05 | Q79: =G79/E79 -> 0.0499 | R79: =O79+Q79 -> 0.1704 | S79: =R79*E79 -> 17.04 | T79: =-(F79-H79)/E79 -> -0.007 | U79: =R79+T79 -> 0.1634 | V79: =U79*E79 -> 16.34 | W79: =SUMIF(GLS!B:B,K79,GLS!C:C) -> 5.25 | Z79: =-IF(W79+X79+Y79=0,"à vérifier",W79+X79+Y79) -> -5.25 | AA79: =IFERROR((SUMIF($K:$K,K79,$Z:$Z)/COUNTIF($K:$K,K79))*E79/SUMIF($K:$K,K79,$E:$E),0) -> -5.25 | AB79: =AA79/E79 -> -0.0525 | AC79: =AB79+U79 -> 0.1109 | AD79: =AC79/R79 -> 0.6508216 | AE79: =AC79*E79 -> 11.09 | AF79: =IFERROR(-ABS(INDEX('frais amazon 011225-150326'!H:H,MATCH(Reproting_ERPALIN!K79,'frais amazon 011225-150326'!D:D,0))/1.2),"Commande hors la France") -> -3.1666667 | AG79: =IFERROR(AF79*E79/SUMIF($K:$K,K79,$E:$E),0) -> -3.1666667 | AH79: =AG79/E79 -> -0.031666667 | AI79: =AH79+AC79 -> 0.079233333 | AJ79: =AI79/R79 -> 0.46498435 | AK79: =AI79*E79 -> 7.9233333
A80: HARTMANN - MoliCare Skin - Serviettes imprégnées - Sachet de 50 pièces | B80: 995075 | C80: Hartmann | D80: 2026-02-01 | E80: 100 | F80: 8 | G80: 4.99 | H80: 4.32 | I80: 54 | J80: FR | K80: 408-3250775-8873939 | L80: =MONTH(D80) -> 2 | M80: =YEAR(D80) -> 2026 | N80: =D80*1 -> 46054 | O80: =F80/E80 -> 0.08 | P80: =O80*E80 -> 8 | Q80: =G80/E80 -> 0.0499 | R80: =O80+Q80 -> 0.1299 | S80: =R80*E80 -> 12.99 | T80: =-(F80-H80)/E80 -> -0.0368 | U80: =R80+T80 -> 0.0931 | V80: =U80*E80 -> 9.31 | W80: =SUMIF(GLS!B:B,K80,GLS!C:C) -> 5.25 | Z80: =-IF(W80+X80+Y80=0,"à vérifier",W80+X80+Y80) -> -5.25 | AA80: =IFERROR((SUMIF($K:$K,K80,$Z:$Z)/COUNTIF($K:$K,K80))*E80/SUMIF($K:$K,K80,$E:$E),0) -> -5.25 | AB80: =AA80/E80 -> -0.0525 | AC80: =AB80+U80 -> 0.0406 | AD80: =AC80/R80 -> 0.31254811 | AE80: =AC80*E80 -> 4.06 | AF80: =IFERROR(-ABS(INDEX('frais amazon 011225-150326'!H:H,MATCH(Reproting_ERPALIN!K80,'frais amazon 011225-150326'!D:D,0))/1.2),"Commande hors la France") -> -1.2666667 | AG80: =IFERROR(AF80*E80/SUMIF($K:$K,K80,$E:$E),0) -> -1.2666667 | AH80: =AG80/E80 -> -0.012666667 | AI80: =AH80+AC80 -> 0.027933333 | AJ80: =AI80/R80 -> 0.21503721 | AK80: =AI80*E80 -> 2.7933333
A81: Comed - Abaisse langue en bois adulte (Boite de 100 pièces) | B81: 25 105 00 | C81: COMED | D81: 2025-12-01 | E81: 100 | F81: 6.23 | G81: 0 | H81: 4.62 | I81: 74.16 | J81: FR | K81: 408-3160821-7768310 | L81: =MONTH(D81) -> 12 | M81: =YEAR(D81) -> 2025 | N81: =D81*1 -> 45992 | O81: =F81/E81 -> 0.0623 | P81: =O81*E81 -> 6.23 | Q81: =G81/E81 -> 0 | R81: =O81+Q81 -> 0.0623 | S81: =R81*E81 -> 6.23 | T81: =-(F81-H81)/E81 -> -0.0161 | U81: =R81+T81 -> 0.0462 | V81: =U81*E81 -> 4.62 | W81: =SUMIF(GLS!B:B,K81,GLS!C:C) -> 5.25 | Z81: =-IF(W81+X81+Y81=0,"à vérifier",W81+X81+Y81) -> -5.25 | AA81: =IFERROR((SUMIF($K:$K,K81,$Z:$Z)/COUNTIF($K:$K,K81))*E81/SUMIF($K:$K,K81,$E:$E),0) -> -5.25 | AB81: =AA81/E81 -> -0.0525 | AC81: =AB81+U81 -> -0.0063 | AD81: =AC81/R81 -> -0.1011236 | AE81: =AC81*E81 -> -0.63 | AF81: =IFERROR(-ABS(INDEX('frais amazon 011225-150326'!H:H,MATCH(Reproting_ERPALIN!K81,'frais amazon 011225-150326'!D:D,0))/1.2),"Commande hors la France") -> -0.61666667 | AG81: =IFERROR(AF81*E81/SUMIF($K:$K,K81,$E:$E),0) -> -0.61666667 | AH81: =AG81/E81 -> -0.0061666667 | AI81: =AH81+AC81 -> -0.012466667 | AJ81: =AI81/R81 -> -0.20010701 | AK81: =AI81*E81 -> -1.2466667
A82: TENA - Proskin Wash Glove Gant de Toilette - Boite de 175 pièces | B82: 740500 | C82: TENA | D82: 2026-02-01 | E82: 175 | F82: 12.51 | G82: 8.79 | H82: 1.99 | I82: 15.93 | J82: ES | K82: 408-3089690-9661110 | L82: =MONTH(D82) -> 2 | M82: =YEAR(D82) -> 2026 | N82: =D82*1 -> 46054 | O82: =F82/E82 -> 0.071485714 | P82: =O82*E82 -> 12.51 | Q82: =G82/E82 -> 0.050228571 | R82: =O82+Q82 -> 0.12171429 | S82: =R82*E82 -> 21.3 | T82: =-(F82-H82)/E82 -> -0.060114286 | U82: =R82+T82 -> 0.0616 | V82: =U82*E82 -> 10.78 | W82: =SUMIF(GLS!B:B,K82,GLS!C:C) -> 11.42 | Z82: =-IF(W82+X82+Y82=0,"à vérifier",W82+X82+Y82) -> -11.42 | AA82: =IFERROR((SUMIF($K:$K,K82,$Z:$Z)/COUNTIF($K:$K,K82))*E82/SUMIF($K:$K,K82,$E:$E),0) -> -11.42 | AB82: =AA82/E82 -> -0.065257143 | AC82: =AB82+U82 -> -0.0036571429 | AD82: =AC82/R82 -> -0.030046948 | AE82: =AC82*E82 -> -0.64 | AF82: =IFERROR(-ABS(INDEX('frais amazon 011225-150326'!H:H,MATCH(Reproting_ERPALIN!K82,'frais amazon 011225-150326'!D:D,0))/1.2),"Commande hors la France") -> Commande hors la France | AG82: =IFERROR(AF82*E82/SUMIF($K:$K,K82,$E:$E),0) -> 0 | AH82: =AG82/E82 -> 0 | AI82: =AH82+AC82 -> -0.0036571429 | AJ82: =AI82/R82 -> -0.030046948 | AK82: =AI82*E82 -> -0.64
A83: Abena - Couches adulte intraversables Maternity Pad Super - Sachet de 15 pièces | B83: 1000022654 | C83: Abena | D83: 2026-01-01 | E83: 15 | F83: 6.82 | G83: 4.99 | H83: 4.68 | I83: 68.66 | J83: FR | K83: 408-3062248-1636365 | L83: =MONTH(D83) -> 1 | M83: =YEAR(D83) -> 2026 | N83: =D83*1 -> 46023 | O83: =F83/E83 -> 0.45466667 | P83: =O83*E83 -> 6.82 | Q83: =G83/E83 -> 0.33266667 | R83: =O83+Q83 -> 0.78733333 | S83: =R83*E83 -> 11.81 | T83: =-(F83-H83)/E83 -> -0.14266667 | U83: =R83+T83 -> 0.64466667 | V83: =U83*E83 -> 9.67 | W83: =SUMIF(GLS!B:B,K83,GLS!C:C) -> 5.48 | Z83: =-IF(W83+X83+Y83=0,"à vérifier",W83+X83+Y83) -> -5.48 | AA83: =IFERROR((SUMIF($K:$K,K83,$Z:$Z)/COUNTIF($K:$K,K83))*E83/SUMIF($K:$K,K83,$E:$E),0) -> -5.48 | AB83: =AA83/E83 -> -0.36533333 | AC83: =AB83+U83 -> 0.27933333 | AD83: =AC83/R83 -> 0.35478408 | AE83: =AC83*E83 -> 4.19 | AF83: =IFERROR(-ABS(INDEX('frais amazon 011225-150326'!H:H,MATCH(Reproting_ERPALIN!K83,'frais amazon 011225-150326'!D:D,0))/1.2),"Commande hors la France") -> -2.1833333 | AG83: =IFERROR(AF83*E83/SUMIF($K:$K,K83,$E:$E),0) -> -2.1833333 | AH83: =AG83/E83 -> -0.14555556 | AI83: =AH83+AC83 -> 0.13377778 | AJ83: =AI83/R83 -> 0.1699125 | AK83: =AI83*E83 -> 2.0066667
A84: Aiguille hypodermique à usage unique non sécurisée 25G, 0,5 mm x 40 mm | B84: IN-05X40 | C84: ZARYS International Group sp. z o.o. sp.k. | D84: 2026-01-01 | E84: 100 | F84: 10.04 | G84: 2.495 | H84: 9.17 | I84: 91.33 | J84: FR | K84: 408-3016147-3497103 | L84: =MONTH(D84) -> 1 | M84: =YEAR(D84) -> 2026 | N84: =D84*1 -> 46023 | O84: =F84/E84 -> 0.1004 | P84: =O84*E84 -> 10.04 | Q84: =G84/E84 -> 0.02495 | R84: =O84+Q84 -> 0.12535 | S84: =R84*E84 -> 12.535 | T84: =-(F84-H84)/E84 -> -0.0087 | U84: =R84+T84 -> 0.11665 | V84: =U84*E84 -> 11.665 | W84: =SUMIF(GLS!B:B,K84,GLS!C:C) -> 5.25 | Z84: =-IF(W84+X84+Y84=0,"à vérifier",W84+X84+Y84) -> -5.25 | AA84: =IFERROR((SUMIF($K:$K,K84,$Z:$Z)/COUNTIF($K:$K,K84))*E84/SUMIF($K:$K,K84,$E:$E),0) -> -2.625 | AB84: =AA84/E84 -> -0.02625 | AC84: =AB84+U84 -> 0.0904 | AD84: =AC84/R84 -> 0.72118069 | AE84: =AC84*E84 -> 9.04 | AF84: =IFERROR(-ABS(INDEX('frais amazon 011225-150326'!H:H,MATCH(Reproting_ERPALIN!K84,'frais amazon 011225-150326'!D:D,0))/1.2),"Commande hors la France") -> -4.8916667 | AG84: =IFERROR(AF84*E84/SUMIF($K:$K,K84,$E:$E),0) -> -2.4458333 | AH84: =AG84/E84 -> -0.024458333 | AI84: =AH84+AC84 -> 0.065941667 | AJ84: =AI84/R84 -> 0.52606036 | AK84: =AI84*E84 -> 6.5941667
A85: Aiguille hypodermique à usage unique non sécurisée 18G, 1,2 mm x 50 mm | B85: IN-12X50 | C85: ZARYS International Group sp. z o.o. sp.k. | D85: 2026-01-01 | E85: 100 | F85: 11.41 | G85: 2.495 | H85: 10.2 | I85: 89.4 | J85: FR | K85: 408-3016147-3497103 | L85: =MONTH(D85) -> 1 | M85: =YEAR(D85) -> 2026 | N85: =D85*1 -> 46023 | O85: =F85/E85 -> 0.1141 | P85: =O85*E85 -> 11.41 | Q85: =G85/E85 -> 0.02495 | R85: =O85+Q85 -> 0.13905 | S85: =R85*E85 -> 13.905 | T85: =-(F85-H85)/E85 -> -0.0121 | U85: =R85+T85 -> 0.12695 | V85: =U85*E85 -> 12.695 | W85: =SUMIF(GLS!B:B,K85,GLS!C:C) -> 5.25 | Z85: =-IF(W85+X85+Y85=0,"à vérifier",W85+X85+Y85) -> -5.25 | AA85: =IFERROR((SUMIF($K:$K,K85,$Z:$Z)/COUNTIF($K:$K,K85))*E85/SUMIF($K:$K,K85,$E:$E),0) -> -2.625 | AB85: =AA85/E85 -> -0.02625 | AC85: =AB85+U85 -> 0.1007 | AD85: =AC85/R85 -> 0.72419993 | AE85: =AC85*E85 -> 10.07 | AF85: =IFERROR(-ABS(INDEX('frais amazon 011225-150326'!H:H,MATCH(Reproting_ERPALIN!K85,'frais amazon 011225-150326'!D:D,0))/1.2),"Commande hors la France") -> -4.8916667 | AG85: =IFERROR(AF85*E85/SUMIF($K:$K,K85,$E:$E),0) -> -2.4458333 | AH85: =AG85/E85 -> -0.024458333 | AI85: =AH85+AC85 -> 0.076241667 | AJ85: =AI85/R85 -> 0.54830397 | AK85: =AI85*E85 -> 7.6241667
A86: Comed - Spéculums auriculaires Diamètre 4 mm / Gris - Boite de 250 pièces | B86: 24 700 40A | C86: COMED | D86: 2026-01-01 | E86: 250 | F86: 7.68 | G86: 10.5 | H86: 3.93 | I86: 51.17 | J86: IT | K86: 408-2982363-3382725 | L86: =MONTH(D86) -> 1 | M86: =YEAR(D86) -> 2026 | N86: =D86*1 -> 46023 | O86: =F86/E86 -> 0.03072 | P86: =O86*E86 -> 7.68 | Q86: =G86/E86 -> 0.042 | R86: =O86+Q86 -> 0.07272 | S86: =R86*E86 -> 18.18 | T86: =-(F86-H86)/E86 -> -0.015 | U86: =R86+T86 -> 0.05772 | V86: =U86*E86 -> 14.43 | W86: =SUMIF(GLS!B:B,K86,GLS!C:C) -> 10.72 | Z86: =-IF(W86+X86+Y86=0,"à vérifier",W86+X86+Y86) -> -10.72 | AA86: =IFERROR((SUMIF($K:$K,K86,$Z:$Z)/COUNTIF($K:$K,K86))*E86/SUMIF($K:$K,K86,$E:$E),0) -> -10.72 | AB86: =AA86/E86 -> -0.04288 | AC86: =AB86+U86 -> 0.01484 | AD86: =AC86/R86 -> 0.20407041 | AE86: =AC86*E86 -> 3.71 | AF86: =IFERROR(-ABS(INDEX('frais amazon 011225-150326'!H:H,MATCH(Reproting_ERPALIN!K86,'frais amazon 011225-150326'!D:D,0))/1.2),"Commande hors la France") -> Commande hors la France | AG86: =IFERROR(AF86*E86/SUMIF($K:$K,K86,$E:$E),0) -> 0 | AH86: =AG86/E86 -> 0 | AI86: =AH86+AC86 -> 0.01484 | AJ86: =AI86/R86 -> 0.20407041 | AK86: =AI86*E86 -> 3.71
A87: Aiguille hypodermique à usage unique sécurisée 21G, 0,8 mm x 40 mm - Boite de 50 | B87: INB-08X40 | C87: ZARYS International Group sp. z o.o. sp.k. | D87: 2026-01-01 | E87: 50 | F87: 6.7 | G87: 4.99 | H87: 4.71 | I87: 70.3 | J87: FR | K87: 408-2840850-9093111 | L87: =MONTH(D87) -> 1 | M87: =YEAR(D87) -> 2026 | N87: =D87*1 -> 46023 | O87: =F87/E87 -> 0.134 | P87: =O87*E87 -> 6.7 | Q87: =G87/E87 -> 0.0998 | R87: =O87+Q87 -> 0.2338 | S87: =R87*E87 -> 11.69 | T87: =-(F87-H87)/E87 -> -0.0398 | U87: =R87+T87 -> 0.194 | V87: =U87*E87 -> 9.7 | W87: =SUMIF(GLS!B:B,K87,GLS!C:C) -> 6.4 | Z87: =-IF(W87+X87+Y87=0,"à vérifier",W87+X87+Y87) -> -6.4 | AA87: =IFERROR((SUMIF($K:$K,K87,$Z:$Z)/COUNTIF($K:$K,K87))*E87/SUMIF($K:$K,K87,$E:$E),0) -> -6.4 | AB87: =AA87/E87 -> -0.128 | AC87: =AB87+U87 -> 0.066 | AD87: =AC87/R87 -> 0.28229256 | AE87: =AC87*E87 -> 3.3 | AF87: =IFERROR(-ABS(INDEX('frais amazon 011225-150326'!H:H,MATCH(Reproting_ERPALIN!K87,'frais amazon 011225-150326'!D:D,0))/1.2),"Commande hors la France") -> -2.1583333 | AG87: =IFERROR(AF87*E87/SUMIF($K:$K,K87,$E:$E),0) -> -2.1583333 | AH87: =AG87/E87 -> -0.043166667 | AI87: =AH87+AC87 -> 0.022833333 | AJ87: =AI87/R87 -> 0.097661819 | AK87: =AI87*E87 -> 1.1416667
A88: Aiguille hypodermique à usage unique non sécurisée 21G, 0,8 mm x 50 mm | B88: IN-08X50 | C88: ZARYS International Group sp. z o.o. sp.k. | D88: 2025-12-01 | E88: 100 | F88: 16.06 | G88: 8.75 | H88: 14.6 | I88: 90.91 | J88: ES | K88: 408-2827164-8981127 | L88: =MONTH(D88) -> 12 | M88: =YEAR(D88) -> 2025 | N88: =D88*1 -> 45992 | O88: =F88/E88 -> 0.1606 | P88: =O88*E88 -> 16.06 | Q88: =G88/E88 -> 0.0875 | R88: =O88+Q88 -> 0.2481 | S88: =R88*E88 -> 24.81 | T88: =-(F88-H88)/E88 -> -0.0146 | U88: =R88+T88 -> 0.2335 | V88: =U88*E88 -> 23.35 | W88: =SUMIF(GLS!B:B,K88,GLS!C:C) -> 10.72 | Z88: =-IF(W88+X88+Y88=0,"à vérifier",W88+X88+Y88) -> -10.72 | AA88: =IFERROR((SUMIF($K:$K,K88,$Z:$Z)/COUNTIF($K:$K,K88))*E88/SUMIF($K:$K,K88,$E:$E),0) -> -10.72 | AB88: =AA88/E88 -> -0.1072 | AC88: =AB88+U88 -> 0.1263 | AD88: =AC88/R88 -> 0.50906892 | AE88: =AC88*E88 -> 12.63 | AF88: =IFERROR(-ABS(INDEX('frais amazon 011225-150326'!H:H,MATCH(Reproting_ERPALIN!K88,'frais amazon 011225-150326'!D:D,0))/1.2),"Commande hors la France") -> Commande hors la France | AG88: =IFERROR(AF88*E88/SUMIF($K:$K,K88,$E:$E),0) -> 0 | AH88: =AG88/E88 -> 0 | AI88: =AH88+AC88 -> 0.1263 | AJ88: =AI88/R88 -> 0.50906892 | AK88: =AI88*E88 -> 12.63
A89: TENA - Proskin Wash Glove Gant de Toilette - Boite de 175 pièces | B89: 740500 | C89: TENA | D89: 2025-12-01 | E89: 175 | F89: 11.66 | G89: 0 | H89: 1.14 | I89: 9.8 | J89: FR | K89: 408-2776916-7287558 | L89: =MONTH(D89) -> 12 | M89: =YEAR(D89) -> 2025 | N89: =D89*1 -> 45992 | O89: =F89/E89 -> 0.066628571 | P89: =O89*E89 -> 11.66 | Q89: =G89/E89 -> 0 | R89: =O89+Q89 -> 0.066628571 | S89: =R89*E89 -> 11.66 | T89: =-(F89-H89)/E89 -> -0.060114286 | U89: =R89+T89 -> 0.0065142857 | V89: =U89*E89 -> 1.14 | W89: =SUMIF(GLS!B:B,K89,GLS!C:C) -> 5.48 | Z89: =-IF(W89+X89+Y89=0,"à vérifier",W89+X89+Y89) -> -5.48 | AA89: =IFERROR((SUMIF($K:$K,K89,$Z:$Z)/COUNTIF($K:$K,K89))*E89/SUMIF($K:$K,K89,$E:$E),0) -> -5.48 | AB89: =AA89/E89 -> -0.031314286 | AC89: =AB89+U89 -> -0.0248 | AD89: =AC89/R89 -> -0.37221269 | AE89: =AC89*E89 -> -4.34 | AF89: =IFERROR(-ABS(INDEX('frais amazon 011225-150326'!H:H,MATCH(Reproting_ERPALIN!K89,'frais amazon 011225-150326'!D:D,0))/1.2),"Commande hors la France") -> -2.1583333 | AG89: =IFERROR(AF89*E89/SUMIF($K:$K,K89,$E:$E),0) -> -2.1583333 | AH89: =AG89/E89 -> -0.012333333 | AI89: =AH89+AC89 -> -0.037133333 | AJ89: =AI89/R89 -> -0.55731847 | AK89: =AI89*E89 -> -6.4983333
A90: Abena - Couches adulte intraversables Maternity Pad Super - Sachet de 15 pièces | B90: 1000022654 | C90: Abena | D90: 2026-01-01 | E90: 30 | F90: 14.79 | G90: 0 | H90: 10.52 | I90: 71.1 | J90: FR | K90: 408-2682674-4129125 | L90: =MONTH(D90) -> 1 | M90: =YEAR(D90) -> 2026 | N90: =D90*1 -> 46023 | O90: =F90/E90 -> 0.493 | P90: =O90*E90 -> 14.79 | Q90: =G90/E90 -> 0 | R90: =O90+Q90 -> 0.493 | S90: =R90*E90 -> 14.79 | T90: =-(F90-H90)/E90 -> -0.14233333 | U90: =R90+T90 -> 0.35066667 | V90: =U90*E90 -> 10.52 | W90: =SUMIF(GLS!B:B,K90,GLS!C:C) -> 5.48 | Z90: =-IF(W90+X90+Y90=0,"à vérifier",W90+X90+Y90) -> -5.48 | AA90: =IFERROR((SUMIF($K:$K,K90,$Z:$Z)/COUNTIF($K:$K,K90))*E90/SUMIF($K:$K,K90,$E:$E),0) -> -5.48 | AB90: =AA90/E90 -> -0.18266667 | AC90: =AB90+U90 -> 0.168 | AD90: =AC90/R90 -> 0.34077079 | AE90: =AC90*E90 -> 5.04 | AF90: =IFERROR(-ABS(INDEX('frais amazon 011225-150326'!H:H,MATCH(Reproting_ERPALIN!K90,'frais amazon 011225-150326'!D:D,0))/1.2),"Commande hors la France") -> -2.75 | AG90: =IFERROR(AF90*E90/SUMIF($K:$K,K90,$E:$E),0) -> -2.75 | AH90: =AG90/E90 -> -0.091666667 | AI90: =AH90+AC90 -> 0.076333333 | AJ90: =AI90/R90 -> 0.15483435 | AK90: =AI90*E90 -> 2.29
A91: Abena - Couches adulte intraversables Maternity Pad Super - Sachet de 15 pièces | B91: 1000022654 | C91: Abena | D91: 2026-01-01 | E91: 15 | F91: 6.93 | G91: 4.99 | H91: 4.79 | I91: 69.16 | J91: FR | K91: 408-2524951-3181938 | L91: =MONTH(D91) -> 1 | M91: =YEAR(D91) -> 2026 | N91: =D91*1 -> 46023 | O91: =F91/E91 -> 0.462 | P91: =O91*E91 -> 6.93 | Q91: =G91/E91 -> 0.33266667 | R91: =O91+Q91 -> 0.79466667 | S91: =R91*E91 -> 11.92 | T91: =-(F91-H91)/E91 -> -0.14266667 | U91: =R91+T91 -> 0.652 | V91: =U91*E91 -> 9.78 | W91: =SUMIF(GLS!B:B,K91,GLS!C:C) -> 5.25 | Z91: =-IF(W91+X91+Y91=0,"à vérifier",W91+X91+Y91) -> -5.25 | AA91: =IFERROR((SUMIF($K:$K,K91,$Z:$Z)/COUNTIF($K:$K,K91))*E91/SUMIF($K:$K,K91,$E:$E),0) -> -5.25 | AB91: =AA91/E91 -> -0.35 | AC91: =AB91+U91 -> 0.302 | AD91: =AC91/R91 -> 0.38003356 | AE91: =AC91*E91 -> 4.53 | AF91: =IFERROR(-ABS(INDEX('frais amazon 011225-150326'!H:H,MATCH(Reproting_ERPALIN!K91,'frais amazon 011225-150326'!D:D,0))/1.2),"Commande hors la France") -> -2.2083333 | AG91: =IFERROR(AF91*E91/SUMIF($K:$K,K91,$E:$E),0) -> -2.2083333 | AH91: =AG91/E91 -> -0.14722222 | AI91: =AH91+AC91 -> 0.15477778 | AJ91: =AI91/R91 -> 0.19477069 | AK91: =AI91*E91 -> 2.3216667
A92: HARTMANN - Peha haft latex free 20 m - Bande de fixation élastique et cohésive 10 cm x 20 m (932449) | B92: 300083 | C92: Hartmann | D92: 2026-01-01 | E92: 3 | F92: 19.21 | G92: 10.36 | H92: 9.31 | I92: 48.46 | J92: BE | K92: 408-2523868-5881104 | L92: =MONTH(D92) -> 1 | M92: =YEAR(D92) -> 2026 | N92: =D92*1 -> 46023 | O92: =F92/E92 -> 6.4033333 | P92: =O92*E92 -> 19.21 | Q92: =G92/E92 -> 3.4533333 | R92: =O92+Q92 -> 9.8566667 | S92: =R92*E92 -> 29.57 | T92: =-(F92-H92)/E92 -> -3.3 | U92: =R92+T92 -> 6.5566667 | V92: =U92*E92 -> 19.67 | W92: =SUMIF(GLS!B:B,K92,GLS!C:C) -> 9.39 | Z92: =-IF(W92+X92+Y92=0,"à vérifier",W92+X92+Y92) -> -9.39 | AA92: =IFERROR((SUMIF($K:$K,K92,$Z:$Z)/COUNTIF($K:$K,K92))*E92/SUMIF($K:$K,K92,$E:$E),0) -> -9.39 | AB92: =AA92/E92 -> -3.13 | AC92: =AB92+U92 -> 3.4266667 | AD92: =AC92/R92 -> 0.34764964 | AE92: =AC92*E92 -> 10.28 | AF92: =IFERROR(-ABS(INDEX('frais amazon 011225-150326'!H:H,MATCH(Reproting_ERPALIN!K92,'frais amazon 011225-150326'!D:D,0))/1.2),"Commande hors la France") -> Commande hors la France | AG92: =IFERROR(AF92*E92/SUMIF($K:$K,K92,$E:$E),0) -> 0 | AH92: =AG92/E92 -> 0 | AI92: =AH92+AC92 -> 3.4266667 | AJ92: =AI92/R92 -> 0.34764964 | AK92: =AI92*E92 -> 10.28
A93: Abena - Couches adulte intraversables Maternity Pad Super - Sachet de 15 pièces | B93: 1000022654 | C93: Abena | D93: 2026-01-01 | E93: 15 | F93: 16.05 | G93: 0 | H93: 13.91 | I93: 86.68 | J93: FR | K93: 408-2399142-7169103 | L93: =MONTH(D93) -> 1 | M93: =YEAR(D93) -> 2026 | N93: =D93*1 -> 46023 | O93: =F93/E93 -> 1.07 | P93: =O93*E93 -> 16.05 | Q93: =G93/E93 -> 0 | R93: =O93+Q93 -> 1.07 | S93: =R93*E93 -> 16.05 | T93: =-(F93-H93)/E93 -> -0.14266667 | U93: =R93+T93 -> 0.92733333 | V93: =U93*E93 -> 13.91 | W93: =SUMIF(GLS!B:B,K93,GLS!C:C) -> 5.25 | Z93: =-IF(W93+X93+Y93=0,"à vérifier",W93+X93+Y93) -> -5.25 | AA93: =IFERROR((SUMIF($K:$K,K93,$Z:$Z)/COUNTIF($K:$K,K93))*E93/SUMIF($K:$K,K93,$E:$E),0) -> -5.25 | AB93: =AA93/E93 -> -0.35 | AC93: =AB93+U93 -> 0.57733333 | AD93: =AC93/R93 -> 0.53956386 | AE93: =AC93*E93 -> 8.66 | AF93: =IFERROR(-ABS(INDEX('frais amazon 011225-150326'!H:H,MATCH(Reproting_ERPALIN!K93,'frais amazon 011225-150326'!D:D,0))/1.2),"Commande hors la France") -> -2.9833333 | AG93: =IFERROR(AF93*E93/SUMIF($K:$K,K93,$E:$E),0) -> -2.9833333 | AH93: =AG93/E93 -> -0.19888889 | AI93: =AH93+AC93 -> 0.37844444 | AJ93: =AI93/R93 -> 0.3536864 | AK93: =AI93*E93 -> 5.6766667
A94: Abena - Couche culotte absorbante Pants Premium - Nuit - Niveau 3 - Large - Sachet de 15 pièces | B94: 1000021327 | C94: Abena | D94: 2026-01-01 | E94: 45 | F94: 54.95 | G94: 0 | H94: 24.29 | I94: 44.21 | J94: FR | K94: 408-2340673-0156346 | L94: =MONTH(D94) -> 1 | M94: =YEAR(D94) -> 2026 | N94: =D94*1 -> 46023 | O94: =F94/E94 -> 1.2211111 | P94: =O94*E94 -> 54.95 | Q94: =G94/E94 -> 0 | R94: =O94+Q94 -> 1.2211111 | S94: =R94*E94 -> 54.95 | T94: =-(F94-H94)/E94 -> -0.68133333 | U94: =R94+T94 -> 0.53977778 | V94: =U94*E94 -> 24.29 | W94: =SUMIF(GLS!B:B,K94,GLS!C:C) -> 6.13 | Z94: =-IF(W94+X94+Y94=0,"à vérifier",W94+X94+Y94) -> -6.13 | AA94: =IFERROR((SUMIF($K:$K,K94,$Z:$Z)/COUNTIF($K:$K,K94))*E94/SUMIF($K:$K,K94,$E:$E),0) -> -6.13 | AB94: =AA94/E94 -> -0.13622222 | AC94: =AB94+U94 -> 0.40355556 | AD94: =AC94/R94 -> 0.33048226 | AE94: =AC94*E94 -> 18.16 | AF94: =IFERROR(-ABS(INDEX('frais amazon 011225-150326'!H:H,MATCH(Reproting_ERPALIN!K94,'frais amazon 011225-150326'!D:D,0))/1.2),"Commande hors la France") -> -10.2 | AG94: =IFERROR(AF94*E94/SUMIF($K:$K,K94,$E:$E),0) -> -10.2 | AH94: =AG94/E94 -> -0.22666667 | AI94: =AH94+AC94 -> 0.17688889 | AJ94: =AI94/R94 -> 0.14485896 | AK94: =AI94*E94 -> 7.96
A95: Seringue 3 pièces luer lock stérile 10ml, (Boite de 100 pièces) | B95: CH03010LL | C95: Vitrex Medical | D95: 2026-01-01 | E95: 100 | F95: 14.78 | G95: 0 | H95: 8.98 | I95: 60.76 | J95: FR | K95: 408-2268799-4222759 | L95: =MONTH(D95) -> 1 | M95: =YEAR(D95) -> 2026 | N95: =D95*1 -> 46023 | O95: =F95/E95 -> 0.1478 | P95: =O95*E95 -> 14.78 | Q95: =G95/E95 -> 0 | R95: =O95+Q95 -> 0.1478 | S95: =R95*E95 -> 14.78 | T95: =-(F95-H95)/E95 -> -0.058 | U95: =R95+T95 -> 0.0898 | V95: =U95*E95 -> 8.98 | W95: =SUMIF(GLS!B:B,K95,GLS!C:C) -> 5.48 | Z95: =-IF(W95+X95+Y95=0,"à vérifier",W95+X95+Y95) -> -5.48 | AA95: =IFERROR((SUMIF($K:$K,K95,$Z:$Z)/COUNTIF($K:$K,K95))*E95/SUMIF($K:$K,K95,$E:$E),0) -> -5.48 | AB95: =AA95/E95 -> -0.0548 | AC95: =AB95+U95 -> 0.035 | AD95: =AC95/R95 -> 0.2368065 | AE95: =AC95*E95 -> 3.5 | AF95: =IFERROR(-ABS(INDEX('frais amazon 011225-150326'!H:H,MATCH(Reproting_ERPALIN!K95,'frais amazon 011225-150326'!D:D,0))/1.2),"Commande hors la France") -> -2.7416667 | AG95: =IFERROR(AF95*E95/SUMIF($K:$K,K95,$E:$E),0) -> -2.7416667 | AH95: =AG95/E95 -> -0.027416667 | AI95: =AH95+AC95 -> 0.0075833333 | AJ95: =AI95/R95 -> 0.051308074 | AK95: =AI95*E95 -> 0.75833333
A96: FL MEDICAL - Pots à urine 120 ml avec étiquette avec bouchon à vis - 300 pièces | B96: 25033 | C96: FL MEDICAL | D96: 2026-02-01 | E96: 300 | F96: 32.52 | G96: 14.96 | H96: 16.17 | I96: 49.72 | J96: IT | K96: 408-2253082-7301106 | L96: =MONTH(D96) -> 2 | M96: =YEAR(D96) -> 2026 | N96: =D96*1 -> 46054 | O96: =F96/E96 -> 0.1084 | P96: =O96*E96 -> 32.52 | Q96: =G96/E96 -> 0.049866667 | R96: =O96+Q96 -> 0.15826667 | S96: =R96*E96 -> 47.48 | T96: =-(F96-H96)/E96 -> -0.0545 | U96: =R96+T96 -> 0.10376667 | V96: =U96*E96 -> 31.13 | W96: =SUMIF(GLS!B:B,K96,GLS!C:C) -> 12.06 | Z96: =-IF(W96+X96+Y96=0,"à vérifier",W96+X96+Y96) -> -12.06 | AA96: =IFERROR((SUMIF($K:$K,K96,$Z:$Z)/COUNTIF($K:$K,K96))*E96/SUMIF($K:$K,K96,$E:$E),0) -> -12.06 | AB96: =AA96/E96 -> -0.0402 | AC96: =AB96+U96 -> 0.063566667 | AD96: =AC96/R96 -> 0.4016428 | AE96: =AC96*E96 -> 19.07 | AF96: =IFERROR(-ABS(INDEX('frais amazon 011225-150326'!H:H,MATCH(Reproting_ERPALIN!K96,'frais amazon 011225-150326'!D:D,0))/1.2),"Commande hors la France") -> Commande hors la France | AG96: =IFERROR(AF96*E96/SUMIF($K:$K,K96,$E:$E),0) -> 0 | AH96: =AG96/E96 -> 0 | AI96: =AH96+AC96 -> 0.063566667 | AJ96: =AI96/R96 -> 0.4016428 | AK96: =AI96*E96 -> 19.07
A97: Abena - Couches adulte intraversables Maternity Pad Super - Sachet de 15 pièces | B97: 1000022654 | C97: Abena | D97: 2026-01-01 | E97: 30 | F97: 13.49 | G97: 0 | H97: 9.22 | I97: 68.31 | J97: FR | K97: 408-2244771-4977969 | L97: =MONTH(D97) -> 1 | M97: =YEAR(D97) -> 2026 | N97: =D97*1 -> 46023 | O97: =F97/E97 -> 0.44966667 | P97: =O97*E97 -> 13.49 | Q97: =G97/E97 -> 0 | R97: =O97+Q97 -> 0.44966667 | S97: =R97*E97 -> 13.49 | T97: =-(F97-H97)/E97 -> -0.14233333 | U97: =R97+T97 -> 0.30733333 | V97: =U97*E97 -> 9.22 | W97: =SUMIF(GLS!B:B,K97,GLS!C:C) -> 5.48 | Z97: =-IF(W97+X97+Y97=0,"à vérifier",W97+X97+Y97) -> -5.48 | AA97: =IFERROR((SUMIF($K:$K,K97,$Z:$Z)/COUNTIF($K:$K,K97))*E97/SUMIF($K:$K,K97,$E:$E),0) -> -5.48 | AB97: =AA97/E97 -> -0.18266667 | AC97: =AB97+U97 -> 0.12466667 | AD97: =AC97/R97 -> 0.2772424 | AE97: =AC97*E97 -> 3.74 | AF97: =IFERROR(-ABS(INDEX('frais amazon 011225-150326'!H:H,MATCH(Reproting_ERPALIN!K97,'frais amazon 011225-150326'!D:D,0))/1.2),"Commande hors la France") -> -2.5083333 | AG97: =IFERROR(AF97*E97/SUMIF($K:$K,K97,$E:$E),0) -> -2.5083333 | AH97: =AG97/E97 -> -0.083611111 | AI97: =AH97+AC97 -> 0.041055556 | AJ97: =AI97/R97 -> 0.091302199 | AK97: =AI97*E97 -> 1.2316667
A98: Abena - Couches adulte intraversables Maternity Pad Super - Sachet de 15 pièces | B98: 1000022654 | C98: Abena | D98: 2026-02-01 | E98: 15 | F98: 6.82 | G98: 4.99 | H98: 4.68 | I98: 68.66 | J98: FR | K98: 408-2239098-5649945 | L98: =MONTH(D98) -> 2 | M98: =YEAR(D98) -> 2026 | N98: =D98*1 -> 46054 | O98: =F98/E98 -> 0.45466667 | P98: =O98*E98 -> 6.82 | Q98: =G98/E98 -> 0.33266667 | R98: =O98+Q98 -> 0.78733333 | S98: =R98*E98 -> 11.81 | T98: =-(F98-H98)/E98 -> -0.14266667 | U98: =R98+T98 -> 0.64466667 | V98: =U98*E98 -> 9.67 | W98: =SUMIF(GLS!B:B,K98,GLS!C:C) -> 5.25 | Z98: =-IF(W98+X98+Y98=0,"à vérifier",W98+X98+Y98) -> -5.25 | AA98: =IFERROR((SUMIF($K:$K,K98,$Z:$Z)/COUNTIF($K:$K,K98))*E98/SUMIF($K:$K,K98,$E:$E),0) -> -5.25 | AB98: =AA98/E98 -> -0.35 | AC98: =AB98+U98 -> 0.29466667 | AD98: =AC98/R98 -> 0.3742591 | AE98: =AC98*E98 -> 4.42 | AF98: =IFERROR(-ABS(INDEX('frais amazon 011225-150326'!H:H,MATCH(Reproting_ERPALIN!K98,'frais amazon 011225-150326'!D:D,0))/1.2),"Commande hors la France") -> -2.2 | AG98: =IFERROR(AF98*E98/SUMIF($K:$K,K98,$E:$E),0) -> -2.2 | AH98: =AG98/E98 -> -0.14666667 | AI98: =AH98+AC98 -> 0.148 | AJ98: =AI98/R98 -> 0.18797629 | AK98: =AI98*E98 -> 2.22
A99: MoliCare Skin - Huile protectrice 200ml - spray | B99: 995023 | C99: Hartmann | D99: 2026-01-01 | E99: 1 | F99: 11.4 | G99: 0 | H99: 6.41 | I99: 56.23 | J99: FR | K99: 408-2070536-1700358 | L99: =MONTH(D99) -> 1 | M99: =YEAR(D99) -> 2026 | N99: =D99*1 -> 46023 | O99: =F99/E99 -> 11.4 | P99: =O99*E99 -> 11.4 | Q99: =G99/E99 -> 0 | R99: =O99+Q99 -> 11.4 | S99: =R99*E99 -> 11.4 | T99: =-(F99-H99)/E99 -> -4.99 | U99: =R99+T99 -> 6.41 | V99: =U99*E99 -> 6.41 | W99: =SUMIF(GLS!B:B,K99,GLS!C:C) -> 5.25 | Z99: =-IF(W99+X99+Y99=0,"à vérifier",W99+X99+Y99) -> -5.25 | AA99: =IFERROR((SUMIF($K:$K,K99,$Z:$Z)/COUNTIF($K:$K,K99))*E99/SUMIF($K:$K,K99,$E:$E),0) -> -5.25 | AB99: =AA99/E99 -> -5.25 | AC99: =AB99+U99 -> 1.16 | AD99: =AC99/R99 -> 0.10175439 | AE99: =AC99*E99 -> 1.16 | AF99: =IFERROR(-ABS(INDEX('frais amazon 011225-150326'!H:H,MATCH(Reproting_ERPALIN!K99,'frais amazon 011225-150326'!D:D,0))/1.2),"Commande hors la France") -> -2.1083333 | AG99: =IFERROR(AF99*E99/SUMIF($K:$K,K99,$E:$E),0) -> -2.1083333 | AH99: =AG99/E99 -> -2.1083333 | AI99: =AH99+AC99 -> -0.94833333 | AJ99: =AI99/R99 -> -0.083187135 | AK99: =AI99*E99 -> -0.94833333
A100: Tena - Protection urinaire anatomique comfort ProSkin Extra - Sachet de 40 pièces | B100: 753040 | C100: TENA | D100: 2026-01-01 | E100: 80 | F100: 32.84 | G100: 9.19 | H100: 6.46 | I100: 19.66 | J100: ES | K100: 408-1956151-4877150 | L100: =MONTH(D100) -> 1 | M100: =YEAR(D100) -> 2026 | N100: =D100*1 -> 46023 | O100: =F100/E100 -> 0.4105 | P100: =O100*E100 -> 32.84 | Q100: =G100/E100 -> 0.114875 | R100: =O100+Q100 -> 0.525375 | S100: =R100*E100 -> 42.03 | T100: =-(F100-H100)/E100 -> -0.32975 | U100: =R100+T100 -> 0.195625 | V100: =U100*E100 -> 15.65 | W100: =SUMIF(GLS!B:B,K100,GLS!C:C) -> 12.73 | Z100: =-IF(W100+X100+Y100=0,"à vérifier",W100+X100+Y100) -> -12.73 | AA100: =IFERROR((SUMIF($K:$K,K100,$Z:$Z)/COUNTIF($K:$K,K100))*E100/SUMIF($K:$K,K100,$E:$E),0) -> -12.73 | AB100: =AA100/E100 -> -0.159125 | AC100: =AB100+U100 -> 0.0365 | AD100: =AC100/R100 -> 0.069474185 | AE100: =AC100*E100 -> 2.92 | AF100: =IFERROR(-ABS(INDEX('frais amazon 011225-150326'!H:H,MATCH(Reproting_ERPALIN!K100,'frais amazon 011225-150326'!D:D,0))/1.2),"Commande hors la France") -> Commande hors la France | AG100: =IFERROR(AF100*E100/SUMIF($K:$K,K100,$E:$E),0) -> 0 | AH100: =AG100/E100 -> 0 | AI100: =AH100+AC100 -> 0.0365 | AJ100: =AI100/R100 -> 0.069474185 | AK100: =AI100*E100 -> 2.92
...

Sheet frais amazon 011225-150326
A1: Date | B1: Statut de la transaction | C1: Type de transaction | D1: Numéro de la commande | E1: Détails sur le produit | F1: Total des frais produit | G1: Total des rabais promotionnels | H1: Commissions Amazon | I1: Autres | J1: Total (EUR)
A2: 46096 | B2: Sorti | C2: Paiement de la commande | D2: 408-7107728-4926706 | E2: MoliCare Premium Elastic Slip : 10 goutt... | F2: 18 | G2: 0 | H2: -4.01 | I2: 3.6 | J2: 17.59
A3: 46096 | B3: Sorti | C3: Paiement de la commande | D3: 402-8980354-7775534 | E3: Abena Premium Lot de 2x14 serviettes hyg... | F3: 13.53 | G3: 0 | H3: -3 | I3: 2.71 | J3: 13.24
A4: 46096 | B4: Sorti | C4: Paiement de la commande | D4: 405-0206505-2222716 | E4: Abena Premium Lot de 2x14 serviettes hyg... | F4: 13.53 | G4: 0 | H4: -3 | I4: 2.71 | J4: 13.24
A5: 46096 | B5: Sorti | C5: Paiement de la commande | D5: 408-1635227-2411501 | E5: iD Intime Pants Normal Discret et Confor... | F5: 11.75 | G5: 0 | H5: -3.73 | I5: 8.34 | J5: 16.36
A6: 46096 | B6: Sorti | C6: Paiement de la commande | D6: 403-7237882-4667552 | E6: Blouse visiteur jetable - Lot de 40 | F6: 19.2 | G6: 0 | H6: -4.28 | I6: 3.84 | J6: 18.76
A7: 46096 | B7: Sorti | C7: Remboursement | D7: 171-9729146-8673155 | E7: Aiguille d'injection de sécurité, stéril... | F7: -8.76 | G7: 0 | H7: 2.45 | I7: -7.74 | J7: -14.05
A8: 46096 | B8: Sorti | C8: Paiement de la commande | D8: 171-9729146-8673155 | E8: Aiguille d'injection de sécurité, stéril... | F8: 8.76 | G8: 0 | H8: -3.05 | I8: 7.74 | J8: 13.45
A9: 46096 | B9: Sorti | C9: Paiement de la commande | D9: 406-6036257-1683508 | E9: KIBERTIC - 100 Pcs Tablier Plastique Jet... | F9: 27.9 | G9: 0 | H9: -2.02 | I9: 5.58 | J9: 31.46
A10: 46095 | B10: Sorti | C10: Paiement de la commande | D10: 405-5177594-4800327 | E10: Abena Premium Lot de 2x14 serviettes hyg... | F10: 13.53 | G10: 0 | H10: -3.02 | I10: 2.71 | J10: 13.22
A11: 46095 | B11: Sorti | C11: Solde non disponible | D11: --- | E11: Montant de la réserve actuelle | F11: 0 | G11: 0 | H11: 0 | I11: -749.94 | J11: -749.94
A12: 46095 | B12: Sorti | C12: Solde non disponible de la période précédente | D12: --- | E12: Solde du montant de la réserve précédente | F12: 0 | G12: 0 | H12: 0 | I12: 749.94 | J12: 749.94
A13: 46095 | B13: Différé | C13: Paiement de la commande | D13: 402-7877131-5482714 | E13: Seringue stérile Luer Lock CHIRANA 3 piè... | F13: 13.96 | G13: 0 | H13: -3.1 | I13: 2.79 | J13: 13.65
... A326: 46087 | B326: Sorti | C326: Paiement de la commande | D326: 406-1009443-3154763 | E326: Abena Premium Lot de 2x14 serviettes hyg... | F326: 13.53 | G326: 0 | H326: -3.02 | I326: 2.71 | J326: 13.22
A327: 46086 | B327: Sorti | C327: Paiement de la commande | D327: 402-8113032-0362723 | E327: =-LILLE Suprem Fit Extra+ Incontinence mo... -> #NAME? | F327: 19.77 | G327: 0 | H327: -4.4 | I327: 3.96 | J327: 19.33
A328: 46086 | B328: Sorti | C328: Paiement de la commande | D328: 407-6832828-0098739 | E328: Sonde de Foley à deux voies avec valve e... | F328: 16.43 | G328: 0 | H328: -4.77 | I328: 9.28 | J328: 20.94
A329: 46086 | B329: Sorti | C329: Paiement de la commande | D329: 404-2405113-4545904 | E329: MoliCare Premium Elastic Lot de 14 slips... | F329: 80.2 | G329: 0 | H329: -17.85 | I329: 16.04 | J329: 78.39
A330: 46086 | B330: Sorti | C330: Paiement de la commande | D330: 405-3331286-9894718 | E330: Pansement non tissé avec compresse absor... | F330: 14.37 | G330: 0 | H330: -4.29 | I330: 8.86 | J330: 18.94
A331: 46086 | B331: Sorti | C331: Paiement de la commande | D331: 404-6995517-3984333 | E331: Hartmann - Carrés de Soin 50g Octolin - ... | F331: 5.59 | G331: 0 | H331: -1.25 | I331: 7.11 | J331: 11.45
A332: 46086 | B332: Sorti | C332: Paiement de la commande | D332: 402-9514833-3010705 | E332: Molicare Premium Fixpants - Slip de Main... | F332: 8.47 | G332: 0 | H332: -3 | I332: 7.68 | J332: 13.15
A333: 46086 | B333: Sorti | C333: Paiement de la commande | D333: 402-3761586-4925108 | E333: ABENA Slip Premium Lot de 3 paquets de 2... | F333: 97.68 | G333: 0 | H333: -21.74 | I333: 19.54 | J333: 95.48
A334: 46086 | B334: Sorti | C334: Paiement de la commande | D334: 408-1142178-0097115 | E334: Sterilux Pads BIO - Rectangles De Coton ... | F334: 16.26 | G334: 0 | H334: -2.54 | I334: 9.23 | J334: 22.95
A335: 46086 | B335: Sorti | C335: Paiement de la commande | D335: 405-5199459-5829963 | E335: iD Expert Lot de 28 slips taille M super... | F335: 22.14 | G335: 0 | H335: -6.03 | I335: 10.42 | J335: 26.53
A336: 46086 | B336: Sorti | C336: Paiement de la commande | D336: 405-9534028-8448320 | E336: Abena Premium Lot de 2x14 serviettes hyg... | F336: 13.53 | G336: 0 | H336: -3.02 | I336: 2.71 | J336: 13.22
A337: 46086 | B337: Sorti | C337: Paiement de la commande | D337: 407-5775677-3730730 | E337: Zarys Seringue à usage unique en 3 parti... | F337: 21.38 | G337: 0 | H337: -5.86 | I337: 10.27 | J337: 25.79
A338: 46086 | B338: Sorti | C338: Paiement de la commande | D338: 406-3225484-4849966 | E338: Abena Premium Lot de 2x14 serviettes hyg... | F338: 13.53 | G338: 0 | H338: -3.02 | I338: 2.71 | J338: 13.22
A339: 46086 | B339: Sorti | C339: Paiement de la commande | D339: 406-5511120-6409958 | E339: Zarys Seringue à usage unique en 3 parti... | F339: 11.62 | G339: 0 | H339: -3.7 | I339: 8.31 | J339: 16.23
... A2145: 45992 | B2145: Sorti | C2145: Remboursement | D2145: 402-4814753-1215527 | E2145: Lille Classic Bed Extra 60 x 90 cm - Car... | F2145: -56.76 | G2145: 0 | H2145: 11.09 | I2145: -17.34 | J2145: -63.01

Sheet GLS
A1: NumÃ©ro de colis | B1: Client RÃ©fÃ©rence 1 | C1: Total facturé
A2: 00KEHAT6 | B2: 8869 | C2: 3.5 | D2: =IF(COUNTIFS(A:A,A2,B:B,B2,C:C,C2)>1,"Doublon","Unique") -> Unique
A3: 00KIXPSK | B3: WS160321 | C3: 6.7 | D3: =IF(COUNTIFS(A:A,A3,B:B,B3,C:C,C3)>1,"Doublon","Unique") -> Unique
A4: 00KI50EZ | B4: 9178 | C4: 6.7 | D4: =IF(COUNTIFS(A:A,A4,B:B,B4,C:C,C4)>1,"Doublon","Unique") -> Unique
A5: 00KI50CU | B5: 9143 | C5: -0.02 | D5: =IF(COUNTIFS(A:A,A5,B:B,B5,C:C,C5)>1,"Doublon","Unique") -> Unique
A6: 00KI50F8 | B6: 9216 | C6: -0.5 | D6: =IF(COUNTIFS(A:A,A6,B:B,B6,C:C,C6)>1,"Doublon","Unique") -> Unique
A7: 00KI50CP | B7: 9139 | C7: -0.5 | D7: =IF(COUNTIFS(A:A,A7,B:B,B7,C:C,C7)>1,"Doublon","Unique") -> Unique
A8: 00KJ48Z5 | B8: 405-4708345-6904338 | C8: 5.48 | D8: =IF(COUNTIFS(A:A,A8,B:B,B8,C:C,C8)>1,"Doublon","Unique") -> Unique
A9: 00KJ48Z5 | B9: 405-4708345-6904338 | C9: 5.25 | D9: =IF(COUNTIFS(A:A,A9,B:B,B9,C:C,C9)>1,"Doublon","Unique") -> Unique
A10: 00KI50FX | B10: 8745 | C10: -0.5 | D10: =IF(COUNTIFS(A:A,A10,B:B,B10,C:C,C10)>1,"Doublon","Unique") -> Unique
A11: 00KI50HR | B11: 8967 | C11: -0.5 | D11: =IF(COUNTIFS(A:A,A11,B:B,B11,C:C,C11)>1,"Doublon","Unique") -> Unique
A12: 00KI50HK | B12: 9319 | C12: -0.5 | D12: =IF(COUNTIFS(A:A,A12,B:B,B12,C:C,C12)>1,"Doublon","Unique") -> Unique
A13: 00KI50F5 | B13: 9208 | C13: -0.5 | D13: =IF(COUNTIFS(A:A,A13,B:B,B13,C:C,C13)>1,"Doublon","Unique") -> Unique
A14: 00KI50CV | B14: 9145 | C14: -0.5 | D14: =IF(COUNTIFS(A:A,A14,B:B,B14,C:C,C14)>1,"Doublon","Unique") -> Unique
A15: 00KI50G7 | B15: 9256 | C15: -0.5 | D15: =IF(COUNTIFS(A:A,A15,B:B,B15,C:C,C15)>1,"Doublon","Unique") -> Unique
A16: 00KIXYSJ | B16: 403-9264929-6249967 | C16: 5.5 | D16: =IF(COUNTIFS(A:A,A16,B:B,B16,C:C,C16)>1,"Doublon","Unique") -> Unique
A17: 00KI50G7 | B17: 9256 | C17: -0.02 | D17: =IF(COUNTIFS(A:A,A17,B:B,B17,C:C,C17)>1,"Doublon","Unique") -> Unique
A18: 00KI50I0 | B18: 9256 | C18: -0.04 | D18: =IF(COUNTIFS(A:A,A18,B:B,B18,C:C,C18)>1,"Doublon","Unique") -> Unique
A19: 00KI50G7 | B19: 9256 | C19: 8.1 | D19: =IF(COUNTIFS(A:A,A19,B:B,B19,C:C,C19)>1,"Doublon","Unique") -> Unique
A20: 00KI50I0 | B20: 9256 | C20: 8.1 | D20: =IF(COUNTIFS(A:A,A20,B:B,B20,C:C,C20)>1,"Doublon","Unique") -> Unique
A21: 00KI50EQ | B21: 9123 | C21: 6.57 | D21: =IF(COUNTIFS(A:A,A21,B:B,B21,C:C,C21)>1,"Doublon","Unique") -> Unique
A22: 00KIW45E | B22: 408-3160821-7768310 | C22: 5.25 | D22: =IF(COUNTIFS(A:A,A22,B:B,B22,C:C,C22)>1,"Doublon","Unique") -> Unique
A23: 00KIXGM9 | B23: 407-2430595-1536334 | C23: 5.25 | D23: =IF(COUNTIFS(A:A,A23,B:B,B23,C:C,C23)>1,"Doublon","Unique") -> Unique
A24: 00KI50HM | B24: 9320 | C24: 5.5 | D24: =IF(COUNTIFS(A:A,A24,B:B,B24,C:C,C24)>1,"Doublon","Unique") -> Unique
A25: 00KIXGUQ | B25: 406-4359445-7162731 | C25: 5.25 | D25: =IF(COUNTIFS(A:A,A25,B:B,B25,C:C,C25)>1,"Doublon","Unique") -> Unique
A26: 00KIXXXY | B26: 408-3376791-7795524 | C26: 5.48 | D26: =IF(COUNTIFS(A:A,A26,B:B,B26,C:C,C26)>1,"Doublon","Unique") -> Unique
A27: 00KIXPSK | B27: WS160321 | C27: -0.5 | D27: =IF(COUNTIFS(A:A,A27,B:B,B27,C:C,C27)>1,"Doublon","Unique") -> Unique
A28: 00KIXPSK | B28: WS160321 | C28: -1 | D28: =IF(COUNTIFS(A:A,A28,B:B,B28,C:C,C28)>1,"Doublon","Unique") -> Unique
A29: 00KI50EC | B29: 9143 | C29: -0.05 | D29: =IF(COUNTIFS(A:A,A29,B:B,B29,C:C,C29)>1,"Doublon","Unique") -> Unique
A30: 00KI50ED | B30: 9143 | C30: -0.05 | D30: =IF(COUNTIFS(A:A,A30,B:B,B30,C:C,C30)>1,"Doublon","Unique") -> Unique
A31: 00KI50CU | B31: 9143 | C31: 6.57 | D31: =IF(COUNTIFS(A:A,A31,B:B,B31,C:C,C31)>1,"Doublon","Unique") -> Unique
A32: 00KI50EC | B32: 9143 | C32: 6.84 | D32: =IF(COUNTIFS(A:A,A32,B:B,B32,C:C,C32)>1,"Doublon","Unique") -> Unique
A33: 00KI50ED | B33: 9143 | C33: 8.38 | D33: =IF(COUNTIFS(A:A,A33,B:B,B33,C:C,C33)>1,"Doublon","Unique") -> Unique
A34: 00KI50DY | B34: 9187 | C34: 6.84 | D34: =IF(COUNTIFS(A:A,A34,B:B,B34,C:C,C34)>1,"Doublon","Unique") -> Unique
A35: 00KI50BW | B35: 8819 | C35: 5.25 | D35: =IF(COUNTIFS(A:A,A35,B:B,B35,C:C,C35)>1,"Doublon","Unique") -> Unique
A36: 00KI50G1 | B36: 9249 | C36: 5.25 | D36: =IF(COUNTIFS(A:A,A36,B:B,B36,C:C,C36)>1,"Doublon","Unique") -> Unique
A37: 00KI50FM | B37: 9232 | C37: 5.48 | D37: =IF(COUNTIFS(A:A,A37,B:B,B37,C:C,C37)>1,"Doublon","Unique") -> Unique
A38: 00KI50CU | B38: 9143 | C38: -0.5 | D38: =IF(COUNTIFS(A:A,A38,B:B,B38,C:C,C38)>1,"Doublon","Unique") -> Unique
A39: 00KI50HF | B39: 9316 | C39: -0.5 | D39: =IF(COUNTIFS(A:A,A39,B:B,B39,C:C,C39)>1,"Doublon","Unique") -> Unique
A40: 00KI50D8 | B40: 9157 | C40: -0.5 | D40: =IF(COUNTIFS(A:A,A40,B:B,B40,C:C,C40)>1,"Doublon","Unique") -> Unique
... A42: 00KI50C1 | B42: 9099 | C42: -0.5 | D42: =IF(COUNTIFS(A:A,A42,B:B,B42,C:C,C42)>1,"Doublon","Unique") -> Unique
A43: 00KIYPBS | B43: MG771111 | C43: -0.5 | D43: =IF(COUNTIFS(A:A,A43,B:B,B43,C:C,C43)>1,"Doublon","Unique") -> Unique
A44: 00KIWRHL | B44: BL0021307 | C44: -0.5 | D44: =IF(COUNTIFS(A:A,A44,B:B,B44,C:C,C44)>1,"Doublon","Unique") -> Unique
A45: 00KIXPS4 | B45: PHARM15 | C45: -0.5 | D45: =IF(COUNTIFS(A:A,A45,B:B,B45,C:C,C45)>1,"Doublon","Unique") -> Unique
A46: 00KJ0X9H | B46: c.plichon@chu-tours. | C46: -0.5 | D46: =IF(COUNTIFS(A:A,A46,B:B,B46,C:C,C46)>1,"Doublon","Unique") -> Unique
A47: 00KIT07I | B47: 22001901 | C47: -0.5 | D47: =IF(COUNTIFS(A:A,A47,B:B,B47,C:C,C47)>1,"Doublon","Unique") -> Unique
A48: 00KI50HK | B48: 9319 | C48: -0.02 | D48: =IF(COUNTIFS(A:A,A48,B:B,B48,C:C,C48)>1,"Doublon","Unique") -> Unique
A49: 00KI50HL | B49: 9319 | C49: -0.04 | D49: =IF(COUNTIFS(A:A,A49,B:B,B49,C:C,C49)>1,"Doublon","Unique") -> Unique
A50: 00KI50HK | B50: 9319 | C50: 8.1 | D50: =IF(COUNTIFS(A:A,A50,B:B,B50,C:C,C50)>1,"Doublon","Unique") -> Unique
A51: 00KI50HL | B51: 9319 | C51: 8.38 | D51: =IF(COUNTIFS(A:A,A51,B:B,B51,C:C,C51)>1,"Doublon","Unique") -> Unique
A52: 00KI50C4 | B52: 9105 | C52: 5.5 | D52: =IF(COUNTIFS(A:A,A52,B:B,B52,C:C,C52)>1,"Doublon","Unique") -> Unique
A53: 00KI50E1 | B53: 9191 | C53: 5.25 | D53: =IF(COUNTIFS(A:A,A53,B:B,B53,C:C,C53)>1,"Doublon","Unique") -> Unique
A54: 00KIXXWU | B54: 407-4862695-0957931 | C54: 5.48 | D54: =IF(COUNTIFS(A:A,A54,B:B,B54,C:C,C54)>1,"Doublon","Unique") -> Unique
A55: 00KJ4UA4 | B55: 405-0903014-7910700 | C55: 5.25 | D55: =IF(COUNTIFS(A:A,A55,B:B,B55,C:C,C55)>1,"Doublon","Unique") -> Unique
A56: 00KIXF3E | B56: 171-8956593-1819530 | C56: 5.25 | D56: =IF(COUNTIFS(A:A,A56,B:B,B56,C:C,C56)>1,"Doublon","Unique") -> Unique
A57: 00KI50F5 | B57: 9208 | C57: -0.02 | D57: =IF(COUNTIFS(A:A,A57,B:B,B57,C:C,C57)>1,"Doublon","Unique") -> Unique
A58: 00KI50F6 | B58: 9208 | C58: -0.04 | D58: =IF(COUNTIFS(A:A,A58,B:B,B58,C:C,C58)>1,"Doublon","Unique") -> Unique
A59: 00KI50I6 | B59: 8967 | C59: -0.04 | D59: =IF(COUNTIFS(A:A,A59,B:B,B59,C:C,C59)>1,"Doublon","Unique") -> Unique
A60: 00KI50HR | B60: 8967 | C60: 6.57 | D60: =IF(COUNTIFS(A:A,A60,B:B,B60,C:C,C60)>1,"Doublon","Unique") -> Unique
A61: 00KI50I6 | B61: 8967 | C61: 6.57 | D61: =IF(COUNTIFS(A:A,A61,B:B,B61,C:C,C61)>1,"Doublon","Unique") -> Unique
A62: 00KIXZD6 | B62: 404-6226048-1426701 | C62: 5.25 | D62: =IF(COUNTIFS(A:A,A62,B:B,B62,C:C,C62)>1,"Doublon","Unique") -> Unique
A63: 00KJ4EME | B63: 403-7683016-4898724 | C63: 5.25 | D63: =IF(COUNTIFS(A:A,A63,B:B,B63,C:C,C63)>1,"Doublon","Unique") -> Unique
A64: 00KI50EW | B64: 9162 | C64: 9.99 | D64: =IF(COUNTIFS(A:A,A64,B:B,B64,C:C,C64)>1,"Doublon","Unique") -> Unique
A65: 00KIXEJU | B65: 408-2268799-4222759 | C65: 5.48 | D65: =IF(COUNTIFS(A:A,A65,B:B,B65,C:C,C65)>1,"Doublon","Unique") -> Unique
A66: 00KIXFB1 | B66: 402-2080311-7856364 | C66: 5.25 | D66: =IF(COUNTIFS(A:A,A66,B:B,B66,C:C,C66)>1,"Doublon","Unique") -> Unique
A67: 00KIXEQ8 | B67: 404-3647745-4253930 | C67: 5.48 | D67: =IF(COUNTIFS(A:A,A67,B:B,B67,C:C,C67)>1,"Doublon","Unique") -> Unique
A68: 00KJ4TPV | B68: 402-8703509-3570730 | C68: 5.25 | D68: =IF(COUNTIFS(A:A,A68,B:B,B68,C:C,C68)>1,"Doublon","Unique") -> Unique
A69: 00KIYK2L | B69: 402-4405062-5020362 | C69: 5.25 | D69: =IF(COUNTIFS(A:A,A69,B:B,B69,C:C,C69)>1,"Doublon","Unique") -> Unique
A70: 00KI50F0 | B70: 9180 | C70: 10.28 | D70: =IF(COUNTIFS(A:A,A70,B:B,B70,C:C,C70)>1,"Doublon","Unique") -> Unique
A71: 00KIWQK9 | B71: 407-4287445-1666746 | C71: 5.25 | D71: =IF(COUNTIFS(A:A,A71,B:B,B71,C:C,C71)>1,"Doublon","Unique") -> Unique
A72: 00KI50EV | B72: 9141 | C72: 8.96 | D72: =IF(COUNTIFS(A:A,A72,B:B,B72,C:C,C72)>1,"Doublon","Unique") -> Unique
A73: 00KJ4Z3R | B73: 402-1681287-8004335 | C73: 5.25 | D73: =IF(COUNTIFS(A:A,A73,B:B,B73,C:C,C73)>1,"Doublon","Unique") -> Unique
A74: 00KJ32SW | B74: 171-4283870-2766716 | C74: 5.48 | D74: =IF(COUNTIFS(A:A,A74,B:B,B74,C:C,C74)>1,"Doublon","Unique") -> Unique
A75: 00KJ30X3 | B75: 408-5814323-4233141 | C75: 9.22 | D75: =IF(COUNTIFS(A:A,A75,B:B,B75,C:C,C75)>1,"Doublon","Unique") -> Unique
A76: 00KI50FW | B76: 9243 | C76: 5.5 | D76: =IF(COUNTIFS(A:A,A76,B:B,B76,C:C,C76)>1,"Doublon","Unique") -> Unique
A77: 00KI50F5 | B77: 9208 | C77: 7.1 | D77: =IF(COUNTIFS(A:A,A77,B:B,B77,C:C,C77)>1,"Doublon","Unique") -> Unique
A78: 00KI50F6 | B78: 9208 | C78: 7.36 | D78: =IF(COUNTIFS(A:A,A78,B:B,B78,C:C,C78)>1,"Doublon","Unique") -> Unique
A79: 00KIW5Z0 | B79: 406-2338658-6762761 | C79: 5.48 | D79: =IF(COUNTIFS(A:A,A79,B:B,B79,C:C,C79)>1,"Doublon","Unique") -> Unique
A80: 00KI50CV | B80: 9145 | C80: -0.02 | D80: =IF(COUNTIFS(A:A,A80,B:B,B80,C:C,C80)>1,"Doublon","Unique") -> Unique
A81: 00KI50E9 | B81: 9145 | C81: -0.04 | D81: =IF(COUNTIFS(A:A,A81,B:B,B81,C:C,C81)>1,"Doublon","Unique") -> Unique
A82: 00KI50E9 | B82: 9145 | C82: 7.36 | D82: =IF(COUNTIFS(A:A,A82,B:B,B82,C:C,C82)>1,"Doublon","Unique") -> Unique
A83: 00KI50CV | B83: 9145 | C83: 8.67 | D83: =IF(COUNTIFS(A:A,A83,B:B,B83,C:C,C83)>1,"Doublon","Unique") -> Unique
A84: 00KI50HA | B84: 9307 | C84: 5.5 | D84: =IF(COUNTIFS(A:A,A84,B:B,B84,C:C,C84)>1,"Doublon","Unique") -> Unique
A85: 00KI50ER | B85: 9130 | C85: 7.36 | D85: =IF(COUNTIFS(A:A,A85,B:B,B85,C:C,C85)>1,"Doublon","Unique") -> Unique
A86: 00KJ3QGN | B86: 403-7259142-0945123 | C86: 5.48 | D86: =IF(COUNTIFS(A:A,A86,B:B,B86,C:C,C86)>1,"Doublon","Unique") -> Unique
A87: 00KJ3ITW | B87: 171-3077738-2865901 | C87: 5.25 | D87: =IF(COUNTIFS(A:A,A87,B:B,B87,C:C,C87)>1,"Doublon","Unique") -> Unique
A88: 00KIRZBA | B88: BL0021276 | C88: 6.84 | D88: =IF(COUNTIFS(A:A,A88,B:B,B88,C:C,C88)>1,"Doublon","Unique") -> Unique
A89: 00KIT089 | B89: 2600004/9991 | C89: 5.49 | D89: =IF(COUNTIFS(A:A,A89,B:B,B89,C:C,C89)>1,"Doublon","Unique") -> Unique
A90: 00KIYPB9 | B90: A1154341 | C90: 6.57 | D90: =IF(COUNTIFS(A:A,A90,B:B,B90,C:C,C90)>1,"Doublon","Unique") -> Unique
A91: 00KIXPS5 | B91: PHARM15 | C91: 12.29 | D91: =IF(COUNTIFS(A:A,A91,B:B,B91,C:C,C91)>1,"Doublon","Unique") -> Unique
A92: 00KIXPS4 | B92: PHARM15 | C92: 12.29 | D92: =IF(COUNTIFS(A:A,A92,B:B,B92,C:C,C92)>1,"Doublon","Unique") -> Unique
A93: 00KIXPS5 | B93: PHARM15 | C93: -0.04 | D93: =IF(COUNTIFS(A:A,A93,B:B,B93,C:C,C93)>1,"Doublon","Unique") -> Unique
A94: 00KIXPS4 | B94: PHARM15 | C94: -0.02 | D94: =IF(COUNTIFS(A:A,A94,B:B,B94,C:C,C94)>1,"Doublon","Unique") -> Unique
A95: 00KIT06F | B95: PHARM38 | C95: 7.1 | D95: =IF(COUNTIFS(A:A,A95,B:B,B95,C:C,C95)>1,"Doublon","Unique") -> Unique
A96: 00KIWRHM | B96: BL0021307 | C96: 9.22 | D96: =IF(COUNTIFS(A:A,A96,B:B,B96,C:C,C96)>1,"Doublon","Unique") -> Unique
A97: 00KIWRHL | B97: BL0021307 | C97: 9.22 | D97: =IF(COUNTIFS(A:A,A97,B:B,B97,C:C,C97)>1,"Doublon","Unique") -> Unique
... A104: 00KIYPBT | B104: MG771111 | C104: -0.04 | D104: =IF(COUNTIFS(A:A,A104,B:B,B104,C:C,C104)>1,"Doublon","Unique") -> Unique
A105: 00KJ0X9V | B105: 26000335 | C105: 5.49 | D105: =IF(COUNTIFS(A:A,A105,B:B,B105,C:C,C105)>1,"Doublon","Unique") -> Unique
A106: 00KIT07I | B106: 22001901 | C106: 10.28 | D106: =IF(COUNTIFS(A:A,A106,B:B,B106,C:C,C106)>1,"Doublon","Unique") -> Unique
A107: 00KIWKGO | B107: 22001901 | C107: 9.22 | D107: =IF(COUNTIFS(A:A,A107,B:B,B107,C:C,C107)>1,"Doublon","Unique") -> Unique
...

Sheet Analyse ==>

Sheet Parametres_Dates
A2: Date début | B2: 45962
A3: Date de fin | B3: 46142

Sheet Classement des produits
A1: SKU du produit | B1: CA sur la période | C1: Classement
A2: IN-08X50 | B2: =SUMIFS(Reproting_ERPALIN!S:S,Reproting_ERPALIN!B:B,'Classement des produits'!A2,Reproting_ERPALIN!N:N,">"&Parametres_Dates!$B$2,Reproting_ERPALIN!$N:$N,"<="&Parametres_Dates!$B$3) -> 512.84333 | C2: =RANK(B2,$B$2:$B$234) -> 9
A3: IN-05X40 | B3: =SUMIFS(Reproting_ERPALIN!S:S,Reproting_ERPALIN!B:B,'Classement des produits'!A3,Reproting_ERPALIN!N:N,">"&Parametres_Dates!$B$2,Reproting_ERPALIN!$N:$N,"<="&Parametres_Dates!$B$3) -> 799.40833 | C3: =RANK(B3,$B$2:$B$234) -> 4
A4: CH03010LL | B4: =SUMIFS(Reproting_ERPALIN!S:S,Reproting_ERPALIN!B:B,'Classement des produits'!A4,Reproting_ERPALIN!N:N,">"&Parametres_Dates!$B$2,Reproting_ERPALIN!$N:$N,"<="&Parametres_Dates!$B$3) -> 394.73333 | C4: =RANK(B4,$B$2:$B$234) -> 10
A5: CH18200 | B5: =SUMIFS(Reproting_ERPALIN!S:S,Reproting_ERPALIN!B:B,'Classement des produits'!A5,Reproting_ERPALIN!N:N,">"&Parametres_Dates!$B$2,Reproting_ERPALIN!$N:$N,"<="&Parametres_Dates!$B$3) -> 15.92 | C5: =RANK(B5,$B$2:$B$234) -> 192
A6: 1000022654 | B6: =SUMIFS(Reproting_ERPALIN!S:S,Reproting_ERPALIN!B:B,'Classement des produits'!A6,Reproting_ERPALIN!N:N,">"&Parametres_Dates!$B$2,Reproting_ERPALIN!$N:$N,"<="&Parametres_Dates!$B$3) -> 2219.89 | C6: =RANK(B6,$B$2:$B$234) -> 1
A7: 413772 | B7: =SUMIFS(Reproting_ERPALIN!S:S,Reproting_ERPALIN!B:B,'Classement des produits'!A7,Reproting_ERPALIN!N:N,">"&Parametres_Dates!$B$2,Reproting_ERPALIN!$N:$N,"<="&Parametres_Dates!$B$3) -> 147.54 | C7: =RANK(B7,$B$2:$B$234) -> 37
A8: NL105-S-40 | B8: =SUMIFS(Reproting_ERPALIN!S:S,Reproting_ERPALIN!B:B,'Classement des produits'!A8,Reproting_ERPALIN!N:N,">"&Parametres_Dates!$B$2,Reproting_ERPALIN!$N:$N,"<="&Parametres_Dates!$B$3) -> 35.04 | C8: =RANK(B8,$B$2:$B$234) -> 132
A9: 931305 | B9: =SUMIFS(Reproting_ERPALIN!S:S,Reproting_ERPALIN!B:B,'Classement des produits'!A9,Reproting_ERPALIN!N:N,">"&Parametres_Dates!$B$2,Reproting_ERPALIN!$N:$N,"<="&Parametres_Dates!$B$3) -> 18.71 | C9: =RANK(B9,$B$2:$B$234) -> 184
A10: 684358 | B10: =SUMIFS(Reproting_ERPALIN!S:S,Reproting_ERPALIN!B:B,'Classement des produits'!A10,Reproting_ERPALIN!N:N,">"&Parametres_Dates!$B$2,Reproting_ERPALIN!$N:$N,"<="&Parametres_Dates!$B$3) -> 26.147857 | C10: =RANK(B10,$B$2:$B$234) -> 156
A11: 684352 | B11: =SUMIFS(Reproting_ERPALIN!S:S,Reproting_ERPALIN!B:B,'Classement des produits'!A11,Reproting_ERPALIN!N:N,">"&Parametres_Dates!$B$2,Reproting_ERPALIN!$N:$N,"<="&Parametres_Dates!$B$3) -> 149.65214 | C11: =RANK(B11,$B$2:$B$234) -> 33
A12: IN-09X25 | B12: =SUMIFS(Reproting_ERPALIN!S:S,Reproting_ERPALIN!B:B,'Classement des produits'!A12,Reproting_ERPALIN!N:N,">"&Parametres_Dates!$B$2,Reproting_ERPALIN!$N:$N,"<="&Parametres_Dates!$B$3) -> 187.14167 | C12: =RANK(B12,$B$2:$B$234) -> 27
A13: IN-08X25 | B13: =SUMIFS(Reproting_ERPALIN!S:S,Reproting_ERPALIN!B:B,'Classement des produits'!A13,Reproting_ERPALIN!N:N,">"&Parametres_Dates!$B$2,Reproting_ERPALIN!$N:$N,"<="&Parametres_Dates!$B$3) -> 735.17333 | C13: =RANK(B13,$B$2:$B$234) -> 5
... A234: CP-38-40 | B234: =SUMIFS(Reproting_ERPALIN!S:S,Reproting_ERPALIN!B:B,'Classement des produits'!A234,Reproting_ERPALIN!N:N,">"&Parametres_Dates!$B$2,Reproting_ERPALIN!$N:$N,"<="&Parametres_Dates!$B$3) -> 26.93 | C234: =RANK(B234,$B$2:$B$234) -> 154

Sheet Analyses produits
A1: Classement | B1: SKU | C1: CA, incluant transport | D1: Marge brute (€) | E1: Marge brute (%)
A2: 1 | B2: =INDEX('Classement des produits'!A:A,MATCH('Analyses produits'!A2,'Classement des produits'!C:C,0)) -> 1000022654 | C2: =SUMIFS(Reproting_ERPALIN!S:S,Reproting_ERPALIN!B:B,'Analyses produits'!B2,Reproting_ERPALIN!$N:$N,">"&Parametres_Dates!$B$2,Reproting_ERPALIN!$N:$N,"<="&Parametres_Dates!$B$3) -> 2219.89 | D2: =SUMIFS(Reproting_ERPALIN!AK:AK,Reproting_ERPALIN!B:B,'Analyses produits'!B2,Reproting_ERPALIN!$N:$N,">"&Parametres_Dates!$B$2,Reproting_ERPALIN!$N:$N,"<="&Parametres_Dates!$B$3) -> 474.32833 | E2: =IFERROR(D2/C2,"n.a") -> 0.213672
A3: =A2+1 -> 2 | B3: =INDEX('Classement des produits'!A:A,MATCH('Analyses produits'!A3,'Classement des produits'!C:C,0)) -> IN-U40-1-BL | C3: =SUMIFS(Reproting_ERPALIN!S:S,Reproting_ERPALIN!B:B,'Analyses produits'!B3,Reproting_ERPALIN!$N:$N,">"&Parametres_Dates!$B$2,Reproting_ERPALIN!$N:$N,"<="&Parametres_Dates!$B$3) -> 1426.97 | D3: =SUMIFS(Reproting_ERPALIN!AK:AK,Reproting_ERPALIN!B:B,'Analyses produits'!B3,Reproting_ERPALIN!$N:$N,">"&Parametres_Dates!$B$2,Reproting_ERPALIN!$N:$N,"<="&Parametres_Dates!$B$3) -> 799.71667 | E3: =IFERROR(D3/C3,"n.a") -> 0.56042991
A4: =A3+1 -> 3 | B4: =INDEX('Classement des produits'!A:A,MATCH('Analyses produits'!A4,'Classement des produits'!C:C,0)) -> IN-07X30 | C4: =SUMIFS(Reproting_ERPALIN!S:S,Reproting_ERPALIN!B:B,'Analyses produits'!B4,Reproting_ERPALIN!$N:$N,">"&Parametres_Dates!$B$2,Reproting_ERPALIN!$N:$N,"<="&Parametres_Dates!$B$3) -> 826.07457 | D4: =SUMIFS(Reproting_ERPALIN!AK:AK,Reproting_ERPALIN!B:B,'Analyses produits'!B4,Reproting_ERPALIN!$N:$N,">"&Parametres_Dates!$B$2,Reproting_ERPALIN!$N:$N,"<="&Parametres_Dates!$B$3) -> 388.3696 | E4: =IFERROR(D4/C4,"n.a") -> 0.47013867
A5: =A4+1 -> 4 | B5: =INDEX('Classement des produits'!A:A,MATCH('Analyses produits'!A5,'Classement des produits'!C:C,0)) -> IN-05X40 | C5: =SUMIFS(Reproting_ERPALIN!S:S,Reproting_ERPALIN!B:B,'Analyses produits'!B5,Reproting_ERPALIN!$N:$N,">"&Parametres_Dates!$B$2,Reproting_ERPALIN!$N:$N,"<="&Parametres_Dates!$B$3) -> 799.40833 | D5: =SUMIFS(Reproting_ERPALIN!AK:AK,Reproting_ERPALIN!B:B,'Analyses produits'!B5,Reproting_ERPALIN!$N:$N,">"&Parametres_Dates!$B$2,Reproting_ERPALIN!$N:$N,"<="&Parametres_Dates!$B$3) -> 376.6375 | E5: =IFERROR(D5/C5,"n.a") -> 0.47114533
A6: =A5+1 -> 5 | B6: =INDEX('Classement des produits'!A:A,MATCH('Analyses produits'!A6,'Classement des produits'!C:C,0)) -> IN-08X25 | C6: =SUMIFS(Reproting_ERPALIN!S:S,Reproting_ERPALIN!B:B,'Analyses produits'!B6,Reproting_ERPALIN!$N:$N,">"&Parametres_Dates!$B$2,Reproting_ERPALIN!$N:$N,"<="&Parametres_Dates!$B$3) -> 735.17333 | D6: =SUMIFS(Reproting_ERPALIN!AK:AK,Reproting_ERPALIN!B:B,'Analyses produits'!B6,Reproting_ERPALIN!$N:$N,">"&Parametres_Dates!$B$2,Reproting_ERPALIN!$N:$N,"<="&Parametres_Dates!$B$3) -> 318.43222 | E6: =IFERROR(D6/C6,"n.a") -> 0.43313897
A7: =A6+1 -> 6 | B7: =INDEX('Classement des produits'!A:A,MATCH('Analyses produits'!A7,'Classement des produits'!C:C,0)) -> 1000021324 | C7: =SUMIFS(Reproting_ERPALIN!S:S,Reproting_ERPALIN!B:B,'Analyses produits'!B7,Reproting_ERPALIN!$N:$N,">"&Parametres_Dates!$B$2,Reproting_ERPALIN!$N:$N,"<="&Parametres_Dates!$B$3) -> 538.28 | D7: =SUMIFS(Reproting_ERPALIN!AK:AK,Reproting_ERPALIN!B:B,'Analyses produits'!B7,Reproting_ERPALIN!$N:$N,">"&Parametres_Dates!$B$2,Reproting_ERPALIN!$N:$N,"<="&Parametres_Dates!$B$3) -> 42.706667 | E7: =IFERROR(D7/C7,"n.a") -> 0.07933913
A8: =A7+1 -> 7 | B8: =INDEX('Classement des produits'!A:A,MATCH('Analyses produits'!A8,'Classement des produits'!C:C,0)) -> 1000021327 | C8: =SUMIFS(Reproting_ERPALIN!S:S,Reproting_ERPALIN!B:B,'Analyses produits'!B8,Reproting_ERPALIN!$N:$N,">"&Parametres_Dates!$B$2,Reproting_ERPALIN!$N:$N,"<="&Parametres_Dates!$B$3) -> 531.2 | D8: =SUMIFS(Reproting_ERPALIN!AK:AK,Reproting_ERPALIN!B:B,'Analyses produits'!B8,Reproting_ERPALIN!$N:$N,">"&Parametres_Dates!$B$2,Reproting_ERPALIN!$N:$N,"<="&Parametres_Dates!$B$3) -> 78.756667 | E8: =IFERROR(D8/C8,"n.a") -> 0.1482618
A9: =A8+1 -> 8 | B9: =INDEX('Classement des produits'!A:A,MATCH('Analyses produits'!A9,'Classement des produits'!C:C,0)) -> IN-U100-1-BL | C9: =SUMIFS(Reproting_ERPALIN!S:S,Reproting_ERPALIN!B:B,'Analyses produits'!B9,Reproting_ERPALIN!$N:$N,">"&Parametres_Dates!$B$2,Reproting_ERPALIN!$N:$N,"<="&Parametres_Dates!$B$3) -> 529.895 | D9: =SUMIFS(Reproting_ERPALIN!AK:AK,Reproting_ERPALIN!B:B,'Analyses produits'!B9,Reproting_ERPALIN!$N:$N,">"&Parametres_Dates!$B$2,Reproting_ERPALIN!$N:$N,"<="&Parametres_Dates!$B$3) -> 324.15 | E9: =IFERROR(D9/C9,"n.a") -> 0.61172496
A10: =A9+1 -> 9 | B10: =INDEX('Classement des produits'!A:A,MATCH('Analyses produits'!A10,'Classement des produits'!C:C,0)) -> IN-08X50 | C10: =SUMIFS(Reproting_ERPALIN!S:S,Reproting_ERPALIN!B:B,'Analyses produits'!B10,Reproting_ERPALIN!$N:$N,">"&Parametres_Dates!$B$2,Reproting_ERPALIN!$N:$N,"<="&Parametres_Dates!$B$3) -> 512.84333 | D10: =SUMIFS(Reproting_ERPALIN!AK:AK,Reproting_ERPALIN!B:B,'Analyses produits'!B10,Reproting_ERPALIN!$N:$N,">"&Parametres_Dates!$B$2,Reproting_ERPALIN!$N:$N,"<="&Parametres_Dates!$B$3) -> 261.0075 | E10: =IFERROR(D10/C10,"n.a") -> 0.50894198
A11: =A10+1 -> 10 | B11: =INDEX('Classement des produits'!A:A,MATCH('Analyses produits'!A11,'Classement des produits'!C:C,0)) -> CH03010LL | C11: =SUMIFS(Reproting_ERPALIN!S:S,Reproting_ERPALIN!B:B,'Analyses produits'!B11,Reproting_ERPALIN!$N:$N,">"&Parametres_Dates!$B$2,Reproting_ERPALIN!$N:$N,"<="&Parametres_Dates!$B$3) -> 394.73333 | D11: =SUMIFS(Reproting_ERPALIN!AK:AK,Reproting_ERPALIN!B:B,'Analyses produits'!B11,Reproting_ERPALIN!$N:$N,">"&Parametres_Dates!$B$2,Reproting_ERPALIN!$N:$N,"<="&Parametres_Dates!$B$3) -> 91.720833 | E11: =IFERROR(D11/C11,"n.a") -> 0.23236151
A12: =A11+1 -> 11 | B12: =INDEX('Classement des produits'!A:A,MATCH('Analyses produits'!A12,'Classement des produits'!C:C,0)) -> 002ML-3CZ-SN | C12: =SUMIFS(Reproting_ERPALIN!S:S,Reproting_ERPALIN!B:B,'Analyses produits'!B12,Reproting_ERPALIN!$N:$N,">"&Parametres_Dates!$B$2,Reproting_ERPALIN!$N:$N,"<="&Parametres_Dates!$B$3) -> 376.84833 | D12: =SUMIFS(Reproting_ERPALIN!AK:AK,Reproting_ERPALIN!B:B,'Analyses produits'!B12,Reproting_ERPALIN!$N:$N,">"&Parametres_Dates!$B$2,Reproting_ERPALIN!$N:$N,"<="&Parametres_Dates!$B$3) -> 123.35056 | E12: =IFERROR(D12/C12,"n.a") -> 0.32732148
A13: =A12+1 -> 12 | B13: =INDEX('Classement des produits'!A:A,MATCH('Analyses produits'!A13,'Classement des produits'!C:C,0)) -> 32 820 00 | C13: =SUMIFS(Reproting_ERPALIN!S:S,Reproting_ERPALIN!B:B,'Analyses produits'!B13,Reproting_ERPALIN!$N:$N,">"&Parametres_Dates!$B$2,Reproting_ERPALIN!$N:$N,"<="&Parametres_Dates!$B$3) -> 355.67 | D13: =SUMIFS(Reproting_ERPALIN!AK:AK,Reproting_ERPALIN!B:B,'Analyses produits'!B13,Reproting_ERPALIN!$N:$N,">"&Parametres_Dates!$B$2,Reproting_ERPALIN!$N:$N,"<="&Parametres_Dates!$B$3) -> 98.903333 | E13: =IFERROR(D13/C13,"n.a") -> 0.27807612
A14: =A13+1 -> 13 | B14: =INDEX('Classement des produits'!A:A,MATCH('Analyses produits'!A14,'Classement des produits'!C:C,0)) -> 5310375210-02 | C14: =SUMIFS(Reproting_ERPALIN!S:S,Reproting_ERPALIN!B:B,'Analyses produits'!B14,Reproting_ERPALIN!$N:$N,">"&Parametres_Dates!$B$2,Reproting_ERPALIN!$N:$N,"<="&Parametres_Dates!$B$3) -> 337.6 | D14: =SUMIFS(Reproting_ERPALIN!AK:AK,Reproting_ERPALIN!B:B,'Analyses produits'!B14,Reproting_ERPALIN!$N:$N,">"&Parametres_Dates!$B$2,Reproting_ERPALIN!$N:$N,"<="&Parametres_Dates!$B$3) -> 101.55 | E14: =IFERROR(D14/C14,"n.a") -> 0.30079976
... A2002: =A2001+1 -> 2001 | B2002: =INDEX('Classement des produits'!A:A,MATCH('Analyses produits'!A2002,'Classement des produits'!C:C,0)) -> #N/A | C2002: =SUMIFS(Reproting_ERPALIN!S:S,Reproting_ERPALIN!B:B,'Analyses produits'!B2002,Reproting_ERPALIN!$N:$N,">"&Parametres_Dates!$B$2,Reproting_ERPALIN!$N:$N,"<="&Parametres_Dates!$B$3) -> 0 | D2002: =SUMIFS(Reproting_ERPALIN!AK:AK,Reproting_ERPALIN!B:B,'Analyses produits'!B2002,Reproting_ERPALIN!$N:$N,">"&Parametres_Dates!$B$2,Reproting_ERPALIN!$N:$N,"<="&Parametres_Dates!$B$3) -> 0 | E2002: =IFERROR(D2002/C2002,"n.a") -> n.a
